Workbook

Sheet 00_Lecture
A1: TAQADDUM — Référentiel de 43 KPI (version recentrée)
A3: Version | B3: v1 — 12/10/2026 — remplace le classeur « 55 KPI » (voir feuille 07_Correspondance).
A4: Source | B4: Fiches projets CNED — situation arrêtée au 30 juin 2025 (51 projets, 6 538,322 Md DA) et critique du classeur précédent.
A5: Principe | B5: 43 KPI répartis en 9 familles (AV, FI, DL, BU, QR, DO, PP, CO, GV). L'acteur concerné est un filtre (colonnes Alimenté_par et Responsable), pas un axe de classement.
A7: IMPORTANCE | B7: Lettre indiquant le rôle du KPI dans le dispositif (colonne D de 01_KPI). Elle est indépendante de la phase de déploiement.
A8: [M] Obligatoire | B8: Indispensable : socle du suivi, à afficher dans toute vue, à produire dès le pilote. 20 KPI.
A9: [A] Avancé | B9: Complémentaire : approfondit l'analyse ; nécessite souvent des données de détail (MO, BET, terrain). 14 KPI.
A10: [S] Stratégique | B10: Décision et pilotage : synthèses et prévisions pour la direction (arbitrage de financement, sort d'un contractant, vue portefeuille). 9 KPI.
A12: PHASE | B12: MVP = calculable ou saisissable dès le pilote. V2 = après le pilote (saisie MO, BET ou terrain). Vision = hors pilote, aucune donnée disponible dans les fiches CNED.
A13: CALCULABILITÉ | B13: Évaluée par rapport au PDF des fiches CNED : « Calculable sur fiches CNED », « Partiel (extraction texte) », « Saisie requise », « Calculable par la plateforme ».
A15: RÈGLES COMMUNES
A16: Projet actif | B16: Projet ni achevé ni réceptionné. Sur le PDF : 46 projets (38 en cours + 8 en voie d'achèvement).
A17: Deux délais | B17: Le délai initial et le délai en vigueur (après avenants) sont toujours conservés ; la consommation du délai n'est jamais plafonnée à 100 %.
A18: AE de référence | B18: AE actuelle approuvée. L'AE initiale est ajustée des transferts de maîtrise d'ouvrage ou de périmètre. L'AE déléguée est distinguée de l'AE totale.
A19: TAP consolidé | B19: Avancement valorisé de tous les marchés du projet, y compris marchés résiliés et marchés de parachèvement. Les avances forfaitaires sont comptées à part.
A20: Seuils | B20: Numériques (colonnes K et L) : Vert si « plus haut = mieux » ≥ Seuil_Vert ; Orange si ≥ Seuil_Rouge ; Rouge sinon. Pour « plus bas = mieux » : Vert ≤ Seuil_Vert ; Orange ≤ Seuil_Rouge ; Rouge au-delà. « Écart absolu » : même règle sur la valeur absolue. Les bornes sont incluses côté meilleur niveau. Les règles spéciales et KPI d'information n'ont pas de seuil numérique.
A21: ⚠ Seuils provisoires | B21: Les seuils sont des propositions TAQADDUM, ni officiels CNED ni validés. À recalibrer sur 12–24 mois d'historique. Les pondérations de CO1 et CO6 sont également provisoires et à valider en équipe.
A22: Langage | B22: Les acronymes techniques (EVM, CPI, SPI) ne sont pas exposés aux utilisateurs non spécialistes ; les définitions de la colonne G sont rédigées en langage courant.
A24: FEUILLES | B24: 01_KPI : référentiel complet · 02_Regles_Alertes : 17 règles d'alerte reliées aux KPI · 03_Matrice_Roles : qui voit quoi (R/S/V) · 04_Vue_Role : vue personnalisée par rôle (liste déroulante) · 05_Synthese : comptages par famille, importance, phase · 06_Simulateur : test des seuils (formules) · 07_Correspondance : devenir des 55 anciens KPI · 08_Glossaire · 09_Roles_Interfaces : implémentation de chaque rôle dans chaque interface (mode, KPI R/S/V, alertes D/I).
A26: RÔLES | B26: 6 rôles : Direction CNED, CNED/PMO, Maître d'ouvrage, Bureau d'études, Contractant, Contrôleur budgétaire. Droits : R = responsable, S = alimente, V = consulte. Le contractant ne voit que ses propres marchés et jamais les scores d'autres contractants.

Sheet 01_KPI
A1: KPI_ID | B1: Famille | C1: Nom_KPI | D1: Importance | E1: Phase | F1: Calculabilité | G1: Définition | H1: Formule | I1: Unité | J1: Sens | K1: Seuil_Vert | L1: Seuil_Rouge | M1: Vert | N1: Orange | O1: Rouge | P1: Alimenté_par | Q1: Responsable | R1: Fréquence_cible | S1: Tables_sources | T1: Justification_importance
A2: AV1 | B2: AV – Avancement physique | C2: Avancement physique consolidé | D2: [M] | E2: MVP | F2: Partiel | G2: Part des travaux réellement exécutés sur l'ensemble du projet, tous marchés confondus (y compris marchés résiliés et de parachèvement). | H2: Valeur des travaux réalisés ÷ coût total estimé du projet × 100 | I2: % | J2: Information | M2: Information | N2: — | O2: Information | P2: Fiche CNED / MO | Q2: MO | R2: Mensuelle | S2: Projets; Marches; Avancement_Historique | T2: Socle de tout le suivi : sans lui, aucun autre KPI d'avancement n'a de sens.
A3: AV2 | B3: AV – Avancement physique | C3: Indice d'avancement | D3: [M] | E3: MVP | F3: Calculable sur fiches CNED | G3: Compare l'avancement physique au temps déjà consommé ; 1 = projet dans le rythme. | H3: TAP consolidé ÷ % du délai en vigueur consommé | I3: ratio | J3: Plus haut = mieux | K3: 0.9 | L3: 0.7 | M3: ≥ 0.9 ratio | N3: de 0.7 à < 0.9 ratio | O3: < 0.7 ratio | P3: Plateforme | Q3: CNED / PMO | R3: Mensuelle | S3: Projets; Marches | T3: KPI central de détection du retard ; remplace cinq anciens KPI d'avancement absolu.
A4: AV3 | B4: AV – Avancement physique | C4: Cadence récente | D4: [A] | E4: V2 | F4: Saisie requise | G4: Vitesse d'avancement des trois derniers mois comparée à celle nécessaire pour finir dans le délai. | H4: ΔTAP des 3 derniers mois ÷ ΔTAP requis pour finir dans le délai en vigueur | I4: ratio | J4: Plus haut = mieux | K4: 0.9 | L4: 0.7 | M4: ≥ 0.9 ratio | N4: de 0.7 à < 0.9 ratio | O4: < 0.7 ratio | P4: MO / BET | Q4: MO | R4: Mensuelle | S4: Avancement_Historique | T4: Exige un historique mensuel ; utile pour anticiper, pas indispensable au pilote.
A5: AV4 | B5: AV – Avancement physique | C5: Part non contractualisée | D5: [A] | E5: MVP | F5: Partiel (extraction texte) | G5: Part du reste à réaliser pour laquelle aucun marché n'est notifié (lots non lancés, appels d'offres infructueux). | H5: Coût du reste à réaliser sans marché notifié ÷ coût du reste à réaliser × 100 | I5: % | J5: Plus bas = mieux | K5: 10 | L5: 30 | M5: ≤ 10 % | N5: > 10 à 30 % | O5: > 30 % | P5: MO | Q5: MO | R5: Mensuelle | S5: Marches; Projets | T5: Distingue lots non lancés et travaux arrêtés ; affine le diagnostic.
A6: AV5 | B6: AV – Avancement physique | C6: Mise en service fonctionnelle | D6: [S] | E6: MVP | F6: Partiel (extraction texte) | G6: Part des ouvrages mis en service qui fonctionnent pleinement (sans réserve ni lot système, signalisation ou énergie en retard). | H6: Ouvrages mis en service sans réserve ni lot système en retard ÷ ouvrages mis en service × 100 | I6: % | J6: Plus haut = mieux | K6: 90 | L6: 60 | M6: ≥ 90 % | N6: de 60 à < 90 % | O6: < 60 % | P6: CNED / MO | Q6: CNED | R6: Mensuelle | S6: Projets; Marches; Receptions (à créer) | T6: Mesure le service réellement rendu, pas seulement l'avancement des travaux.
A7: FI1 | B7: FI – Finance | C7: Écart physique–financier | D7: [M] | E7: MVP | F7: Calculable sur fiches CNED | G7: Écart entre avancement physique et consommation financière des travaux, hors avances. Positif : retard de paiement ; négatif : paiement en avance du réalisé. | H7: TAP − taux financier travaux hors avances (en points) | I7: pts | J7: Écart absolu | K7: 5 | L7: 10 | M7: |écart| ≤ 5 pts | N7: |écart| > 5 à 10 pts | O7: |écart| > 10 pts | P7: MO / Finance | Q7: MO | R7: Mensuelle | S7: Projets; Marches; Situations_Facturations | T7: Détecte à la fois les retards de paiement et les paiements non adossés à du réalisé.
A8: FI2 | B8: FI – Finance | C8: Couverture du reste à faire | D8: [S] | E8: V2 | F8: Saisie requise | G8: Capacité des ressources financières restantes à couvrir ce qu'il reste à payer, avenants en préparation compris. | H8: (AE actuelle − paiements) ÷ reste à faire estimé × 100 | I8: % | J8: Plus haut = mieux | K8: 100 | L8: 90 | M8: ≥ 100 % | N8: de 90 à < 100 % | O8: < 90 % | P8: MO / Finance | Q8: MO / Finance | R8: Mensuelle | S8: Projets; Reevaluations_AE; AE_Operations (à créer) | T8: Soutient l'arbitrage de financement ; remplace cinq KPI redondants ou contradictoires.
A9: FI3 | B9: FI – Finance | C9: Couverture des crédits de paiement | D9: [S] | E9: V2 | F9: Saisie requise | G9: Les crédits de paiement de l'exercice couvrent-ils les paiements prévus ? (insuffisance des CP : contrainte récurrente.) | H9: CP inscrits de l'exercice ÷ paiements prévus de l'exercice × 100 | I9: % | J9: Plus haut = mieux | K9: 100 | L9: 80 | M9: ≥ 100 % | N9: de 80 à < 100 % | O9: < 80 % | P9: Finance | Q9: Contrôleur budgétaire | R9: Mensuelle | S9: Credits_Paiement (à créer); Planning | T9: Les CP étaient absents de l'ancien modèle alors que le PDF les cite comme contrainte.
A10: FI4 | B10: FI – Finance | C10: Dérive d'AE ajustée | D10: [M] | E10: MVP | F10: Calculable sur fiches CNED | G10: Augmentation de l'AE par rapport à l'AE initiale, après neutralisation des transferts de maîtrise d'ouvrage ou de périmètre. | H10: (AE actuelle − AE initiale ajustée) ÷ AE initiale ajustée × 100 | I10: % | J10: Plus bas = mieux | K10: 20 | L10: 60 | M10: ≤ 20 % | N10: > 20 à 60 % | O10: > 60 % | P10: Fiche CNED | Q10: Contrôleur budgétaire | R10: Mensuelle | S10: Projets; Reevaluations_AE; AE_Operations (à créer) | T10: Mesure du dérapage budgétaire ; remplace trois KPI identiques. Seuils provisoires calés sur le portefeuille.
A11: FI5 | B11: FI – Finance | C11: Réévaluations d'AE en attente | D11: [M] | E11: MVP | F11: Partiel (extraction texte) | G11: Ancienneté de la plus ancienne réévaluation d'AE non encore approuvée ; le montant en attente est affiché à côté. | H11: Date de référence − date de la plus ancienne demande non approuvée (jours) | I11: j | J11: Plus bas = mieux | K11: 60 | L11: 120 | M11: ≤ 60 j | N11: > 60 à 120 j | O11: > 120 j | P11: Fiche CNED | Q11: Contrôleur budgétaire / CNED | R11: Mensuelle | S11: Reevaluations_AE | T11: Les notifications dépendent d'une approbation en réunion de Gouvernement ou Conseil des Ministres : goulot majeur.
A12: FI6 | B12: FI – Finance | C12: Retard de paiement des situations | D12: [A] | E12: V2 | F12: Saisie requise | G12: Ancienneté médiane des situations de travaux reçues mais non payées. | H12: Médiane (date de référence − date de réception) des situations non payées (jours) | I12: j | J12: Plus bas = mieux | K12: 30 | L12: 60 | M12: ≤ 30 j | N12: > 30 à 60 j | O12: > 60 j | P12: MO / Finance | Q12: MO / Finance | R12: Mensuelle | S12: Situations_Facturations | T12: Cause documentée de démobilisation des entreprises ; données hors fiches CNED.
A13: FI7 | B13: FI – Finance | C13: Encours de situations | D13: [A] | E13: V2 | F13: Saisie requise | G13: Poids des situations reçues mais non payées par rapport au montant du marché. | H13: Σ situations reçues non payées ÷ montant du marché × 100 | I13: % | J13: Plus bas = mieux | K13: 5 | L13: 15 | M13: ≤ 5 % | N13: > 5 à 15 % | O13: > 15 % | P13: Contrôleur budgétaire | Q13: Contrôleur budgétaire | R13: Mensuelle | S13: Situations_Facturations; Marches | T13: Complète FI6 en montant ; données hors fiches CNED.
A14: DL1 | B14: DL – Délais | C14: Consommation du délai en vigueur | D14: [M] | E14: MVP | F14: Calculable sur fiches CNED | G14: Part du délai contractuel en vigueur (avenants inclus) déjà écoulée ; non plafonnée à 100 %. | H14: Jours écoulés depuis l'ODS de démarrage ÷ délai en vigueur × 100 | I14: % | J14: Plus bas = mieux | K14: 90 | L14: 100 | M14: ≤ 90 % | N14: > 90 à 100 % | O14: > 100 % | P14: Fiche CNED | Q14: MO | R14: Mensuelle | S14: Marches; ODS | T14: Base du suivi des délais ; indispensable à AV2.
... A24: QR4 | B24: QR – Blocages, qualité, risques | C24: Temps perdu à l'arrêt | D24: [M] | E24: MVP | F24: Partiel (extraction texte) | G24: Part du temps écoulé pendant laquelle le chantier est arrêté (ODS d'arrêt ou arrêt de fait). | H24: Jours d'arrêt ÷ jours écoulés × 100 | I24: % | J24: Plus bas = mieux | K24: 5 | L24: 15 | M24: ≤ 5 % | N24: > 5 à 15 % | O24: > 15 % | P24: MO | Q24: MO | R24: Mensuelle | S24: ODS; Blocages_Institutionnels | T24: Sépare « travaux arrêtés » et « lots non lancés » : distinction clé du portefeuille.
A25: QR5 | B25: QR – Blocages, qualité, risques | C25: Aléas non prévus ouverts | D25: [A] | E25: V2 | F25: Partiel (extraction texte) | G25: Événements imprévus ouverts (glissement de terrain, inondation, géologie). | H25: Nombre d'aléas ouverts et état de la solution | I25: nombre | J25: Règle spéciale | M25: 0 aléa ouvert | N25: ≥ 1 aléa avec solution arrêtée | O25: ≥ 1 aléa sans solution arrêtée | P25: MO / BET | Q25: MO | R25: Mensuelle | S25: Blocages_Institutionnels; Taches_Critiques | T25: Cas particuliers (ex. glissement) ; renforce l'analyse sans être indispensable.
A26: QR6 | B26: QR – Blocages, qualité, risques | C26: Modification de consistance en cours | D26: [A] | E26: V2 | F26: Saisie requise | G26: Indique si la consistance du projet est en cours de modification (signe de maturation insuffisante). | H26: Oui / Non | I26: oui/non | J26: Règle spéciale | M26: Non | N26: — | O26: Oui | P26: BET / MO | Q26: BET / MO | R26: Mensuelle | S26: Projets; Avenants | T26: Drapeau de maturation ; utile surtout en revue technique.
A27: QR7 | B27: QR – Blocages, qualité, risques | C27: Non-conformité critique la plus ancienne | D27: [A] | E27: V2 | F27: Saisie requise | G27: Ancienneté de la non-conformité critique ouverte la plus ancienne. | H27: Date de référence − date de découverte de la NC critique ouverte la plus ancienne (jours) | I27: j | J27: Plus bas = mieux | K27: 15 | L27: 30 | M27: ≤ 15 j | N27: > 15 à 30 j | O27: > 30 j | P27: BET | Q27: BET | R27: Mensuelle | S27: Non_Conformites_BET | T27: Registre de NC absent des fiches CNED ; saisie BET nécessaire.
A28: QR8 | B28: QR – Blocages, qualité, risques | C28: Incidents HSE graves | D28: [A] | E28: Vision | F28: Saisie requise | G28: Nombre d'incidents de sécurité graves sur 12 mois. | H28: Nombre d'incidents graves sur 12 mois | I28: nombre | J28: Règle spéciale | M28: 0 | N28: — | O28: ≥ 1 | P28: BET / HSE | Q28: BET / HSE | R28: Mensuelle + immédiate | S28: HSE_Incidents | T28: Hors périmètre du pilote : aucune donnée dans les fiches CNED.
A29: DO1 | B29: DO – Fiabilité des données | C29: Fraîcheur des données | D29: [M] | E29: MVP | F29: Calculable par la plateforme | G29: Âge de la dernière mise à jour d'un projet comparé à la périodicité attendue. | H29: Âge de la dernière mise à jour ÷ périodicité attendue | I29: ratio | J29: Plus bas = mieux | K29: 1 | L29: 2 | M29: ≤ 1 ratio | N29: > 1 à 2 ratio | O29: > 2 ratio | P29: Plateforme | Q29: PMO | R29: Mensuelle | S29: KPI_Valeurs; Projets | T29: Sans données fraîches, tous les autres KPI sont trompeurs.
A30: DO2 | B30: DO – Fiabilité des données | C30: Complétude | D30: [M] | E30: MVP | F30: Calculable par la plateforme | G30: Part des champs obligatoires renseignés. | H30: Champs obligatoires renseignés ÷ champs requis × 100 | I30: % | J30: Plus haut = mieux | K30: 90 | L30: 70 | M30: ≥ 90 % | N30: de 70 à < 90 % | O30: < 70 % | P30: Plateforme | Q30: PMO | R30: Mensuelle | S30: Toutes tables | T30: Rend visible ce qui manque plutôt que de le masquer.
A31: DO3 | B31: DO – Fiabilité des données | C31: Cohérence | D31: [M] | E31: MVP | F31: Calculable par la plateforme | G31: Part des projets présentant au moins une anomalie détectée automatiquement (TAP > 100 %, paiements > engagements, dates incohérentes). | H31: Projets avec ≥ 1 anomalie ÷ projets × 100 | I31: % | J31: Plus bas = mieux | K31: 5 | L31: 20 | M31: ≤ 5 % | N31: > 5 à 20 % | O31: > 20 % | P31: Plateforme | Q31: PMO | R31: Mensuelle | S31: Projets; Marches | T31: Contrôle de qualité minimal avant toute présentation au CNED.
A32: PP1 | B32: PP – Terrain (planification fiable) | C32: Fiabilité du planning hebdomadaire | D32: [A] | E32: V2 | F32: Saisie requise | G32: Part des tâches planifiées de la semaine réellement terminées (PPC). | H32: Tâches terminées ÷ tâches planifiées × 100 | I32: % | J32: Plus haut = mieux | K32: 80 | L32: 60 | M32: ≥ 80 % | N32: de 60 à < 80 % | O32: < 60 % | P32: Terrain / entreprise | Q32: MO | R32: Hebdomadaire | S32: Taches_Critiques; Planning | T32: Cœur de la logique terrain, mais saisie hebdomadaire hors fiches CNED.
A33: PP2 | B33: PP – Terrain (planification fiable) | C33: Mobilisation effective | D33: [A] | E33: V2 | F33: Saisie requise | G33: Moyens (heures, main-d'œuvre, matériel) effectivement mobilisés par rapport au plan. | H33: Moyens effectifs ÷ moyens planifiés × 100 | I33: % | J33: Plus haut = mieux | K33: 90 | L33: 70 | M33: ≥ 90 % | N33: de 70 à < 90 % | O33: < 70 % | P33: Entreprise | Q33: MO | R33: Hebdomadaire | S33: Moyens_Mobilises | T33: La « faible mobilisation des moyens » est citée dans une dizaine de fiches.
A34: PP3 | B34: PP – Terrain (planification fiable) | C34: Causes de non-réalisation externes | D34: [A] | E34: V2 | F34: Saisie requise | G34: Répartition des non-réalisations dues à l'emprise, au paiement, aux matériaux ou aux réseaux. | H34: Non-réalisations d'origine externe par cause ÷ total des non-réalisations | I34: % | J34: Information | M34: Information | N34: — | O34: Information | P34: Terrain | Q34: MO | R34: Hebdomadaire | S34: Taches_Critiques | T34: Pareto des causes : prépare l'escalade vers les bons responsables.
A35: CO1 | B35: CO – Contractants et portefeuille | C35: Santé du contractant (0–100) | D35: [S] | E35: MVP | F35: Partiel (poids à valider) | G35: Note synthétique de fiabilité d'un contractant ou groupement. | H35: 40 % AV2 (plafonné à 1) + 25 % inverse de BU1 + 20 % PP2 + 15 % historique de résiliations ; si PP2 absent, ses 20 % sont redistribués (poids provisoires) | I35: 0–100 | J35: Plus haut = mieux | K35: 75 | L35: 50 | M35: ≥ 75 0–100 | N35: de 50 à < 75 0–100 | O35: < 50 0–100 | P35: CNED / MO | Q35: CNED | R35: Mensuelle | S35: Scoring_Contractants; Groupements (à créer); Marches | T35: Aide à décider de la suite donnée à un contractant ; poids à valider en équipe.
A36: CO2 | B36: CO – Contractants et portefeuille | C36: Concentration par contractant | D36: [S] | E36: V2 | F36: Partiel (groupements à modéliser) | G36: Part de l'AE en cours confiée à un même contractant ou groupement. | H36: AE en cours confiée à un contractant ÷ AE en cours × 100 | I36: % | J36: Plus bas = mieux | K36: 15 | L36: 25 | M36: ≤ 15 % | N36: > 15 à 25 % | O36: > 25 % | P36: CNED | Q36: CNED | R36: Mensuelle | S36: Marches; Groupements (à créer) | T36: Risque systémique ; le portefeuille montre une forte concentration.
A37: CO3 | B37: CO – Contractants et portefeuille | C37: Part en parachèvement après résiliation | D37: [S] | E37: MVP | F37: Partiel (extraction texte) | G37: Part de l'AE des projets actifs dont le marché initial a été résilié. | H37: AE des projets dont le marché initial est résilié ÷ AE des projets actifs × 100 | I37: % | J37: Plus bas = mieux | K37: 5 | L37: 15 | M37: ≤ 5 % | N37: > 5 à 15 % | O37: > 15 % | P37: CNED | Q37: CNED | R37: Mensuelle | S37: Marches; Projets | T37: Mesure l'ampleur des défaillances contractuelles à l'échelle du portefeuille.
A38: CO4 | B38: CO – Contractants et portefeuille | C38: Projets en retard important | D38: [M] | E38: MVP | F38: Calculable sur fiches CNED | G38: Part des projets actifs dont le délai est dépassé et l'avancement insuffisant. | H38: Projets avec DL1 > 100 % et AV2 < 0,90 ÷ projets actifs × 100 | I38: % | J38: Plus bas = mieux | K38: 15 | L38: 35 | M38: ≤ 15 % | N38: > 15 à 35 % | O38: > 35 % | P38: Plateforme | Q38: CNED | R38: Mensuelle | S38: Projets; Marches | T38: Donne une définition opérationnelle à « retard important ».
A39: CO5 | B39: CO – Contractants et portefeuille | C39: Projets à l'arrêt | D39: [M] | E39: MVP | F39: Partiel (extraction texte) | G39: Part des projets actifs à l'arrêt (ODS d'arrêt ou arrêt de fait) depuis plus de 60 jours. | H39: Projets arrêtés > 60 jours ÷ projets actifs × 100 | I39: % | J39: Plus bas = mieux | K39: 5 | L39: 15 | M39: ≤ 5 % | N39: > 5 à 15 % | O39: > 15 % | P39: CNED | Q39: CNED | R39: Mensuelle + immédiate | S39: ODS; Projets | T39: Alerte portefeuille de premier niveau.
A40: CO6 | B40: CO – Contractants et portefeuille | C40: Score de santé du portefeuille | D40: [S] | E40: V2 | F40: Partiel (poids à valider) | G40: Note synthétique de l'état du portefeuille, pondérée par l'AE. | H40: 25 % AV2 + 20 % délais (DL1, DL3) + 20 % finance (FI2, FI6) + 20 % blocages (QR1 à QR4) + 15 % CO1 (pondéré AE ; poids provisoires) | I40: 0–100 | J40: Plus haut = mieux | K40: 75 | L40: 55 | M40: ≥ 75 0–100 | N40: de 55 à < 75 0–100 | O40: < 55 0–100 | P40: Plateforme | Q40: CNED / PMO | R40: Mensuelle | S40: Tous KPI de projet | T40: Vue de pilotage ; ne doit être publiée qu'après validation des poids.
A41: GV1 | B41: GV – Gouvernance | C41: Blocages avec responsable et échéance | D41: [M] | E41: MVP | F41: Saisie requise | G41: Part des blocages ouverts ayant un responsable nommé et une date cible. | H41: Blocages ouverts avec responsable et échéance ÷ blocages ouverts × 100 | I41: % | J41: Plus haut = mieux | K41: 90 | L41: 70 | M41: ≥ 90 % | N41: de 70 à < 90 % | O41: < 70 % | P41: CNED / PMO | Q41: CNED / PMO | R41: Mensuelle | S41: Blocages_Institutionnels | T41: Sans responsable, un blocage ne se débloque pas.
A42: GV2 | B42: GV – Gouvernance | C42: Avenants en attente de visa (CSM) | D42: [M] | E42: MVP | F42: Partiel (extraction texte) | G42: Ancienneté de l'avenant le plus ancien non visé par la Commission sectorielle des marchés ; le nombre est affiché à côté. | H42: Date de référence − date de dépôt de l'avenant non visé le plus ancien (jours) | I42: j | J42: Plus bas = mieux | K42: 60 | L42: 120 | M42: ≤ 60 j | N42: > 60 à 120 j | O42: > 120 j | P42: MO / CNED | Q42: MO / CNED | R42: Mensuelle | S42: Avenants | T42: Goulot documenté dans le PDF (visa avec réserves, ajournements).
A43: GV3 | B43: GV – Gouvernance | C43: Arbitrages échus | D43: [A] | E43: V2 | F43: Saisie requise | G43: Part des projets actifs avec un arbitrage ayant dépassé son échéance. | H43: Projets avec arbitrage échu ÷ projets actifs × 100 | I43: % | J43: Plus bas = mieux | K43: 10 | L43: 25 | M43: ≤ 10 % | N43: > 10 à 25 % | O43: > 25 % | P43: CNED | Q43: CNED | R43: Mensuelle | S43: Decisions_Arbitrages | T43: Utile quand le registre de décisions sera alimenté.
A44: GV4 | B44: GV – Gouvernance | C44: Réceptions en attente | D44: [A] | E44: MVP | F44: Partiel (extraction texte) | G44: Part des réceptions provisoires avec réserves non levées depuis plus de 6 mois. | H44: Réceptions avec réserves non levées > 6 mois ÷ réceptions provisoires × 100 | I44: % | J44: Plus bas = mieux | K44: 0 | L44: 25 | M44: ≤ 0 % | N44: > 0 à 25 % | O44: > 25 % | P44: MO | Q44: MO | R44: Mensuelle | S44: Receptions (à créer) | T44: Affine le suivi de clôture ; non bloquant pour le pilote.
A46: Note : Seuil_Vert / Seuil_Rouge en bleu = valeurs saisies (provisoires, à recalibrer). Importance, Phase et Sens sont modifiables par liste déroulante.

Sheet 02_Regles_Alertes
A1: Regle_ID | B1: Nom | C1: Niveau | D1: Importance | E1: Phase | F1: Condition (lisible) | G1: Logique | H1: C1_KPI_ou_champ | I1: C1_Op | J1: C1_Seuil | K1: C2_KPI_ou_champ | L1: C2_Op | M1: C2_Seuil | N1: C3_KPI_ou_champ | O1: C3_Op | P1: C3_Seuil | Q1: Destinataire | R1: Action | S1: Fréquence | T1: Origine | U1: Changement par rapport à l'ancienne règle
A2: AL01 | B2: Avant-coureur d'abandon | C2: ROUGE | D2: [A] | E2: V2 | F2: Retard de paiement > 60 j ET (cadence récente < 0,70 OU mobilisation < 70 %) | G2: C1 ET (C2 OU C3) | H2: FI6 | I2: > | J2: 60 | K2: AV3 | L2: < | M2: 0.7 | N2: PP2 | O2: < | P2: 70 | Q2: MO + CNED | R2: Revue contractuelle immédiate ; plan de continuité | S2: Hebdomadaire | T2: AL01 (modifiée) | U2: Seuil de paiement 180 j → 60 j (aligné sur FI6) ; condition « ODS refusé » (non modélisée) supprimée ; trois ET remplacés par ET + OU pour qu'elle se déclenche avant l'abandon et non après.
A3: AL02 | B3: Emprise bloquée critique | C3: ROUGE | D3: [M] | E3: MVP | F3: Emprise libérée < 50 % ET délai consommé > 60 % ET aucun plan de déblocage validé | G3: C1 ET C2 ET C3 | H3: QR1 | I3: < | J3: 50 | K3: DL1 | L3: > | M3: 60 | N3: Blocage.Plan_Valide | O3: = | P3: Non | Q3: MO + CNED + responsable territorial | R3: Escalade institutionnelle | S3: Mensuelle | T3: AL02 | U3: Conditions inchangées, désormais reliées à QR1 (qui existe maintenant comme KPI).
A4: AL03 | B4: Étranglement financier | C4: ROUGE | D4: [S] | E4: V2 | F4: Couverture du reste à faire < 90 % ET (réévaluation en attente > 120 j OU couverture des CP < 80 %) | G4: C1 ET (C2 OU C3) | H4: FI2 | I4: < | J4: 90 | K4: FI5 | L4: > | M4: 120 | N4: FI3 | O4: < | P4: 80 | Q4: Contrôleur budgétaire + CNED | R4: Arbitrage financement / réévaluation | S4: Mensuelle | T4: AL03 (modifiée) | U4: « Engagement > 95 % » (qui n'est pas un signal de santé) remplacé par la couverture du reste à faire ; ajout des crédits de paiement.
A5: AL04 | B5: Dégradation contractant | C5: ORANGE | D5: [A] | E5: V2 | F5: Baisse de santé du contractant > 10 pts en un mois ET mobilisation < 70 % ET retard de paiement > 60 j | G5: C1 ET C2 ET C3 | H5: CO1 (variation mensuelle) | I5: < | J5: -10 | K5: PP2 | L5: < | M5: 70 | N5: FI6 | O5: > | P5: 60 | Q5: MO | R5: Plan de redressement du contractant | S5: Hebdomadaire | T5: AL04 (modifiée) | U5: ISC, TMM et paiements remplacés par CO1, PP2 et FI6.
A6: AL05 | B6: Déblocage critique qui approche | C6: ORANGE | D6: [A] | E6: V2 | F6: Date de déblocage estimée dans ≤ 60 j ET blocage en cours ET plan non confirmé | G6: C1 ET C2 ET C3 | H6: Blocage.Jours_avant_date_estimee | I6: <= | J6: 60 | K6: Blocage.Statut | L6: = | M6: Ouvert | N6: Blocage.Plan_Confirme | O6: = | P6: Non | Q6: MO + responsable du déblocage | R6: Confirmer les actions et la date cible | S6: Hebdomadaire | T6: AL05 | U6: Inchangée ; s'appuie sur les champs de la table des blocages (pas sur un KPI).
A7: AL06 | B7: Dérive de délai | C7: ROUGE | D7: [M] | E7: MVP | F7: Délai en vigueur dépassé ET indice d'avancement < 0,70 ET projet non achevé | G7: C1 ET C2 ET C3 | H7: DL1 | I7: > | J7: 100 | K7: AV2 | L7: < | M7: 0.7 | N7: Projet.Statut | O7: ≠ | P7: Achevé | Q7: MO + CNED | R7: Plan de rattrapage | S7: Mensuelle | T7: AL06 (modifiée) | U7: « TAP < 90 % » remplacé par AV2 < 0,70 : l'ancienne règle se serait déclenchée sur une bonne quinzaine de fiches (saturation).
A8: AL07 | B8: Sous-performance physique | C8: ORANGE | D8: [A] | E8: V2 | F8: Indice d'avancement < 0,70 sur ≥ 2 périodes ET cadence récente < 0,70 | G8: C1 ET C2 | H8: AV2 (2 périodes) | I8: < | J8: 0.7 | K8: AV3 | L8: < | M8: 0.7 | Q8: MO + contractant | R8: Plan de rattrapage sous 7 jours | S8: Mensuelle | T8: AL07 (modifiée) | U8: Seuils reliés à AV2 et AV3.
A9: AL08 | B9: Dérive d'AE | C9: ROUGE | D9: [M] | E9: MVP | F9: Dérive d'AE ajustée > 60 % ET réévaluation en attente > 60 j | G9: C1 ET C2 | H9: FI4 | I9: > | J9: 60 | K9: FI5 | L9: > | M9: 60 | Q9: Finance + MO | R9: Analyse des causes et sécurisation de l'AE | S9: Mensuelle | T9: AL08 (modifiée) | U9: Seuil 15 % → 60 % (à 15 %, 20 projets sur 24 se déclenchaient) ; condition « impact délai > 60 j » retirée.
A10: AL09 | B10: NC critique persistante | C10: ROUGE | D10: [A] | E10: V2 | F10: NC critique ouverte > 30 j ET action corrective non validée | G10: C1 ET C2 | H10: QR7 | I10: > | J10: 30 | K10: NC.Action_Validee | L10: = | M10: Non | Q10: BET + MO | R10: Action corrective immédiate | S10: Hebdomadaire | T10: AL09 | U10: Inchangée ; reliée à QR7.
A11: AL10 | B11: Responsable de blocage absent | C11: ORANGE | D11: [M] | E11: MVP | F11: Blocage ouvert > 30 j ET responsable vide | G11: C1 ET C2 | H11: Blocage.Age_jours | I11: > | J11: 30 | K11: Blocage.Responsable | L11: = | M11: Vide | Q11: CNED / PMO | R11: Nommer un responsable et une date cible | S11: Mensuelle | T11: AL10 | U11: Inchangée ; alimente GV1.
A12: AL11 | B12: Paiement anormalement lent | C12: ROUGE | D12: [A] | E12: V2 | F12: Retard de paiement des situations > 60 j OU situation individuelle > 90 j | G12: C1 OU C2 | H12: FI6 | I12: > | J12: 60 | K12: Situation.Age_jours | L12: > | M12: 90 | Q12: Finance + MO | R12: Identifier la cause et fixer une date de paiement | S12: Hebdomadaire | T12: AL11 (modifiée) | U12: Niveau ORANGE → ROUGE pour être cohérent avec le seuil Rouge de FI6 (> 60 j).
A13: AL12 | B13: Maturation critique | C13: ORANGE | D13: [A] | E13: V2 | F13: Modification de consistance en cours ET avancement < 50 % ET avenant en préparation | G13: C1 ET C2 ET C3 | H13: QR6 | I13: = | J13: Oui | K13: AV1 | L13: < | M13: 50 | N13: Avenant.Statut | O13: = | P13: En préparation | Q13: MO + BET | R13: Revue technique du périmètre | S13: Mensuelle | T13: AL12 (modifiée) | U13: Reliée à QR6 et AV1.
A14: AL13 | B14: Dérive de délai extrême | C14: ORANGE | D14: [M] | E14: MVP | F14: Délai en vigueur > 2 × le délai initial ET délai en vigueur dépassé | G14: C1 ET C2 | H14: DL2 | I14: > | J14: 2 | K14: DL1 | L14: > | M14: 100 | Q14: CNED | R14: Revue contractuelle : poursuite, résiliation ou réengagement | S14: Mensuelle | T14: Nouvelle | U14: Couvre la pathologie n°1 du portefeuille (ex. 24 mois devenus 110), sans règle dédiée auparavant.
A15: AL14 | B15: Avenant bloqué au visa | C15: ORANGE | D15: [M] | E15: MVP | F15: Avenant non visé par la CSM depuis plus de 120 j | G15: C1 | H15: GV2 | I15: > | J15: 120 | Q15: MO + CNED | R15: Relancer la CSM ; lever les réserves | S15: Mensuelle | T15: Nouvelle | U15: Goulot très présent dans les fiches (visa avec réserves, ajournements).
A16: AL15 | B16: Arrêt prolongé | C16: ROUGE | D16: [M] | E16: MVP | F16: Temps perdu à l'arrêt > 15 % OU arrêt en cours depuis > 60 j | G16: C1 OU C2 | H16: QR4 | I16: > | J16: 15 | K16: Projet.Arret_en_cours_jours | L16: > | M16: 60 | Q16: CNED + MO | R16: Plan de reprise ; sécuriser les travaux déjà réalisés | S16: Mensuelle | T16: Nouvelle | U16: Les projets à l'arrêt (Skikda, Ténès, Guelma…) n'avaient aucune règle dédiée.
A17: AL16 | B17: Données peu fiables | C17: ORANGE | D17: [M] | E17: MVP | F17: Fraîcheur > 2 OU cohérence : anomalies > 20 % des projets | G17: C1 OU C2 | H17: DO1 | I17: > | J17: 2 | K17: DO3 | L17: > | M17: 20 | Q17: PMO | R17: Corriger / valider les données avant diffusion des KPI | S17: Mensuelle | T17: Nouvelle | U17: Empêche de tirer des conclusions sur des KPI calculés sur des données périmées ou incohérentes.
A18: AL17 | B18: Blocage ancien | C18: ORANGE | D18: [M] | E18: MVP | F18: Âge médian des blocages ouverts > 90 j | G18: C1 | H18: QR3 | I18: > | J18: 90 | Q18: CNED / PMO | R18: Escalade au niveau décisionnel | S18: Mensuelle | T18: Nouvelle | U18: Complète AL10 : AL10 vise l'absence de responsable, AL17 la stagnation.
A20: Notes :
A21: • Les seuils des conditions reprennent les seuils Rouge/Orange de 01_KPI (provisoires, à recalibrer). Un champ de type « Objet.Champ » (ex. Blocage.Plan_Valide) provient d'une table du modèle de données, pas d'un KPI.
A22: • Importance : [M] = règle utilisable dès le pilote avec les KPI obligatoires ; [A] = règle avancée (données de détail, V2) ; [S] = règle stratégique de décision.
A23: • Une règle ne produit une alerte que si ses KPI ont une Confiance suffisante (voir DO1 à DO3) ; une alerte est toujours une proposition de revue, jamais une action automatique (pas de mise en demeure automatisée).
A24: • Fréquence : mensuelle tant que la source reste le suivi semestriel / mensuel du CNED ; hebdomadaire dès qu'une saisie MO / terrain existe.
A25: • Modèle de données recommandé pour le moteur : Regles_Alertes (Regle_ID, Nom, Niveau, Importance, Logique, C1..C3 = KPI/champ + opérateur + seuil, Destinataire, Action, Fréquence, Version, Actif) et Alertes (Alerte_ID, Regle_ID, Projet_ID, Marche_ID, Date, Valeurs_déclenchantes, Confiance, Statut, Responsable, Date_clôture).

Sheet 03_Matrice_Roles
A1: Qui voit quoi — matrice KPI × rôles et alertes × rôles
A2: R = responsable du KPI (valide et rend compte) · S = alimente la donnée sans en être responsable · V = consulte · vide = ne voit pas. Alertes : D = destinataire (doit agir) · I = informé. Codes modifiables (bleu) ; la feuille 04_Vue_Role se met à jour toute seule.
A3: KPI_ID | B3: Nom_KPI | C3: Importance | D3: Phase | E3: =$M$4 -> Direction CNED (décideur) | F3: =$M$5 -> CNED / PMO (analyste) | G3: =$M$6 -> Maître d'ouvrage (MO) | H3: =$M$7 -> Bureau d'études (BET) / contrôle | I3: =$M$8 -> Contractant (entreprise) | J3: =$M$9 -> Contrôleur budgétaire (Finance) | K3: Rang_vue_rôle | L3: Remarque de périmètre | M3: Rôle | N3: Périmètre de données | O3: Ce que le rôle voit
A4: AV1 | B4: =INDEX('01_KPI'!$C$2:$C$44,MATCH($A4,'01_KPI'!$A$2:$A$44,0)) -> Avancement physique consolidé | C4: =INDEX('01_KPI'!$D$2:$D$44,MATCH($A4,'01_KPI'!$A$2:$A$44,0)) -> [M] | D4: =INDEX('01_KPI'!$E$2:$E$44,MATCH($A4,'01_KPI'!$A$2:$A$44,0)) -> MVP | F4: S | G4: R | H4: V | I4: V | J4: V | K4: =IF(INDEX($E4:$J4,'04_Vue_Role'!$B$4)="","",MAX(K$3:K3)+1) | M4: Direction CNED (décideur) | N4: Portefeuille national (tous les projets) | O4: Synthèse de pilotage : KPI [S] et [M] clés, arbitrage des alertes ROUGE.
A5: AV2 | B5: =INDEX('01_KPI'!$C$2:$C$44,MATCH($A5,'01_KPI'!$A$2:$A$44,0)) -> Indice d'avancement | C5: =INDEX('01_KPI'!$D$2:$D$44,MATCH($A5,'01_KPI'!$A$2:$A$44,0)) -> [M] | D5: =INDEX('01_KPI'!$E$2:$E$44,MATCH($A5,'01_KPI'!$A$2:$A$44,0)) -> MVP | E5: V | F5: R | G5: V | H5: V | I5: V | J5: V | K5: =IF(INDEX($E5:$J5,'04_Vue_Role'!$B$4)="","",MAX(K$3:K4)+1) -> 1 | M5: CNED / PMO (analyste) | N5: Portefeuille national (tous les projets) | O5: Tous les KPI utiles à l'analyse ; responsable de la qualité des données (DO1 à DO3) et des KPI de portefeuille.
A6: AV3 | B6: =INDEX('01_KPI'!$C$2:$C$44,MATCH($A6,'01_KPI'!$A$2:$A$44,0)) -> Cadence récente | C6: =INDEX('01_KPI'!$D$2:$D$44,MATCH($A6,'01_KPI'!$A$2:$A$44,0)) -> [A] | D6: =INDEX('01_KPI'!$E$2:$E$44,MATCH($A6,'01_KPI'!$A$2:$A$44,0)) -> V2 | F6: V | G6: R | H6: S | I6: V | K6: =IF(INDEX($E6:$J6,'04_Vue_Role'!$B$4)="","",MAX(K$3:K5)+1) | M6: Maître d'ouvrage (MO) | N6: Ses projets uniquement | O6: KPI de pilotage de ses projets ; alimente avancement, délais, blocages, emprises.
A7: AV4 | B7: =INDEX('01_KPI'!$C$2:$C$44,MATCH($A7,'01_KPI'!$A$2:$A$44,0)) -> Part non contractualisée | C7: =INDEX('01_KPI'!$D$2:$D$44,MATCH($A7,'01_KPI'!$A$2:$A$44,0)) -> [A] | D7: =INDEX('01_KPI'!$E$2:$E$44,MATCH($A7,'01_KPI'!$A$2:$A$44,0)) -> MVP | F7: V | G7: R | K7: =IF(INDEX($E7:$J7,'04_Vue_Role'!$B$4)="","",MAX(K$3:K6)+1) | M7: Bureau d'études (BET) / contrôle | N7: Projets et marchés qu'il surveille | O7: KPI techniques et qualité ; alimente non-conformités, HSE et consistance.
A8: AV5 | B8: =INDEX('01_KPI'!$C$2:$C$44,MATCH($A8,'01_KPI'!$A$2:$A$44,0)) -> Mise en service fonctionnelle | C8: =INDEX('01_KPI'!$D$2:$D$44,MATCH($A8,'01_KPI'!$A$2:$A$44,0)) -> [S] | D8: =INDEX('01_KPI'!$E$2:$E$44,MATCH($A8,'01_KPI'!$A$2:$A$44,0)) -> MVP | E8: V | F8: R | G8: S | K8: =IF(INDEX($E8:$J8,'04_Vue_Role'!$B$4)="","",MAX(K$3:K7)+1) -> 2 | M8: Contractant (entreprise) | N8: Ses propres marchés uniquement | O8: Sa propre performance et ce qui l'affecte (paiements, emprises, avenants) ; jamais les KPI ni les scores d'autres contractants.
A9: FI1 | B9: =INDEX('01_KPI'!$C$2:$C$44,MATCH($A9,'01_KPI'!$A$2:$A$44,0)) -> Écart physique–financier | C9: =INDEX('01_KPI'!$D$2:$D$44,MATCH($A9,'01_KPI'!$A$2:$A$44,0)) -> [M] | D9: =INDEX('01_KPI'!$E$2:$E$44,MATCH($A9,'01_KPI'!$A$2:$A$44,0)) -> MVP | F9: V | G9: R | I9: V | J9: S | K9: =IF(INDEX($E9:$J9,'04_Vue_Role'!$B$4)="","",MAX(K$3:K8)+1) | M9: Contrôleur budgétaire (Finance) | N9: Projets de son périmètre budgétaire | O9: KPI financiers (AE, CP, situations) et alertes financières.
A10: FI2 | B10: =INDEX('01_KPI'!$C$2:$C$44,MATCH($A10,'01_KPI'!$A$2:$A$44,0)) -> Couverture du reste à faire | C10: =INDEX('01_KPI'!$D$2:$D$44,MATCH($A10,'01_KPI'!$A$2:$A$44,0)) -> [S] | D10: =INDEX('01_KPI'!$E$2:$E$44,MATCH($A10,'01_KPI'!$A$2:$A$44,0)) -> V2 | E10: V | F10: V | G10: R | J10: S | K10: =IF(INDEX($E10:$J10,'04_Vue_Role'!$B$4)="","",MAX(K$3:K9)+1) -> 3
A11: FI3 | B11: =INDEX('01_KPI'!$C$2:$C$44,MATCH($A11,'01_KPI'!$A$2:$A$44,0)) -> Couverture des crédits de paiement | C11: =INDEX('01_KPI'!$D$2:$D$44,MATCH($A11,'01_KPI'!$A$2:$A$44,0)) -> [S] | D11: =INDEX('01_KPI'!$E$2:$E$44,MATCH($A11,'01_KPI'!$A$2:$A$44,0)) -> V2 | E11: V | F11: V | G11: V | J11: R | K11: =IF(INDEX($E11:$J11,'04_Vue_Role'!$B$4)="","",MAX(K$3:K10)+1) -> 4
A12: FI4 | B12: =INDEX('01_KPI'!$C$2:$C$44,MATCH($A12,'01_KPI'!$A$2:$A$44,0)) -> Dérive d'AE ajustée | C12: =INDEX('01_KPI'!$D$2:$D$44,MATCH($A12,'01_KPI'!$A$2:$A$44,0)) -> [M] | D12: =INDEX('01_KPI'!$E$2:$E$44,MATCH($A12,'01_KPI'!$A$2:$A$44,0)) -> MVP | E12: V | F12: V | G12: V | J12: R | K12: =IF(INDEX($E12:$J12,'04_Vue_Role'!$B$4)="","",MAX(K$3:K11)+1) -> 5
A13: FI5 | B13: =INDEX('01_KPI'!$C$2:$C$44,MATCH($A13,'01_KPI'!$A$2:$A$44,0)) -> Réévaluations d'AE en attente | C13: =INDEX('01_KPI'!$D$2:$D$44,MATCH($A13,'01_KPI'!$A$2:$A$44,0)) -> [M] | D13: =INDEX('01_KPI'!$E$2:$E$44,MATCH($A13,'01_KPI'!$A$2:$A$44,0)) -> MVP | E13: V | F13: S | G13: V | J13: R | K13: =IF(INDEX($E13:$J13,'04_Vue_Role'!$B$4)="","",MAX(K$3:K12)+1) -> 6
A14: FI6 | B14: =INDEX('01_KPI'!$C$2:$C$44,MATCH($A14,'01_KPI'!$A$2:$A$44,0)) -> Retard de paiement des situations | C14: =INDEX('01_KPI'!$D$2:$D$44,MATCH($A14,'01_KPI'!$A$2:$A$44,0)) -> [A] | D14: =INDEX('01_KPI'!$E$2:$E$44,MATCH($A14,'01_KPI'!$A$2:$A$44,0)) -> V2 | F14: V | G14: R | I14: V | J14: S | K14: =IF(INDEX($E14:$J14,'04_Vue_Role'!$B$4)="","",MAX(K$3:K13)+1) | L14: Contractant : ses propres situations.
A15: FI7 | B15: =INDEX('01_KPI'!$C$2:$C$44,MATCH($A15,'01_KPI'!$A$2:$A$44,0)) -> Encours de situations | C15: =INDEX('01_KPI'!$D$2:$D$44,MATCH($A15,'01_KPI'!$A$2:$A$44,0)) -> [A] | D15: =INDEX('01_KPI'!$E$2:$E$44,MATCH($A15,'01_KPI'!$A$2:$A$44,0)) -> V2 | F15: V | G15: V | I15: V | J15: R | K15: =IF(INDEX($E15:$J15,'04_Vue_Role'!$B$4)="","",MAX(K$3:K14)+1) | L15: Contractant : ses propres situations.
A16: DL1 | B16: =INDEX('01_KPI'!$C$2:$C$44,MATCH($A16,'01_KPI'!$A$2:$A$44,0)) -> Consommation du délai en vigueur | C16: =INDEX('01_KPI'!$D$2:$D$44,MATCH($A16,'01_KPI'!$A$2:$A$44,0)) -> [M] | D16: =INDEX('01_KPI'!$E$2:$E$44,MATCH($A16,'01_KPI'!$A$2:$A$44,0)) -> MVP | F16: V | G16: R | H16: V | I16: V | J16: V | K16: =IF(INDEX($E16:$J16,'04_Vue_Role'!$B$4)="","",MAX(K$3:K15)+1)
A17: DL2 | B17: =INDEX('01_KPI'!$C$2:$C$44,MATCH($A17,'01_KPI'!$A$2:$A$44,0)) -> Dérive de délai par avenants | C17: =INDEX('01_KPI'!$D$2:$D$44,MATCH($A17,'01_KPI'!$A$2:$A$44,0)) -> [M] | D17: =INDEX('01_KPI'!$E$2:$E$44,MATCH($A17,'01_KPI'!$A$2:$A$44,0)) -> MVP | E17: V | F17: R | G17: V | H17: V | I17: V | J17: V | K17: =IF(INDEX($E17:$J17,'04_Vue_Role'!$B$4)="","",MAX(K$3:K16)+1) -> 7
A18: DL3 | B18: =INDEX('01_KPI'!$C$2:$C$44,MATCH($A18,'01_KPI'!$A$2:$A$44,0)) -> Dépassement de la date contractuelle | C18: =INDEX('01_KPI'!$D$2:$D$44,MATCH($A18,'01_KPI'!$A$2:$A$44,0)) -> [M] | D18: =INDEX('01_KPI'!$E$2:$E$44,MATCH($A18,'01_KPI'!$A$2:$A$44,0)) -> MVP | E18: V | F18: R | G18: V | H18: V | I18: V | J18: V | K18: =IF(INDEX($E18:$J18,'04_Vue_Role'!$B$4)="","",MAX(K$3:K17)+1) -> 8
A19: DL4 | B19: =INDEX('01_KPI'!$C$2:$C$44,MATCH($A19,'01_KPI'!$A$2:$A$44,0)) -> Date d'achèvement prévisionnelle | C19: =INDEX('01_KPI'!$D$2:$D$44,MATCH($A19,'01_KPI'!$A$2:$A$44,0)) -> [S] | D19: =INDEX('01_KPI'!$E$2:$E$44,MATCH($A19,'01_KPI'!$A$2:$A$44,0)) -> V2 | E19: V | F19: V | G19: R | H19: S | I19: V | K19: =IF(INDEX($E19:$J19,'04_Vue_Role'!$B$4)="","",MAX(K$3:K18)+1) -> 9
A20: BU1 | B20: =INDEX('01_KPI'!$C$2:$C$44,MATCH($A20,'01_KPI'!$A$2:$A$44,0)) -> Poids financier des avenants | C20: =INDEX('01_KPI'!$D$2:$D$44,MATCH($A20,'01_KPI'!$A$2:$A$44,0)) -> [M] | D20: =INDEX('01_KPI'!$E$2:$E$44,MATCH($A20,'01_KPI'!$A$2:$A$44,0)) -> MVP | E20: V | F20: R | G20: S | I20: V | J20: V | K20: =IF(INDEX($E20:$J20,'04_Vue_Role'!$B$4)="","",MAX(K$3:K19)+1) -> 10
A21: BU2 | B21: =INDEX('01_KPI'!$C$2:$C$44,MATCH($A21,'01_KPI'!$A$2:$A$44,0)) -> Nombre d'avenants cumulés | C21: =INDEX('01_KPI'!$D$2:$D$44,MATCH($A21,'01_KPI'!$A$2:$A$44,0)) -> [A] | D21: =INDEX('01_KPI'!$E$2:$E$44,MATCH($A21,'01_KPI'!$A$2:$A$44,0)) -> MVP | F21: V | G21: R | H21: V | I21: V | K21: =IF(INDEX($E21:$J21,'04_Vue_Role'!$B$4)="","",MAX(K$3:K20)+1)
A22: BU3 | B22: =INDEX('01_KPI'!$C$2:$C$44,MATCH($A22,'01_KPI'!$A$2:$A$44,0)) -> Coût final prévisionnel | C22: =INDEX('01_KPI'!$D$2:$D$44,MATCH($A22,'01_KPI'!$A$2:$A$44,0)) -> [S] | D22: =INDEX('01_KPI'!$E$2:$E$44,MATCH($A22,'01_KPI'!$A$2:$A$44,0)) -> V2 | E22: V | F22: V | G22: R | H22: S | J22: V | K22: =IF(INDEX($E22:$J22,'04_Vue_Role'!$B$4)="","",MAX(K$3:K21)+1) -> 11
A23: QR1 | B23: =INDEX('01_KPI'!$C$2:$C$44,MATCH($A23,'01_KPI'!$A$2:$A$44,0)) -> Taux de libération des emprises | C23: =INDEX('01_KPI'!$D$2:$D$44,MATCH($A23,'01_KPI'!$A$2:$A$44,0)) -> [M] | D23: =INDEX('01_KPI'!$E$2:$E$44,MATCH($A23,'01_KPI'!$A$2:$A$44,0)) -> MVP | E23: V | F23: V | G23: R | H23: V | I23: V | K23: =IF(INDEX($E23:$J23,'04_Vue_Role'!$B$4)="","",MAX(K$3:K22)+1) -> 12
A24: QR2 | B24: =INDEX('01_KPI'!$C$2:$C$44,MATCH($A24,'01_KPI'!$A$2:$A$44,0)) -> Interférences réseaux traitées | C24: =INDEX('01_KPI'!$D$2:$D$44,MATCH($A24,'01_KPI'!$A$2:$A$44,0)) -> [M] | D24: =INDEX('01_KPI'!$E$2:$E$44,MATCH($A24,'01_KPI'!$A$2:$A$44,0)) -> MVP | F24: V | G24: R | H24: V | I24: V | K24: =IF(INDEX($E24:$J24,'04_Vue_Role'!$B$4)="","",MAX(K$3:K23)+1)
A25: QR3 | B25: =INDEX('01_KPI'!$C$2:$C$44,MATCH($A25,'01_KPI'!$A$2:$A$44,0)) -> Âge des blocages ouverts | C25: =INDEX('01_KPI'!$D$2:$D$44,MATCH($A25,'01_KPI'!$A$2:$A$44,0)) -> [M] | D25: =INDEX('01_KPI'!$E$2:$E$44,MATCH($A25,'01_KPI'!$A$2:$A$44,0)) -> MVP | E25: V | F25: R | G25: V | H25: V | I25: V | K25: =IF(INDEX($E25:$J25,'04_Vue_Role'!$B$4)="","",MAX(K$3:K24)+1) -> 13
A26: QR4 | B26: =INDEX('01_KPI'!$C$2:$C$44,MATCH($A26,'01_KPI'!$A$2:$A$44,0)) -> Temps perdu à l'arrêt | C26: =INDEX('01_KPI'!$D$2:$D$44,MATCH($A26,'01_KPI'!$A$2:$A$44,0)) -> [M] | D26: =INDEX('01_KPI'!$E$2:$E$44,MATCH($A26,'01_KPI'!$A$2:$A$44,0)) -> MVP | E26: V | F26: V | G26: R | H26: V | I26: V | K26: =IF(INDEX($E26:$J26,'04_Vue_Role'!$B$4)="","",MAX(K$3:K25)+1) -> 14
A27: QR5 | B27: =INDEX('01_KPI'!$C$2:$C$44,MATCH($A27,'01_KPI'!$A$2:$A$44,0)) -> Aléas non prévus ouverts | C27: =INDEX('01_KPI'!$D$2:$D$44,MATCH($A27,'01_KPI'!$A$2:$A$44,0)) -> [A] | D27: =INDEX('01_KPI'!$E$2:$E$44,MATCH($A27,'01_KPI'!$A$2:$A$44,0)) -> V2 | F27: V | G27: R | H27: S | I27: V | K27: =IF(INDEX($E27:$J27,'04_Vue_Role'!$B$4)="","",MAX(K$3:K26)+1)
A28: QR6 | B28: =INDEX('01_KPI'!$C$2:$C$44,MATCH($A28,'01_KPI'!$A$2:$A$44,0)) -> Modification de consistance en cours | C28: =INDEX('01_KPI'!$D$2:$D$44,MATCH($A28,'01_KPI'!$A$2:$A$44,0)) -> [A] | D28: =INDEX('01_KPI'!$E$2:$E$44,MATCH($A28,'01_KPI'!$A$2:$A$44,0)) -> V2 | F28: V | G28: S | H28: R | K28: =IF(INDEX($E28:$J28,'04_Vue_Role'!$B$4)="","",MAX(K$3:K27)+1)
A29: QR7 | B29: =INDEX('01_KPI'!$C$2:$C$44,MATCH($A29,'01_KPI'!$A$2:$A$44,0)) -> Non-conformité critique la plus ancienne | C29: =INDEX('01_KPI'!$D$2:$D$44,MATCH($A29,'01_KPI'!$A$2:$A$44,0)) -> [A] | D29: =INDEX('01_KPI'!$E$2:$E$44,MATCH($A29,'01_KPI'!$A$2:$A$44,0)) -> V2 | F29: V | G29: V | H29: R | I29: V | K29: =IF(INDEX($E29:$J29,'04_Vue_Role'!$B$4)="","",MAX(K$3:K28)+1) | L29: Contractant : les NC qui le concernent.
A30: QR8 | B30: =INDEX('01_KPI'!$C$2:$C$44,MATCH($A30,'01_KPI'!$A$2:$A$44,0)) -> Incidents HSE graves | C30: =INDEX('01_KPI'!$D$2:$D$44,MATCH($A30,'01_KPI'!$A$2:$A$44,0)) -> [A] | D30: =INDEX('01_KPI'!$E$2:$E$44,MATCH($A30,'01_KPI'!$A$2:$A$44,0)) -> Vision | F30: V | G30: V | H30: R | I30: V | K30: =IF(INDEX($E30:$J30,'04_Vue_Role'!$B$4)="","",MAX(K$3:K29)+1) | L30: Contractant : incidents de ses chantiers.
A31: DO1 | B31: =INDEX('01_KPI'!$C$2:$C$44,MATCH($A31,'01_KPI'!$A$2:$A$44,0)) -> Fraîcheur des données | C31: =INDEX('01_KPI'!$D$2:$D$44,MATCH($A31,'01_KPI'!$A$2:$A$44,0)) -> [M] | D31: =INDEX('01_KPI'!$E$2:$E$44,MATCH($A31,'01_KPI'!$A$2:$A$44,0)) -> MVP | F31: R | G31: V | H31: V | K31: =IF(INDEX($E31:$J31,'04_Vue_Role'!$B$4)="","",MAX(K$3:K30)+1)
A32: DO2 | B32: =INDEX('01_KPI'!$C$2:$C$44,MATCH($A32,'01_KPI'!$A$2:$A$44,0)) -> Complétude | C32: =INDEX('01_KPI'!$D$2:$D$44,MATCH($A32,'01_KPI'!$A$2:$A$44,0)) -> [M] | D32: =INDEX('01_KPI'!$E$2:$E$44,MATCH($A32,'01_KPI'!$A$2:$A$44,0)) -> MVP | F32: R | G32: V | H32: V | K32: =IF(INDEX($E32:$J32,'04_Vue_Role'!$B$4)="","",MAX(K$3:K31)+1)
A33: DO3 | B33: =INDEX('01_KPI'!$C$2:$C$44,MATCH($A33,'01_KPI'!$A$2:$A$44,0)) -> Cohérence | C33: =INDEX('01_KPI'!$D$2:$D$44,MATCH($A33,'01_KPI'!$A$2:$A$44,0)) -> [M] | D33: =INDEX('01_KPI'!$E$2:$E$44,MATCH($A33,'01_KPI'!$A$2:$A$44,0)) -> MVP | F33: R | G33: V | H33: V | K33: =IF(INDEX($E33:$J33,'04_Vue_Role'!$B$4)="","",MAX(K$3:K32)+1)
A34: PP1 | B34: =INDEX('01_KPI'!$C$2:$C$44,MATCH($A34,'01_KPI'!$A$2:$A$44,0)) -> Fiabilité du planning hebdomadaire | C34: =INDEX('01_KPI'!$D$2:$D$44,MATCH($A34,'01_KPI'!$A$2:$A$44,0)) -> [A] | D34: =INDEX('01_KPI'!$E$2:$E$44,MATCH($A34,'01_KPI'!$A$2:$A$44,0)) -> V2 | F34: V | G34: R | H34: V | I34: S | K34: =IF(INDEX($E34:$J34,'04_Vue_Role'!$B$4)="","",MAX(K$3:K33)+1)
A35: PP2 | B35: =INDEX('01_KPI'!$C$2:$C$44,MATCH($A35,'01_KPI'!$A$2:$A$44,0)) -> Mobilisation effective | C35: =INDEX('01_KPI'!$D$2:$D$44,MATCH($A35,'01_KPI'!$A$2:$A$44,0)) -> [A] | D35: =INDEX('01_KPI'!$E$2:$E$44,MATCH($A35,'01_KPI'!$A$2:$A$44,0)) -> V2 | F35: V | G35: R | H35: V | I35: S | K35: =IF(INDEX($E35:$J35,'04_Vue_Role'!$B$4)="","",MAX(K$3:K34)+1)
A36: PP3 | B36: =INDEX('01_KPI'!$C$2:$C$44,MATCH($A36,'01_KPI'!$A$2:$A$44,0)) -> Causes de non-réalisation externes | C36: =INDEX('01_KPI'!$D$2:$D$44,MATCH($A36,'01_KPI'!$A$2:$A$44,0)) -> [A] | D36: =INDEX('01_KPI'!$E$2:$E$44,MATCH($A36,'01_KPI'!$A$2:$A$44,0)) -> V2 | F36: V | G36: R | H36: V | I36: S | K36: =IF(INDEX($E36:$J36,'04_Vue_Role'!$B$4)="","",MAX(K$3:K35)+1)
A37: CO1 | B37: =INDEX('01_KPI'!$C$2:$C$44,MATCH($A37,'01_KPI'!$A$2:$A$44,0)) -> Santé du contractant (0–100) | C37: =INDEX('01_KPI'!$D$2:$D$44,MATCH($A37,'01_KPI'!$A$2:$A$44,0)) -> [S] | D37: =INDEX('01_KPI'!$E$2:$E$44,MATCH($A37,'01_KPI'!$A$2:$A$44,0)) -> MVP | E37: V | F37: R | G37: V | I37: V | K37: =IF(INDEX($E37:$J37,'04_Vue_Role'!$B$4)="","",MAX(K$3:K36)+1) -> 15 | L37: Contractant : son propre score uniquement.
A38: CO2 | B38: =INDEX('01_KPI'!$C$2:$C$44,MATCH($A38,'01_KPI'!$A$2:$A$44,0)) -> Concentration par contractant | C38: =INDEX('01_KPI'!$D$2:$D$44,MATCH($A38,'01_KPI'!$A$2:$A$44,0)) -> [S] | D38: =INDEX('01_KPI'!$E$2:$E$44,MATCH($A38,'01_KPI'!$A$2:$A$44,0)) -> V2 | E38: V | F38: R | K38: =IF(INDEX($E38:$J38,'04_Vue_Role'!$B$4)="","",MAX(K$3:K37)+1) -> 16
A39: CO3 | B39: =INDEX('01_KPI'!$C$2:$C$44,MATCH($A39,'01_KPI'!$A$2:$A$44,0)) -> Part en parachèvement après résiliation | C39: =INDEX('01_KPI'!$D$2:$D$44,MATCH($A39,'01_KPI'!$A$2:$A$44,0)) -> [S] | D39: =INDEX('01_KPI'!$E$2:$E$44,MATCH($A39,'01_KPI'!$A$2:$A$44,0)) -> MVP | E39: V | F39: R | K39: =IF(INDEX($E39:$J39,'04_Vue_Role'!$B$4)="","",MAX(K$3:K38)+1) -> 17
A40: CO4 | B40: =INDEX('01_KPI'!$C$2:$C$44,MATCH($A40,'01_KPI'!$A$2:$A$44,0)) -> Projets en retard important | C40: =INDEX('01_KPI'!$D$2:$D$44,MATCH($A40,'01_KPI'!$A$2:$A$44,0)) -> [M] | D40: =INDEX('01_KPI'!$E$2:$E$44,MATCH($A40,'01_KPI'!$A$2:$A$44,0)) -> MVP | E40: V | F40: R | G40: V | J40: V | K40: =IF(INDEX($E40:$J40,'04_Vue_Role'!$B$4)="","",MAX(K$3:K39)+1) -> 18
A41: CO5 | B41: =INDEX('01_KPI'!$C$2:$C$44,MATCH($A41,'01_KPI'!$A$2:$A$44,0)) -> Projets à l'arrêt | C41: =INDEX('01_KPI'!$D$2:$D$44,MATCH($A41,'01_KPI'!$A$2:$A$44,0)) -> [M] | D41: =INDEX('01_KPI'!$E$2:$E$44,MATCH($A41,'01_KPI'!$A$2:$A$44,0)) -> MVP | E41: V | F41: R | G41: V | J41: V | K41: =IF(INDEX($E41:$J41,'04_Vue_Role'!$B$4)="","",MAX(K$3:K40)+1) -> 19
A42: CO6 | B42: =INDEX('01_KPI'!$C$2:$C$44,MATCH($A42,'01_KPI'!$A$2:$A$44,0)) -> Score de santé du portefeuille | C42: =INDEX('01_KPI'!$D$2:$D$44,MATCH($A42,'01_KPI'!$A$2:$A$44,0)) -> [S] | D42: =INDEX('01_KPI'!$E$2:$E$44,MATCH($A42,'01_KPI'!$A$2:$A$44,0)) -> V2 | E42: V | F42: R | K42: =IF(INDEX($E42:$J42,'04_Vue_Role'!$B$4)="","",MAX(K$3:K41)+1) -> 20
A43: GV1 | B43: =INDEX('01_KPI'!$C$2:$C$44,MATCH($A43,'01_KPI'!$A$2:$A$44,0)) -> Blocages avec responsable et échéance | C43: =INDEX('01_KPI'!$D$2:$D$44,MATCH($A43,'01_KPI'!$A$2:$A$44,0)) -> [M] | D43: =INDEX('01_KPI'!$E$2:$E$44,MATCH($A43,'01_KPI'!$A$2:$A$44,0)) -> MVP | F43: R | G43: V | K43: =IF(INDEX($E43:$J43,'04_Vue_Role'!$B$4)="","",MAX(K$3:K42)+1)
A44: GV2 | B44: =INDEX('01_KPI'!$C$2:$C$44,MATCH($A44,'01_KPI'!$A$2:$A$44,0)) -> Avenants en attente de visa (CSM) | C44: =INDEX('01_KPI'!$D$2:$D$44,MATCH($A44,'01_KPI'!$A$2:$A$44,0)) -> [M] | D44: =INDEX('01_KPI'!$E$2:$E$44,MATCH($A44,'01_KPI'!$A$2:$A$44,0)) -> MVP | E44: V | F44: R | G44: S | I44: V | J44: V | K44: =IF(INDEX($E44:$J44,'04_Vue_Role'!$B$4)="","",MAX(K$3:K43)+1) -> 21
A45: GV3 | B45: =INDEX('01_KPI'!$C$2:$C$44,MATCH($A45,'01_KPI'!$A$2:$A$44,0)) -> Arbitrages échus | C45: =INDEX('01_KPI'!$D$2:$D$44,MATCH($A45,'01_KPI'!$A$2:$A$44,0)) -> [A] | D45: =INDEX('01_KPI'!$E$2:$E$44,MATCH($A45,'01_KPI'!$A$2:$A$44,0)) -> V2 | E45: V | F45: R | G45: V | K45: =IF(INDEX($E45:$J45,'04_Vue_Role'!$B$4)="","",MAX(K$3:K44)+1) -> 22
A46: GV4 | B46: =INDEX('01_KPI'!$C$2:$C$44,MATCH($A46,'01_KPI'!$A$2:$A$44,0)) -> Réceptions en attente | C46: =INDEX('01_KPI'!$D$2:$D$44,MATCH($A46,'01_KPI'!$A$2:$A$44,0)) -> [A] | D46: =INDEX('01_KPI'!$E$2:$E$44,MATCH($A46,'01_KPI'!$A$2:$A$44,0)) -> MVP | F46: V | G46: R | H46: V | K46: =IF(INDEX($E46:$J46,'04_Vue_Role'!$B$4)="","",MAX(K$3:K45)+1)
A49: Alertes par rôle
A50: Regle_ID | B50: Nom | C50: Importance | D50: Niveau | E50: =$M$4 -> Direction CNED (décideur) | F50: =$M$5 -> CNED / PMO (analyste) | G50: =$M$6 -> Maître d'ouvrage (MO) | H50: =$M$7 -> Bureau d'études (BET) / contrôle | I50: =$M$8 -> Contractant (entreprise) | J50: =$M$9 -> Contrôleur budgétaire (Finance) | K50: Rang_vue_rôle
A51: AL01 | B51: =INDEX('02_Regles_Alertes'!$B$2:$B$18,MATCH($A51,'02_Regles_Alertes'!$A$2:$A$18,0)) -> Avant-coureur d'abandon | C51: =INDEX('02_Regles_Alertes'!$D$2:$D$18,MATCH($A51,'02_Regles_Alertes'!$A$2:$A$18,0)) -> [A] | D51: =INDEX('02_Regles_Alertes'!$C$2:$C$18,MATCH($A51,'02_Regles_Alertes'!$A$2:$A$18,0)) -> ROUGE | E51: I | F51: D | G51: D | K51: =IF(INDEX($E51:$J51,'04_Vue_Role'!$B$4)="","",MAX(K$50:K50)+1) -> 1
A52: AL02 | B52: =INDEX('02_Regles_Alertes'!$B$2:$B$18,MATCH($A52,'02_Regles_Alertes'!$A$2:$A$18,0)) -> Emprise bloquée critique | C52: =INDEX('02_Regles_Alertes'!$D$2:$D$18,MATCH($A52,'02_Regles_Alertes'!$A$2:$A$18,0)) -> [M] | D52: =INDEX('02_Regles_Alertes'!$C$2:$C$18,MATCH($A52,'02_Regles_Alertes'!$A$2:$A$18,0)) -> ROUGE | E52: I | F52: D | G52: D | K52: =IF(INDEX($E52:$J52,'04_Vue_Role'!$B$4)="","",MAX(K$50:K51)+1) -> 2
A53: AL03 | B53: =INDEX('02_Regles_Alertes'!$B$2:$B$18,MATCH($A53,'02_Regles_Alertes'!$A$2:$A$18,0)) -> Étranglement financier | C53: =INDEX('02_Regles_Alertes'!$D$2:$D$18,MATCH($A53,'02_Regles_Alertes'!$A$2:$A$18,0)) -> [S] | D53: =INDEX('02_Regles_Alertes'!$C$2:$C$18,MATCH($A53,'02_Regles_Alertes'!$A$2:$A$18,0)) -> ROUGE | E53: I | F53: D | G53: I | J53: D | K53: =IF(INDEX($E53:$J53,'04_Vue_Role'!$B$4)="","",MAX(K$50:K52)+1) -> 3
A54: AL04 | B54: =INDEX('02_Regles_Alertes'!$B$2:$B$18,MATCH($A54,'02_Regles_Alertes'!$A$2:$A$18,0)) -> Dégradation contractant | C54: =INDEX('02_Regles_Alertes'!$D$2:$D$18,MATCH($A54,'02_Regles_Alertes'!$A$2:$A$18,0)) -> [A] | D54: =INDEX('02_Regles_Alertes'!$C$2:$C$18,MATCH($A54,'02_Regles_Alertes'!$A$2:$A$18,0)) -> ORANGE | F54: I | G54: D | K54: =IF(INDEX($E54:$J54,'04_Vue_Role'!$B$4)="","",MAX(K$50:K53)+1)
A55: AL05 | B55: =INDEX('02_Regles_Alertes'!$B$2:$B$18,MATCH($A55,'02_Regles_Alertes'!$A$2:$A$18,0)) -> Déblocage critique qui approche | C55: =INDEX('02_Regles_Alertes'!$D$2:$D$18,MATCH($A55,'02_Regles_Alertes'!$A$2:$A$18,0)) -> [A] | D55: =INDEX('02_Regles_Alertes'!$C$2:$C$18,MATCH($A55,'02_Regles_Alertes'!$A$2:$A$18,0)) -> ORANGE | F55: I | G55: D | K55: =IF(INDEX($E55:$J55,'04_Vue_Role'!$B$4)="","",MAX(K$50:K54)+1)
A56: AL06 | B56: =INDEX('02_Regles_Alertes'!$B$2:$B$18,MATCH($A56,'02_Regles_Alertes'!$A$2:$A$18,0)) -> Dérive de délai | C56: =INDEX('02_Regles_Alertes'!$D$2:$D$18,MATCH($A56,'02_Regles_Alertes'!$A$2:$A$18,0)) -> [M] | D56: =INDEX('02_Regles_Alertes'!$C$2:$C$18,MATCH($A56,'02_Regles_Alertes'!$A$2:$A$18,0)) -> ROUGE | E56: I | F56: D | G56: D | I56: I | K56: =IF(INDEX($E56:$J56,'04_Vue_Role'!$B$4)="","",MAX(K$50:K55)+1) -> 4
A57: AL07 | B57: =INDEX('02_Regles_Alertes'!$B$2:$B$18,MATCH($A57,'02_Regles_Alertes'!$A$2:$A$18,0)) -> Sous-performance physique | C57: =INDEX('02_Regles_Alertes'!$D$2:$D$18,MATCH($A57,'02_Regles_Alertes'!$A$2:$A$18,0)) -> [A] | D57: =INDEX('02_Regles_Alertes'!$C$2:$C$18,MATCH($A57,'02_Regles_Alertes'!$A$2:$A$18,0)) -> ORANGE | F57: I | G57: D | I57: D | K57: =IF(INDEX($E57:$J57,'04_Vue_Role'!$B$4)="","",MAX(K$50:K56)+1)
A58: AL08 | B58: =INDEX('02_Regles_Alertes'!$B$2:$B$18,MATCH($A58,'02_Regles_Alertes'!$A$2:$A$18,0)) -> Dérive d'AE | C58: =INDEX('02_Regles_Alertes'!$D$2:$D$18,MATCH($A58,'02_Regles_Alertes'!$A$2:$A$18,0)) -> [M] | D58: =INDEX('02_Regles_Alertes'!$C$2:$C$18,MATCH($A58,'02_Regles_Alertes'!$A$2:$A$18,0)) -> ROUGE | E58: I | F58: I | G58: D | J58: D | K58: =IF(INDEX($E58:$J58,'04_Vue_Role'!$B$4)="","",MAX(K$50:K57)+1) -> 5
A59: AL09 | B59: =INDEX('02_Regles_Alertes'!$B$2:$B$18,MATCH($A59,'02_Regles_Alertes'!$A$2:$A$18,0)) -> NC critique persistante | C59: =INDEX('02_Regles_Alertes'!$D$2:$D$18,MATCH($A59,'02_Regles_Alertes'!$A$2:$A$18,0)) -> [A] | D59: =INDEX('02_Regles_Alertes'!$C$2:$C$18,MATCH($A59,'02_Regles_Alertes'!$A$2:$A$18,0)) -> ROUGE | F59: I | G59: D | H59: D | I59: I | K59: =IF(INDEX($E59:$J59,'04_Vue_Role'!$B$4)="","",MAX(K$50:K58)+1)
A60: AL10 | B60: =INDEX('02_Regles_Alertes'!$B$2:$B$18,MATCH($A60,'02_Regles_Alertes'!$A$2:$A$18,0)) -> Responsable de blocage absent | C60: =INDEX('02_Regles_Alertes'!$D$2:$D$18,MATCH($A60,'02_Regles_Alertes'!$A$2:$A$18,0)) -> [M] | D60: =INDEX('02_Regles_Alertes'!$C$2:$C$18,MATCH($A60,'02_Regles_Alertes'!$A$2:$A$18,0)) -> ORANGE | F60: D | G60: I | K60: =IF(INDEX($E60:$J60,'04_Vue_Role'!$B$4)="","",MAX(K$50:K59)+1)
A61: AL11 | B61: =INDEX('02_Regles_Alertes'!$B$2:$B$18,MATCH($A61,'02_Regles_Alertes'!$A$2:$A$18,0)) -> Paiement anormalement lent | C61: =INDEX('02_Regles_Alertes'!$D$2:$D$18,MATCH($A61,'02_Regles_Alertes'!$A$2:$A$18,0)) -> [A] | D61: =INDEX('02_Regles_Alertes'!$C$2:$C$18,MATCH($A61,'02_Regles_Alertes'!$A$2:$A$18,0)) -> ROUGE | F61: I | G61: D | I61: I | J61: D | K61: =IF(INDEX($E61:$J61,'04_Vue_Role'!$B$4)="","",MAX(K$50:K60)+1)
A62: AL12 | B62: =INDEX('02_Regles_Alertes'!$B$2:$B$18,MATCH($A62,'02_Regles_Alertes'!$A$2:$A$18,0)) -> Maturation critique | C62: =INDEX('02_Regles_Alertes'!$D$2:$D$18,MATCH($A62,'02_Regles_Alertes'!$A$2:$A$18,0)) -> [A] | D62: =INDEX('02_Regles_Alertes'!$C$2:$C$18,MATCH($A62,'02_Regles_Alertes'!$A$2:$A$18,0)) -> ORANGE | F62: I | G62: D | H62: D | K62: =IF(INDEX($E62:$J62,'04_Vue_Role'!$B$4)="","",MAX(K$50:K61)+1)
A63: AL13 | B63: =INDEX('02_Regles_Alertes'!$B$2:$B$18,MATCH($A63,'02_Regles_Alertes'!$A$2:$A$18,0)) -> Dérive de délai extrême | C63: =INDEX('02_Regles_Alertes'!$D$2:$D$18,MATCH($A63,'02_Regles_Alertes'!$A$2:$A$18,0)) -> [M] | D63: =INDEX('02_Regles_Alertes'!$C$2:$C$18,MATCH($A63,'02_Regles_Alertes'!$A$2:$A$18,0)) -> ORANGE | E63: I | F63: D | G63: I | K63: =IF(INDEX($E63:$J63,'04_Vue_Role'!$B$4)="","",MAX(K$50:K62)+1) -> 6
A64: AL14 | B64: =INDEX('02_Regles_Alertes'!$B$2:$B$18,MATCH($A64,'02_Regles_Alertes'!$A$2:$A$18,0)) -> Avenant bloqué au visa | C64: =INDEX('02_Regles_Alertes'!$D$2:$D$18,MATCH($A64,'02_Regles_Alertes'!$A$2:$A$18,0)) -> [M] | D64: =INDEX('02_Regles_Alertes'!$C$2:$C$18,MATCH($A64,'02_Regles_Alertes'!$A$2:$A$18,0)) -> ORANGE | F64: D | G64: D | I64: I | K64: =IF(INDEX($E64:$J64,'04_Vue_Role'!$B$4)="","",MAX(K$50:K63)+1)
A65: AL15 | B65: =INDEX('02_Regles_Alertes'!$B$2:$B$18,MATCH($A65,'02_Regles_Alertes'!$A$2:$A$18,0)) -> Arrêt prolongé | C65: =INDEX('02_Regles_Alertes'!$D$2:$D$18,MATCH($A65,'02_Regles_Alertes'!$A$2:$A$18,0)) -> [M] | D65: =INDEX('02_Regles_Alertes'!$C$2:$C$18,MATCH($A65,'02_Regles_Alertes'!$A$2:$A$18,0)) -> ROUGE | E65: I | F65: D | G65: D | I65: I | K65: =IF(INDEX($E65:$J65,'04_Vue_Role'!$B$4)="","",MAX(K$50:K64)+1) -> 7
A66: AL16 | B66: =INDEX('02_Regles_Alertes'!$B$2:$B$18,MATCH($A66,'02_Regles_Alertes'!$A$2:$A$18,0)) -> Données peu fiables | C66: =INDEX('02_Regles_Alertes'!$D$2:$D$18,MATCH($A66,'02_Regles_Alertes'!$A$2:$A$18,0)) -> [M] | D66: =INDEX('02_Regles_Alertes'!$C$2:$C$18,MATCH($A66,'02_Regles_Alertes'!$A$2:$A$18,0)) -> ORANGE | F66: D | G66: I | H66: I | K66: =IF(INDEX($E66:$J66,'04_Vue_Role'!$B$4)="","",MAX(K$50:K65)+1)
A67: AL17 | B67: =INDEX('02_Regles_Alertes'!$B$2:$B$18,MATCH($A67,'02_Regles_Alertes'!$A$2:$A$18,0)) -> Blocage ancien | C67: =INDEX('02_Regles_Alertes'!$D$2:$D$18,MATCH($A67,'02_Regles_Alertes'!$A$2:$A$18,0)) -> [M] | D67: =INDEX('02_Regles_Alertes'!$C$2:$C$18,MATCH($A67,'02_Regles_Alertes'!$A$2:$A$18,0)) -> ORANGE | E67: I | F67: D | K67: =IF(INDEX($E67:$J67,'04_Vue_Role'!$B$4)="","",MAX(K$50:K66)+1) -> 8

Sheet 04_Vue_Role
A1: Ma vue — KPI et alertes affichés selon le rôle
A3: Rôle | B3: Direction CNED (décideur) | F3: ◄ choisir un rôle dans la liste
A4: Index | B4: =MATCH($B$3,'03_Matrice_Roles'!$M$4:$M$9,0) -> 1
A5: Périmètre | B5: =INDEX('03_Matrice_Roles'!$N$4:$N$9,$B$4) -> Portefeuille national (tous les projets)
A6: Vue | B6: =INDEX('03_Matrice_Roles'!$O$4:$O$9,$B$4) -> Synthèse de pilotage : KPI [S] et [M] clés, arbitrage des alertes ROUGE.
A7: ="KPI visibles : "&MAX('03_Matrice_Roles'!$K$4:$K$46)&" ([M] "&SUMPRODUCT(('03_Matrice_Roles'!$K$4:$K$46<>"")*('03_Matrice_Roles'!$C$4:$C$46="[M]"))&" · [A] "&SUMPRODUCT(('03_Matrice_Roles'!$K$4:$K$46<>"")*('03_Matrice_Roles'!$C$4:$C$46="[A]"))&" · [S] "&SUMPRODUCT(('03_Matrice_Roles'!$K$4:$K$46<>"")*('03_Matrice_Roles'!$C$4:$C$46="[S]"))&") — Règles d'alerte concernées : "&MAX('03_Matrice_Roles'!$K$51:$K$67) -> KPI visibles : 22 ([M] 12 · [A] 1 · [S] 9) — Règles d'alerte concernées : 8
A8: Mes KPI
A9: N° | B9: KPI_ID | C9: Nom_KPI | D9: Importance | E9: Phase | F9: Mon droit | G9: Définition | H9: Unité | I9: Sens | J9: Vert | K9: Orange | L9: Rouge | M9: Fréquence
A10: =IF($B10="","",ROW()-9) -> 1 | B10: =IFERROR(INDEX('03_Matrice_Roles'!$A$4:$A$46,MATCH(ROW()-9,'03_Matrice_Roles'!$K$4:$K$46,0)),"") -> AV2 | C10: =IF($B10="","",INDEX('01_KPI'!$C$2:$C$44,MATCH($B10,'01_KPI'!$A$2:$A$44,0))) -> Indice d'avancement | D10: =IF($B10="","",INDEX('01_KPI'!$D$2:$D$44,MATCH($B10,'01_KPI'!$A$2:$A$44,0))) -> [M] | E10: =IF($B10="","",INDEX('01_KPI'!$E$2:$E$44,MATCH($B10,'01_KPI'!$A$2:$A$44,0))) -> MVP | F10: =IF($B10="","",IF(INDEX('03_Matrice_Roles'!$E$4:$J$46,MATCH($B10,'03_Matrice_Roles'!$A$4:$A$46,0),$B$4)="R","Responsable",IF(INDEX('03_Matrice_Roles'!$E$4:$J$46,MATCH($B10,'03_Matrice_Roles'!$A$4:$A$46,0),$B$4)="S","Alimente","Consulte"))) -> Consulte | G10: =IF($B10="","",INDEX('01_KPI'!$G$2:$G$44,MATCH($B10,'01_KPI'!$A$2:$A$44,0))) -> Compare l'avancement physique au temps déjà consommé ; 1 = projet dans le rythme. | H10: =IF($B10="","",INDEX('01_KPI'!$I$2:$I$44,MATCH($B10,'01_KPI'!$A$2:$A$44,0))) -> ratio | I10: =IF($B10="","",INDEX('01_KPI'!$J$2:$J$44,MATCH($B10,'01_KPI'!$A$2:$A$44,0))) -> Plus haut = mieux | J10: =IF($B10="","",INDEX('01_KPI'!$M$2:$M$44,MATCH($B10,'01_KPI'!$A$2:$A$44,0))) -> ≥ 0.9 ratio | K10: =IF($B10="","",INDEX('01_KPI'!$N$2:$N$44,MATCH($B10,'01_KPI'!$A$2:$A$44,0))) -> de 0.7 à < 0.9 ratio | L10: =IF($B10="","",INDEX('01_KPI'!$O$2:$O$44,MATCH($B10,'01_KPI'!$A$2:$A$44,0))) -> < 0.7 ratio | M10: =IF($B10="","",INDEX('01_KPI'!$R$2:$R$44,MATCH($B10,'01_KPI'!$A$2:$A$44,0))) -> Mensuelle
A11: =IF($B11="","",ROW()-9) -> 2 | B11: =IFERROR(INDEX('03_Matrice_Roles'!$A$4:$A$46,MATCH(ROW()-9,'03_Matrice_Roles'!$K$4:$K$46,0)),"") -> AV5 | C11: =IF($B11="","",INDEX('01_KPI'!$C$2:$C$44,MATCH($B11,'01_KPI'!$A$2:$A$44,0))) -> Mise en service fonctionnelle | D11: =IF($B11="","",INDEX('01_KPI'!$D$2:$D$44,MATCH($B11,'01_KPI'!$A$2:$A$44,0))) -> [S] | E11: =IF($B11="","",INDEX('01_KPI'!$E$2:$E$44,MATCH($B11,'01_KPI'!$A$2:$A$44,0))) -> MVP | F11: =IF($B11="","",IF(INDEX('03_Matrice_Roles'!$E$4:$J$46,MATCH($B11,'03_Matrice_Roles'!$A$4:$A$46,0),$B$4)="R","Responsable",IF(INDEX('03_Matrice_Roles'!$E$4:$J$46,MATCH($B11,'03_Matrice_Roles'!$A$4:$A$46,0),$B$4)="S","Alimente","Consulte"))) -> Consulte | G11: =IF($B11="","",INDEX('01_KPI'!$G$2:$G$44,MATCH($B11,'01_KPI'!$A$2:$A$44,0))) -> Part des ouvrages mis en service qui fonctionnent pleinement (sans réserve ni lot système, signalisation ou énergie en retard). | H11: =IF($B11="","",INDEX('01_KPI'!$I$2:$I$44,MATCH($B11,'01_KPI'!$A$2:$A$44,0))) -> % | I11: =IF($B11="","",INDEX('01_KPI'!$J$2:$J$44,MATCH($B11,'01_KPI'!$A$2:$A$44,0))) -> Plus haut = mieux | J11: =IF($B11="","",INDEX('01_KPI'!$M$2:$M$44,MATCH($B11,'01_KPI'!$A$2:$A$44,0))) -> ≥ 90 % | K11: =IF($B11="","",INDEX('01_KPI'!$N$2:$N$44,MATCH($B11,'01_KPI'!$A$2:$A$44,0))) -> de 60 à < 90 % | L11: =IF($B11="","",INDEX('01_KPI'!$O$2:$O$44,MATCH($B11,'01_KPI'!$A$2:$A$44,0))) -> < 60 % | M11: =IF($B11="","",INDEX('01_KPI'!$R$2:$R$44,MATCH($B11,'01_KPI'!$A$2:$A$44,0))) -> Mensuelle
A12: =IF($B12="","",ROW()-9) -> 3 | B12: =IFERROR(INDEX('03_Matrice_Roles'!$A$4:$A$46,MATCH(ROW()-9,'03_Matrice_Roles'!$K$4:$K$46,0)),"") -> FI2 | C12: =IF($B12="","",INDEX('01_KPI'!$C$2:$C$44,MATCH($B12,'01_KPI'!$A$2:$A$44,0))) -> Couverture du reste à faire | D12: =IF($B12="","",INDEX('01_KPI'!$D$2:$D$44,MATCH($B12,'01_KPI'!$A$2:$A$44,0))) -> [S] | E12: =IF($B12="","",INDEX('01_KPI'!$E$2:$E$44,MATCH($B12,'01_KPI'!$A$2:$A$44,0))) -> V2 | F12: =IF($B12="","",IF(INDEX('03_Matrice_Roles'!$E$4:$J$46,MATCH($B12,'03_Matrice_Roles'!$A$4:$A$46,0),$B$4)="R","Responsable",IF(INDEX('03_Matrice_Roles'!$E$4:$J$46,MATCH($B12,'03_Matrice_Roles'!$A$4:$A$46,0),$B$4)="S","Alimente","Consulte"))) -> Consulte | G12: =IF($B12="","",INDEX('01_KPI'!$G$2:$G$44,MATCH($B12,'01_KPI'!$A$2:$A$44,0))) -> Capacité des ressources financières restantes à couvrir ce qu'il reste à payer, avenants en préparation compris. | H12: =IF($B12="","",INDEX('01_KPI'!$I$2:$I$44,MATCH($B12,'01_KPI'!$A$2:$A$44,0))) -> % | I12: =IF($B12="","",INDEX('01_KPI'!$J$2:$J$44,MATCH($B12,'01_KPI'!$A$2:$A$44,0))) -> Plus haut = mieux | J12: =IF($B12="","",INDEX('01_KPI'!$M$2:$M$44,MATCH($B12,'01_KPI'!$A$2:$A$44,0))) -> ≥ 100 % | K12: =IF($B12="","",INDEX('01_KPI'!$N$2:$N$44,MATCH($B12,'01_KPI'!$A$2:$A$44,0))) -> de 90 à < 100 % | L12: =IF($B12="","",INDEX('01_KPI'!$O$2:$O$44,MATCH($B12,'01_KPI'!$A$2:$A$44,0))) -> < 90 % | M12: =IF($B12="","",INDEX('01_KPI'!$R$2:$R$44,MATCH($B12,'01_KPI'!$A$2:$A$44,0))) -> Mensuelle
A13: =IF($B13="","",ROW()-9) -> 4 | B13: =IFERROR(INDEX('03_Matrice_Roles'!$A$4:$A$46,MATCH(ROW()-9,'03_Matrice_Roles'!$K$4:$K$46,0)),"") -> FI3 | C13: =IF($B13="","",INDEX('01_KPI'!$C$2:$C$44,MATCH($B13,'01_KPI'!$A$2:$A$44,0))) -> Couverture des crédits de paiement | D13: =IF($B13="","",INDEX('01_KPI'!$D$2:$D$44,MATCH($B13,'01_KPI'!$A$2:$A$44,0))) -> [S] | E13: =IF($B13="","",INDEX('01_KPI'!$E$2:$E$44,MATCH($B13,'01_KPI'!$A$2:$A$44,0))) -> V2 | F13: =IF($B13="","",IF(INDEX('03_Matrice_Roles'!$E$4:$J$46,MATCH($B13,'03_Matrice_Roles'!$A$4:$A$46,0),$B$4)="R","Responsable",IF(INDEX('03_Matrice_Roles'!$E$4:$J$46,MATCH($B13,'03_Matrice_Roles'!$A$4:$A$46,0),$B$4)="S","Alimente","Consulte"))) -> Consulte | G13: =IF($B13="","",INDEX('01_KPI'!$G$2:$G$44,MATCH($B13,'01_KPI'!$A$2:$A$44,0))) -> Les crédits de paiement de l'exercice couvrent-ils les paiements prévus ? (insuffisance des CP : contrainte récurrente.) | H13: =IF($B13="","",INDEX('01_KPI'!$I$2:$I$44,MATCH($B13,'01_KPI'!$A$2:$A$44,0))) -> % | I13: =IF($B13="","",INDEX('01_KPI'!$J$2:$J$44,MATCH($B13,'01_KPI'!$A$2:$A$44,0))) -> Plus haut = mieux | J13: =IF($B13="","",INDEX('01_KPI'!$M$2:$M$44,MATCH($B13,'01_KPI'!$A$2:$A$44,0))) -> ≥ 100 % | K13: =IF($B13="","",INDEX('01_KPI'!$N$2:$N$44,MATCH($B13,'01_KPI'!$A$2:$A$44,0))) -> de 80 à < 100 % | L13: =IF($B13="","",INDEX('01_KPI'!$O$2:$O$44,MATCH($B13,'01_KPI'!$A$2:$A$44,0))) -> < 80 % | M13: =IF($B13="","",INDEX('01_KPI'!$R$2:$R$44,MATCH($B13,'01_KPI'!$A$2:$A$44,0))) -> Mensuelle
A14: =IF($B14="","",ROW()-9) -> 5 | B14: =IFERROR(INDEX('03_Matrice_Roles'!$A$4:$A$46,MATCH(ROW()-9,'03_Matrice_Roles'!$K$4:$K$46,0)),"") -> FI4 | C14: =IF($B14="","",INDEX('01_KPI'!$C$2:$C$44,MATCH($B14,'01_KPI'!$A$2:$A$44,0))) -> Dérive d'AE ajustée | D14: =IF($B14="","",INDEX('01_KPI'!$D$2:$D$44,MATCH($B14,'01_KPI'!$A$2:$A$44,0))) -> [M] | E14: =IF($B14="","",INDEX('01_KPI'!$E$2:$E$44,MATCH($B14,'01_KPI'!$A$2:$A$44,0))) -> MVP | F14: =IF($B14="","",IF(INDEX('03_Matrice_Roles'!$E$4:$J$46,MATCH($B14,'03_Matrice_Roles'!$A$4:$A$46,0),$B$4)="R","Responsable",IF(INDEX('03_Matrice_Roles'!$E$4:$J$46,MATCH($B14,'03_Matrice_Roles'!$A$4:$A$46,0),$B$4)="S","Alimente","Consulte"))) -> Consulte | G14: =IF($B14="","",INDEX('01_KPI'!$G$2:$G$44,MATCH($B14,'01_KPI'!$A$2:$A$44,0))) -> Augmentation de l'AE par rapport à l'AE initiale, après neutralisation des transferts de maîtrise d'ouvrage ou de périmètre. | H14: =IF($B14="","",INDEX('01_KPI'!$I$2:$I$44,MATCH($B14,'01_KPI'!$A$2:$A$44,0))) -> % | I14: =IF($B14="","",INDEX('01_KPI'!$J$2:$J$44,MATCH($B14,'01_KPI'!$A$2:$A$44,0))) -> Plus bas = mieux | J14: =IF($B14="","",INDEX('01_KPI'!$M$2:$M$44,MATCH($B14,'01_KPI'!$A$2:$A$44,0))) -> ≤ 20 % | K14: =IF($B14="","",INDEX('01_KPI'!$N$2:$N$44,MATCH($B14,'01_KPI'!$A$2:$A$44,0))) -> > 20 à 60 % | L14: =IF($B14="","",INDEX('01_KPI'!$O$2:$O$44,MATCH($B14,'01_KPI'!$A$2:$A$44,0))) -> > 60 % | M14: =IF($B14="","",INDEX('01_KPI'!$R$2:$R$44,MATCH($B14,'01_KPI'!$A$2:$A$44,0))) -> Mensuelle
A15: =IF($B15="","",ROW()-9) -> 6 | B15: =IFERROR(INDEX('03_Matrice_Roles'!$A$4:$A$46,MATCH(ROW()-9,'03_Matrice_Roles'!$K$4:$K$46,0)),"") -> FI5 | C15: =IF($B15="","",INDEX('01_KPI'!$C$2:$C$44,MATCH($B15,'01_KPI'!$A$2:$A$44,0))) -> Réévaluations d'AE en attente | D15: =IF($B15="","",INDEX('01_KPI'!$D$2:$D$44,MATCH($B15,'01_KPI'!$A$2:$A$44,0))) -> [M] | E15: =IF($B15="","",INDEX('01_KPI'!$E$2:$E$44,MATCH($B15,'01_KPI'!$A$2:$A$44,0))) -> MVP | F15: =IF($B15="","",IF(INDEX('03_Matrice_Roles'!$E$4:$J$46,MATCH($B15,'03_Matrice_Roles'!$A$4:$A$46,0),$B$4)="R","Responsable",IF(INDEX('03_Matrice_Roles'!$E$4:$J$46,MATCH($B15,'03_Matrice_Roles'!$A$4:$A$46,0),$B$4)="S","Alimente","Consulte"))) -> Consulte | G15: =IF($B15="","",INDEX('01_KPI'!$G$2:$G$44,MATCH($B15,'01_KPI'!$A$2:$A$44,0))) -> Ancienneté de la plus ancienne réévaluation d'AE non encore approuvée ; le montant en attente est affiché à côté. | H15: =IF($B15="","",INDEX('01_KPI'!$I$2:$I$44,MATCH($B15,'01_KPI'!$A$2:$A$44,0))) -> j | I15: =IF($B15="","",INDEX('01_KPI'!$J$2:$J$44,MATCH($B15,'01_KPI'!$A$2:$A$44,0))) -> Plus bas = mieux | J15: =IF($B15="","",INDEX('01_KPI'!$M$2:$M$44,MATCH($B15,'01_KPI'!$A$2:$A$44,0))) -> ≤ 60 j | K15: =IF($B15="","",INDEX('01_KPI'!$N$2:$N$44,MATCH($B15,'01_KPI'!$A$2:$A$44,0))) -> > 60 à 120 j | L15: =IF($B15="","",INDEX('01_KPI'!$O$2:$O$44,MATCH($B15,'01_KPI'!$A$2:$A$44,0))) -> > 120 j | M15: =IF($B15="","",INDEX('01_KPI'!$R$2:$R$44,MATCH($B15,'01_KPI'!$A$2:$A$44,0))) -> Mensuelle
A16: =IF($B16="","",ROW()-9) -> 7 | B16: =IFERROR(INDEX('03_Matrice_Roles'!$A$4:$A$46,MATCH(ROW()-9,'03_Matrice_Roles'!$K$4:$K$46,0)),"") -> DL2 | C16: =IF($B16="","",INDEX('01_KPI'!$C$2:$C$44,MATCH($B16,'01_KPI'!$A$2:$A$44,0))) -> Dérive de délai par avenants | D16: =IF($B16="","",INDEX('01_KPI'!$D$2:$D$44,MATCH($B16,'01_KPI'!$A$2:$A$44,0))) -> [M] | E16: =IF($B16="","",INDEX('01_KPI'!$E$2:$E$44,MATCH($B16,'01_KPI'!$A$2:$A$44,0))) -> MVP | F16: =IF($B16="","",IF(INDEX('03_Matrice_Roles'!$E$4:$J$46,MATCH($B16,'03_Matrice_Roles'!$A$4:$A$46,0),$B$4)="R","Responsable",IF(INDEX('03_Matrice_Roles'!$E$4:$J$46,MATCH($B16,'03_Matrice_Roles'!$A$4:$A$46,0),$B$4)="S","Alimente","Consulte"))) -> Consulte | G16: =IF($B16="","",INDEX('01_KPI'!$G$2:$G$44,MATCH($B16,'01_KPI'!$A$2:$A$44,0))) -> Allongement du délai par avenants par rapport au délai initial ; 1 = aucun allongement. | H16: =IF($B16="","",INDEX('01_KPI'!$I$2:$I$44,MATCH($B16,'01_KPI'!$A$2:$A$44,0))) -> ratio | I16: =IF($B16="","",INDEX('01_KPI'!$J$2:$J$44,MATCH($B16,'01_KPI'!$A$2:$A$44,0))) -> Plus bas = mieux | J16: =IF($B16="","",INDEX('01_KPI'!$M$2:$M$44,MATCH($B16,'01_KPI'!$A$2:$A$44,0))) -> ≤ 1.25 ratio | K16: =IF($B16="","",INDEX('01_KPI'!$N$2:$N$44,MATCH($B16,'01_KPI'!$A$2:$A$44,0))) -> > 1.25 à 2.0 ratio | L16: =IF($B16="","",INDEX('01_KPI'!$O$2:$O$44,MATCH($B16,'01_KPI'!$A$2:$A$44,0))) -> > 2.0 ratio | M16: =IF($B16="","",INDEX('01_KPI'!$R$2:$R$44,MATCH($B16,'01_KPI'!$A$2:$A$44,0))) -> Mensuelle
A17: =IF($B17="","",ROW()-9) -> 8 | B17: =IFERROR(INDEX('03_Matrice_Roles'!$A$4:$A$46,MATCH(ROW()-9,'03_Matrice_Roles'!$K$4:$K$46,0)),"") -> DL3 | C17: =IF($B17="","",INDEX('01_KPI'!$C$2:$C$44,MATCH($B17,'01_KPI'!$A$2:$A$44,0))) -> Dépassement de la date contractuelle | D17: =IF($B17="","",INDEX('01_KPI'!$D$2:$D$44,MATCH($B17,'01_KPI'!$A$2:$A$44,0))) -> [M] | E17: =IF($B17="","",INDEX('01_KPI'!$E$2:$E$44,MATCH($B17,'01_KPI'!$A$2:$A$44,0))) -> MVP | F17: =IF($B17="","",IF(INDEX('03_Matrice_Roles'!$E$4:$J$46,MATCH($B17,'03_Matrice_Roles'!$A$4:$A$46,0),$B$4)="R","Responsable",IF(INDEX('03_Matrice_Roles'!$E$4:$J$46,MATCH($B17,'03_Matrice_Roles'!$A$4:$A$46,0),$B$4)="S","Alimente","Consulte"))) -> Consulte | G17: =IF($B17="","",INDEX('01_KPI'!$G$2:$G$44,MATCH($B17,'01_KPI'!$A$2:$A$44,0))) -> Jours écoulés depuis la date de fin contractuelle en vigueur, pour un projet non achevé (0 si non dépassée). Au niveau portefeuille : médiane. | H17: =IF($B17="","",INDEX('01_KPI'!$I$2:$I$44,MATCH($B17,'01_KPI'!$A$2:$A$44,0))) -> j | I17: =IF($B17="","",INDEX('01_KPI'!$J$2:$J$44,MATCH($B17,'01_KPI'!$A$2:$A$44,0))) -> Plus bas = mieux | J17: =IF($B17="","",INDEX('01_KPI'!$M$2:$M$44,MATCH($B17,'01_KPI'!$A$2:$A$44,0))) -> ≤ 0 j | K17: =IF($B17="","",INDEX('01_KPI'!$N$2:$N$44,MATCH($B17,'01_KPI'!$A$2:$A$44,0))) -> > 0 à 180 j | L17: =IF($B17="","",INDEX('01_KPI'!$O$2:$O$44,MATCH($B17,'01_KPI'!$A$2:$A$44,0))) -> > 180 j | M17: =IF($B17="","",INDEX('01_KPI'!$R$2:$R$44,MATCH($B17,'01_KPI'!$A$2:$A$44,0))) -> Mensuelle
A18: =IF($B18="","",ROW()-9) -> 9 | B18: =IFERROR(INDEX('03_Matrice_Roles'!$A$4:$A$46,MATCH(ROW()-9,'03_Matrice_Roles'!$K$4:$K$46,0)),"") -> DL4 | C18: =IF($B18="","",INDEX('01_KPI'!$C$2:$C$44,MATCH($B18,'01_KPI'!$A$2:$A$44,0))) -> Date d'achèvement prévisionnelle | D18: =IF($B18="","",INDEX('01_KPI'!$D$2:$D$44,MATCH($B18,'01_KPI'!$A$2:$A$44,0))) -> [S] | E18: =IF($B18="","",INDEX('01_KPI'!$E$2:$E$44,MATCH($B18,'01_KPI'!$A$2:$A$44,0))) -> V2 | F18: =IF($B18="","",IF(INDEX('03_Matrice_Roles'!$E$4:$J$46,MATCH($B18,'03_Matrice_Roles'!$A$4:$A$46,0),$B$4)="R","Responsable",IF(INDEX('03_Matrice_Roles'!$E$4:$J$46,MATCH($B18,'03_Matrice_Roles'!$A$4:$A$46,0),$B$4)="S","Alimente","Consulte"))) -> Consulte | G18: =IF($B18="","",INDEX('01_KPI'!$G$2:$G$44,MATCH($B18,'01_KPI'!$A$2:$A$44,0))) -> Écart entre la date d'achèvement prévue au rythme actuel (contraintes incluses) et la date contractuelle. | H18: =IF($B18="","",INDEX('01_KPI'!$I$2:$I$44,MATCH($B18,'01_KPI'!$A$2:$A$44,0))) -> mois | I18: =IF($B18="","",INDEX('01_KPI'!$J$2:$J$44,MATCH($B18,'01_KPI'!$A$2:$A$44,0))) -> Plus bas = mieux | J18: =IF($B18="","",INDEX('01_KPI'!$M$2:$M$44,MATCH($B18,'01_KPI'!$A$2:$A$44,0))) -> ≤ 0 mois | K18: =IF($B18="","",INDEX('01_KPI'!$N$2:$N$44,MATCH($B18,'01_KPI'!$A$2:$A$44,0))) -> > 0 à 6 mois | L18: =IF($B18="","",INDEX('01_KPI'!$O$2:$O$44,MATCH($B18,'01_KPI'!$A$2:$A$44,0))) -> > 6 mois | M18: =IF($B18="","",INDEX('01_KPI'!$R$2:$R$44,MATCH($B18,'01_KPI'!$A$2:$A$44,0))) -> Mensuelle
A19: =IF($B19="","",ROW()-9) -> 10 | B19: =IFERROR(INDEX('03_Matrice_Roles'!$A$4:$A$46,MATCH(ROW()-9,'03_Matrice_Roles'!$K$4:$K$46,0)),"") -> BU1 | C19: =IF($B19="","",INDEX('01_KPI'!$C$2:$C$44,MATCH($B19,'01_KPI'!$A$2:$A$44,0))) -> Poids financier des avenants | D19: =IF($B19="","",INDEX('01_KPI'!$D$2:$D$44,MATCH($B19,'01_KPI'!$A$2:$A$44,0))) -> [M] | E19: =IF($B19="","",INDEX('01_KPI'!$E$2:$E$44,MATCH($B19,'01_KPI'!$A$2:$A$44,0))) -> MVP | F19: =IF($B19="","",IF(INDEX('03_Matrice_Roles'!$E$4:$J$46,MATCH($B19,'03_Matrice_Roles'!$A$4:$A$46,0),$B$4)="R","Responsable",IF(INDEX('03_Matrice_Roles'!$E$4:$J$46,MATCH($B19,'03_Matrice_Roles'!$A$4:$A$46,0),$B$4)="S","Alimente","Consulte"))) -> Consulte | G19: =IF($B19="","",INDEX('01_KPI'!$G$2:$G$44,MATCH($B19,'01_KPI'!$A$2:$A$44,0))) -> Part du montant initial d'un marché ajoutée par les avenants. | H19: =IF($B19="","",INDEX('01_KPI'!$I$2:$I$44,MATCH($B19,'01_KPI'!$A$2:$A$44,0))) -> % | I19: =IF($B19="","",INDEX('01_KPI'!$J$2:$J$44,MATCH($B19,'01_KPI'!$A$2:$A$44,0))) -> Plus bas = mieux | J19: =IF($B19="","",INDEX('01_KPI'!$M$2:$M$44,MATCH($B19,'01_KPI'!$A$2:$A$44,0))) -> ≤ 15 % | K19: =IF($B19="","",INDEX('01_KPI'!$N$2:$N$44,MATCH($B19,'01_KPI'!$A$2:$A$44,0))) -> > 15 à 40 % | L19: =IF($B19="","",INDEX('01_KPI'!$O$2:$O$44,MATCH($B19,'01_KPI'!$A$2:$A$44,0))) -> > 40 % | M19: =IF($B19="","",INDEX('01_KPI'!$R$2:$R$44,MATCH($B19,'01_KPI'!$A$2:$A$44,0))) -> Mensuelle
A20: =IF($B20="","",ROW()-9) -> 11 | B20: =IFERROR(INDEX('03_Matrice_Roles'!$A$4:$A$46,MATCH(ROW()-9,'03_Matrice_Roles'!$K$4:$K$46,0)),"") -> BU3 | C20: =IF($B20="","",INDEX('01_KPI'!$C$2:$C$44,MATCH($B20,'01_KPI'!$A$2:$A$44,0))) -> Coût final prévisionnel | D20: =IF($B20="","",INDEX('01_KPI'!$D$2:$D$44,MATCH($B20,'01_KPI'!$A$2:$A$44,0))) -> [S] | E20: =IF($B20="","",INDEX('01_KPI'!$E$2:$E$44,MATCH($B20,'01_KPI'!$A$2:$A$44,0))) -> V2 | F20: =IF($B20="","",IF(INDEX('03_Matrice_Roles'!$E$4:$J$46,MATCH($B20,'03_Matrice_Roles'!$A$4:$A$46,0),$B$4)="R","Responsable",IF(INDEX('03_Matrice_Roles'!$E$4:$J$46,MATCH($B20,'03_Matrice_Roles'!$A$4:$A$46,0),$B$4)="S","Alimente","Consulte"))) -> Consulte | G20: =IF($B20="","",INDEX('01_KPI'!$G$2:$G$44,MATCH($B20,'01_KPI'!$A$2:$A$44,0))) -> Coût estimé à l'achèvement rapporté à l'AE actuelle. | H20: =IF($B20="","",INDEX('01_KPI'!$I$2:$I$44,MATCH($B20,'01_KPI'!$A$2:$A$44,0))) -> % | I20: =IF($B20="","",INDEX('01_KPI'!$J$2:$J$44,MATCH($B20,'01_KPI'!$A$2:$A$44,0))) -> Plus bas = mieux | J20: =IF($B20="","",INDEX('01_KPI'!$M$2:$M$44,MATCH($B20,'01_KPI'!$A$2:$A$44,0))) -> ≤ 100 % | K20: =IF($B20="","",INDEX('01_KPI'!$N$2:$N$44,MATCH($B20,'01_KPI'!$A$2:$A$44,0))) -> > 100 à 110 % | L20: =IF($B20="","",INDEX('01_KPI'!$O$2:$O$44,MATCH($B20,'01_KPI'!$A$2:$A$44,0))) -> > 110 % | M20: =IF($B20="","",INDEX('01_KPI'!$R$2:$R$44,MATCH($B20,'01_KPI'!$A$2:$A$44,0))) -> Mensuelle
A21: =IF($B21="","",ROW()-9) -> 12 | B21: =IFERROR(INDEX('03_Matrice_Roles'!$A$4:$A$46,MATCH(ROW()-9,'03_Matrice_Roles'!$K$4:$K$46,0)),"") -> QR1 | C21: =IF($B21="","",INDEX('01_KPI'!$C$2:$C$44,MATCH($B21,'01_KPI'!$A$2:$A$44,0))) -> Taux de libération des emprises | D21: =IF($B21="","",INDEX('01_KPI'!$D$2:$D$44,MATCH($B21,'01_KPI'!$A$2:$A$44,0))) -> [M] | E21: =IF($B21="","",INDEX('01_KPI'!$E$2:$E$44,MATCH($B21,'01_KPI'!$A$2:$A$44,0))) -> MVP | F21: =IF($B21="","",IF(INDEX('03_Matrice_Roles'!$E$4:$J$46,MATCH($B21,'03_Matrice_Roles'!$A$4:$A$46,0),$B$4)="R","Responsable",IF(INDEX('03_Matrice_Roles'!$E$4:$J$46,MATCH($B21,'03_Matrice_Roles'!$A$4:$A$46,0),$B$4)="S","Alimente","Consulte"))) -> Consulte | G21: =IF($B21="","",INDEX('01_KPI'!$G$2:$G$44,MATCH($B21,'01_KPI'!$A$2:$A$44,0))) -> Part de l'emprise nécessaire à date (selon le planning) effectivement libérée. | H21: =IF($B21="","",INDEX('01_KPI'!$I$2:$I$44,MATCH($B21,'01_KPI'!$A$2:$A$44,0))) -> % | I21: =IF($B21="","",INDEX('01_KPI'!$J$2:$J$44,MATCH($B21,'01_KPI'!$A$2:$A$44,0))) -> Plus haut = mieux | J21: =IF($B21="","",INDEX('01_KPI'!$M$2:$M$44,MATCH($B21,'01_KPI'!$A$2:$A$44,0))) -> ≥ 95 % | K21: =IF($B21="","",INDEX('01_KPI'!$N$2:$N$44,MATCH($B21,'01_KPI'!$A$2:$A$44,0))) -> de 80 à < 95 % | L21: =IF($B21="","",INDEX('01_KPI'!$O$2:$O$44,MATCH($B21,'01_KPI'!$A$2:$A$44,0))) -> < 80 % | M21: =IF($B21="","",INDEX('01_KPI'!$R$2:$R$44,MATCH($B21,'01_KPI'!$A$2:$A$44,0))) -> Mensuelle
... A52: =IF($B52="","",ROW()-9) | B52: =IFERROR(INDEX('03_Matrice_Roles'!$A$4:$A$46,MATCH(ROW()-9,'03_Matrice_Roles'!$K$4:$K$46,0)),"") | C52: =IF($B52="","",INDEX('01_KPI'!$C$2:$C$44,MATCH($B52,'01_KPI'!$A$2:$A$44,0))) | D52: =IF($B52="","",INDEX('01_KPI'!$D$2:$D$44,MATCH($B52,'01_KPI'!$A$2:$A$44,0))) | E52: =IF($B52="","",INDEX('01_KPI'!$E$2:$E$44,MATCH($B52,'01_KPI'!$A$2:$A$44,0))) | F52: =IF($B52="","",IF(INDEX('03_Matrice_Roles'!$E$4:$J$46,MATCH($B52,'03_Matrice_Roles'!$A$4:$A$46,0),$B$4)="R","Responsable",IF(INDEX('03_Matrice_Roles'!$E$4:$J$46,MATCH($B52,'03_Matrice_Roles'!$A$4:$A$46,0),$B$4)="S","Alimente","Consulte"))) | G52: =IF($B52="","",INDEX('01_KPI'!$G$2:$G$44,MATCH($B52,'01_KPI'!$A$2:$A$44,0))) | H52: =IF($B52="","",INDEX('01_KPI'!$I$2:$I$44,MATCH($B52,'01_KPI'!$A$2:$A$44,0))) | I52: =IF($B52="","",INDEX('01_KPI'!$J$2:$J$44,MATCH($B52,'01_KPI'!$A$2:$A$44,0))) | J52: =IF($B52="","",INDEX('01_KPI'!$M$2:$M$44,MATCH($B52,'01_KPI'!$A$2:$A$44,0))) | K52: =IF($B52="","",INDEX('01_KPI'!$N$2:$N$44,MATCH($B52,'01_KPI'!$A$2:$A$44,0))) | L52: =IF($B52="","",INDEX('01_KPI'!$O$2:$O$44,MATCH($B52,'01_KPI'!$A$2:$A$44,0))) | M52: =IF($B52="","",INDEX('01_KPI'!$R$2:$R$44,MATCH($B52,'01_KPI'!$A$2:$A$44,0)))
A55: Mes alertes
A56: N° | B56: Regle_ID | C56: Nom | D56: Niveau | E56: Importance | F56: Mon rôle | G56: Condition | H56: Fréquence | I56: Logique | J56: Action attendue
A57: =IF($B57="","",ROW()-56) -> 1 | B57: =IFERROR(INDEX('03_Matrice_Roles'!$A$51:$A$67,MATCH(ROW()-56,'03_Matrice_Roles'!$K$51:$K$67,0)),"") -> AL01 | C57: =IF($B57="","",INDEX('02_Regles_Alertes'!$B$2:$B$18,MATCH($B57,'02_Regles_Alertes'!$A$2:$A$18,0))) -> Avant-coureur d'abandon | D57: =IF($B57="","",INDEX('02_Regles_Alertes'!$C$2:$C$18,MATCH($B57,'02_Regles_Alertes'!$A$2:$A$18,0))) -> ROUGE | E57: =IF($B57="","",INDEX('02_Regles_Alertes'!$D$2:$D$18,MATCH($B57,'02_Regles_Alertes'!$A$2:$A$18,0))) -> [A] | F57: =IF($B57="","",IF(INDEX('03_Matrice_Roles'!$E$51:$J$67,MATCH($B57,'03_Matrice_Roles'!$A$51:$A$67,0),$B$4)="D","Destinataire (action)","Informé")) -> Informé | G57: =IF($B57="","",INDEX('02_Regles_Alertes'!$F$2:$F$18,MATCH($B57,'02_Regles_Alertes'!$A$2:$A$18,0))) -> Retard de paiement > 60 j ET (cadence récente < 0,70 OU mobilisation < 70 %) | H57: =IF($B57="","",INDEX('02_Regles_Alertes'!$S$2:$S$18,MATCH($B57,'02_Regles_Alertes'!$A$2:$A$18,0))) -> Hebdomadaire | I57: =IF($B57="","",INDEX('02_Regles_Alertes'!$G$2:$G$18,MATCH($B57,'02_Regles_Alertes'!$A$2:$A$18,0))) -> C1 ET (C2 OU C3) | J57: =IF($B57="","",INDEX('02_Regles_Alertes'!$R$2:$R$18,MATCH($B57,'02_Regles_Alertes'!$A$2:$A$18,0))) -> Revue contractuelle immédiate ; plan de continuité
A58: =IF($B58="","",ROW()-56) -> 2 | B58: =IFERROR(INDEX('03_Matrice_Roles'!$A$51:$A$67,MATCH(ROW()-56,'03_Matrice_Roles'!$K$51:$K$67,0)),"") -> AL02 | C58: =IF($B58="","",INDEX('02_Regles_Alertes'!$B$2:$B$18,MATCH($B58,'02_Regles_Alertes'!$A$2:$A$18,0))) -> Emprise bloquée critique | D58: =IF($B58="","",INDEX('02_Regles_Alertes'!$C$2:$C$18,MATCH($B58,'02_Regles_Alertes'!$A$2:$A$18,0))) -> ROUGE | E58: =IF($B58="","",INDEX('02_Regles_Alertes'!$D$2:$D$18,MATCH($B58,'02_Regles_Alertes'!$A$2:$A$18,0))) -> [M] | F58: =IF($B58="","",IF(INDEX('03_Matrice_Roles'!$E$51:$J$67,MATCH($B58,'03_Matrice_Roles'!$A$51:$A$67,0),$B$4)="D","Destinataire (action)","Informé")) -> Informé | G58: =IF($B58="","",INDEX('02_Regles_Alertes'!$F$2:$F$18,MATCH($B58,'02_Regles_Alertes'!$A$2:$A$18,0))) -> Emprise libérée < 50 % ET délai consommé > 60 % ET aucun plan de déblocage validé | H58: =IF($B58="","",INDEX('02_Regles_Alertes'!$S$2:$S$18,MATCH($B58,'02_Regles_Alertes'!$A$2:$A$18,0))) -> Mensuelle | I58: =IF($B58="","",INDEX('02_Regles_Alertes'!$G$2:$G$18,MATCH($B58,'02_Regles_Alertes'!$A$2:$A$18,0))) -> C1 ET C2 ET C3 | J58: =IF($B58="","",INDEX('02_Regles_Alertes'!$R$2:$R$18,MATCH($B58,'02_Regles_Alertes'!$A$2:$A$18,0))) -> Escalade institutionnelle
A59: =IF($B59="","",ROW()-56) -> 3 | B59: =IFERROR(INDEX('03_Matrice_Roles'!$A$51:$A$67,MATCH(ROW()-56,'03_Matrice_Roles'!$K$51:$K$67,0)),"") -> AL03 | C59: =IF($B59="","",INDEX('02_Regles_Alertes'!$B$2:$B$18,MATCH($B59,'02_Regles_Alertes'!$A$2:$A$18,0))) -> Étranglement financier | D59: =IF($B59="","",INDEX('02_Regles_Alertes'!$C$2:$C$18,MATCH($B59,'02_Regles_Alertes'!$A$2:$A$18,0))) -> ROUGE | E59: =IF($B59="","",INDEX('02_Regles_Alertes'!$D$2:$D$18,MATCH($B59,'02_Regles_Alertes'!$A$2:$A$18,0))) -> [S] | F59: =IF($B59="","",IF(INDEX('03_Matrice_Roles'!$E$51:$J$67,MATCH($B59,'03_Matrice_Roles'!$A$51:$A$67,0),$B$4)="D","Destinataire (action)","Informé")) -> Informé | G59: =IF($B59="","",INDEX('02_Regles_Alertes'!$F$2:$F$18,MATCH($B59,'02_Regles_Alertes'!$A$2:$A$18,0))) -> Couverture du reste à faire < 90 % ET (réévaluation en attente > 120 j OU couverture des CP < 80 %) | H59: =IF($B59="","",INDEX('02_Regles_Alertes'!$S$2:$S$18,MATCH($B59,'02_Regles_Alertes'!$A$2:$A$18,0))) -> Mensuelle | I59: =IF($B59="","",INDEX('02_Regles_Alertes'!$G$2:$G$18,MATCH($B59,'02_Regles_Alertes'!$A$2:$A$18,0))) -> C1 ET (C2 OU C3) | J59: =IF($B59="","",INDEX('02_Regles_Alertes'!$R$2:$R$18,MATCH($B59,'02_Regles_Alertes'!$A$2:$A$18,0))) -> Arbitrage financement / réévaluation
A60: =IF($B60="","",ROW()-56) -> 4 | B60: =IFERROR(INDEX('03_Matrice_Roles'!$A$51:$A$67,MATCH(ROW()-56,'03_Matrice_Roles'!$K$51:$K$67,0)),"") -> AL06 | C60: =IF($B60="","",INDEX('02_Regles_Alertes'!$B$2:$B$18,MATCH($B60,'02_Regles_Alertes'!$A$2:$A$18,0))) -> Dérive de délai | D60: =IF($B60="","",INDEX('02_Regles_Alertes'!$C$2:$C$18,MATCH($B60,'02_Regles_Alertes'!$A$2:$A$18,0))) -> ROUGE | E60: =IF($B60="","",INDEX('02_Regles_Alertes'!$D$2:$D$18,MATCH($B60,'02_Regles_Alertes'!$A$2:$A$18,0))) -> [M] | F60: =IF($B60="","",IF(INDEX('03_Matrice_Roles'!$E$51:$J$67,MATCH($B60,'03_Matrice_Roles'!$A$51:$A$67,0),$B$4)="D","Destinataire (action)","Informé")) -> Informé | G60: =IF($B60="","",INDEX('02_Regles_Alertes'!$F$2:$F$18,MATCH($B60,'02_Regles_Alertes'!$A$2:$A$18,0))) -> Délai en vigueur dépassé ET indice d'avancement < 0,70 ET projet non achevé | H60: =IF($B60="","",INDEX('02_Regles_Alertes'!$S$2:$S$18,MATCH($B60,'02_Regles_Alertes'!$A$2:$A$18,0))) -> Mensuelle | I60: =IF($B60="","",INDEX('02_Regles_Alertes'!$G$2:$G$18,MATCH($B60,'02_Regles_Alertes'!$A$2:$A$18,0))) -> C1 ET C2 ET C3 | J60: =IF($B60="","",INDEX('02_Regles_Alertes'!$R$2:$R$18,MATCH($B60,'02_Regles_Alertes'!$A$2:$A$18,0))) -> Plan de rattrapage
A61: =IF($B61="","",ROW()-56) -> 5 | B61: =IFERROR(INDEX('03_Matrice_Roles'!$A$51:$A$67,MATCH(ROW()-56,'03_Matrice_Roles'!$K$51:$K$67,0)),"") -> AL08 | C61: =IF($B61="","",INDEX('02_Regles_Alertes'!$B$2:$B$18,MATCH($B61,'02_Regles_Alertes'!$A$2:$A$18,0))) -> Dérive d'AE | D61: =IF($B61="","",INDEX('02_Regles_Alertes'!$C$2:$C$18,MATCH($B61,'02_Regles_Alertes'!$A$2:$A$18,0))) -> ROUGE | E61: =IF($B61="","",INDEX('02_Regles_Alertes'!$D$2:$D$18,MATCH($B61,'02_Regles_Alertes'!$A$2:$A$18,0))) -> [M] | F61: =IF($B61="","",IF(INDEX('03_Matrice_Roles'!$E$51:$J$67,MATCH($B61,'03_Matrice_Roles'!$A$51:$A$67,0),$B$4)="D","Destinataire (action)","Informé")) -> Informé | G61: =IF($B61="","",INDEX('02_Regles_Alertes'!$F$2:$F$18,MATCH($B61,'02_Regles_Alertes'!$A$2:$A$18,0))) -> Dérive d'AE ajustée > 60 % ET réévaluation en attente > 60 j | H61: =IF($B61="","",INDEX('02_Regles_Alertes'!$S$2:$S$18,MATCH($B61,'02_Regles_Alertes'!$A$2:$A$18,0))) -> Mensuelle | I61: =IF($B61="","",INDEX('02_Regles_Alertes'!$G$2:$G$18,MATCH($B61,'02_Regles_Alertes'!$A$2:$A$18,0))) -> C1 ET C2 | J61: =IF($B61="","",INDEX('02_Regles_Alertes'!$R$2:$R$18,MATCH($B61,'02_Regles_Alertes'!$A$2:$A$18,0))) -> Analyse des causes et sécurisation de l'AE
A62: =IF($B62="","",ROW()-56) -> 6 | B62: =IFERROR(INDEX('03_Matrice_Roles'!$A$51:$A$67,MATCH(ROW()-56,'03_Matrice_Roles'!$K$51:$K$67,0)),"") -> AL13 | C62: =IF($B62="","",INDEX('02_Regles_Alertes'!$B$2:$B$18,MATCH($B62,'02_Regles_Alertes'!$A$2:$A$18,0))) -> Dérive de délai extrême | D62: =IF($B62="","",INDEX('02_Regles_Alertes'!$C$2:$C$18,MATCH($B62,'02_Regles_Alertes'!$A$2:$A$18,0))) -> ORANGE | E62: =IF($B62="","",INDEX('02_Regles_Alertes'!$D$2:$D$18,MATCH($B62,'02_Regles_Alertes'!$A$2:$A$18,0))) -> [M] | F62: =IF($B62="","",IF(INDEX('03_Matrice_Roles'!$E$51:$J$67,MATCH($B62,'03_Matrice_Roles'!$A$51:$A$67,0),$B$4)="D","Destinataire (action)","Informé")) -> Informé | G62: =IF($B62="","",INDEX('02_Regles_Alertes'!$F$2:$F$18,MATCH($B62,'02_Regles_Alertes'!$A$2:$A$18,0))) -> Délai en vigueur > 2 × le délai initial ET délai en vigueur dépassé | H62: =IF($B62="","",INDEX('02_Regles_Alertes'!$S$2:$S$18,MATCH($B62,'02_Regles_Alertes'!$A$2:$A$18,0))) -> Mensuelle | I62: =IF($B62="","",INDEX('02_Regles_Alertes'!$G$2:$G$18,MATCH($B62,'02_Regles_Alertes'!$A$2:$A$18,0))) -> C1 ET C2 | J62: =IF($B62="","",INDEX('02_Regles_Alertes'!$R$2:$R$18,MATCH($B62,'02_Regles_Alertes'!$A$2:$A$18,0))) -> Revue contractuelle : poursuite, résiliation ou réengagement
A63: =IF($B63="","",ROW()-56) -> 7 | B63: =IFERROR(INDEX('03_Matrice_Roles'!$A$51:$A$67,MATCH(ROW()-56,'03_Matrice_Roles'!$K$51:$K$67,0)),"") -> AL15 | C63: =IF($B63="","",INDEX('02_Regles_Alertes'!$B$2:$B$18,MATCH($B63,'02_Regles_Alertes'!$A$2:$A$18,0))) -> Arrêt prolongé | D63: =IF($B63="","",INDEX('02_Regles_Alertes'!$C$2:$C$18,MATCH($B63,'02_Regles_Alertes'!$A$2:$A$18,0))) -> ROUGE | E63: =IF($B63="","",INDEX('02_Regles_Alertes'!$D$2:$D$18,MATCH($B63,'02_Regles_Alertes'!$A$2:$A$18,0))) -> [M] | F63: =IF($B63="","",IF(INDEX('03_Matrice_Roles'!$E$51:$J$67,MATCH($B63,'03_Matrice_Roles'!$A$51:$A$67,0),$B$4)="D","Destinataire (action)","Informé")) -> Informé | G63: =IF($B63="","",INDEX('02_Regles_Alertes'!$F$2:$F$18,MATCH($B63,'02_Regles_Alertes'!$A$2:$A$18,0))) -> Temps perdu à l'arrêt > 15 % OU arrêt en cours depuis > 60 j | H63: =IF($B63="","",INDEX('02_Regles_Alertes'!$S$2:$S$18,MATCH($B63,'02_Regles_Alertes'!$A$2:$A$18,0))) -> Mensuelle | I63: =IF($B63="","",INDEX('02_Regles_Alertes'!$G$2:$G$18,MATCH($B63,'02_Regles_Alertes'!$A$2:$A$18,0))) -> C1 OU C2 | J63: =IF($B63="","",INDEX('02_Regles_Alertes'!$R$2:$R$18,MATCH($B63,'02_Regles_Alertes'!$A$2:$A$18,0))) -> Plan de reprise ; sécuriser les travaux déjà réalisés
A64: =IF($B64="","",ROW()-56) -> 8 | B64: =IFERROR(INDEX('03_Matrice_Roles'!$A$51:$A$67,MATCH(ROW()-56,'03_Matrice_Roles'!$K$51:$K$67,0)),"") -> AL17 | C64: =IF($B64="","",INDEX('02_Regles_Alertes'!$B$2:$B$18,MATCH($B64,'02_Regles_Alertes'!$A$2:$A$18,0))) -> Blocage ancien | D64: =IF($B64="","",INDEX('02_Regles_Alertes'!$C$2:$C$18,MATCH($B64,'02_Regles_Alertes'!$A$2:$A$18,0))) -> ORANGE | E64: =IF($B64="","",INDEX('02_Regles_Alertes'!$D$2:$D$18,MATCH($B64,'02_Regles_Alertes'!$A$2:$A$18,0))) -> [M] | F64: =IF($B64="","",IF(INDEX('03_Matrice_Roles'!$E$51:$J$67,MATCH($B64,'03_Matrice_Roles'!$A$51:$A$67,0),$B$4)="D","Destinataire (action)","Informé")) -> Informé | G64: =IF($B64="","",INDEX('02_Regles_Alertes'!$F$2:$F$18,MATCH($B64,'02_Regles_Alertes'!$A$2:$A$18,0))) -> Âge médian des blocages ouverts > 90 j | H64: =IF($B64="","",INDEX('02_Regles_Alertes'!$S$2:$S$18,MATCH($B64,'02_Regles_Alertes'!$A$2:$A$18,0))) -> Mensuelle | I64: =IF($B64="","",INDEX('02_Regles_Alertes'!$G$2:$G$18,MATCH($B64,'02_Regles_Alertes'!$A$2:$A$18,0))) -> C1 | J64: =IF($B64="","",INDEX('02_Regles_Alertes'!$R$2:$R$18,MATCH($B64,'02_Regles_Alertes'!$A$2:$A$18,0))) -> Escalade au niveau décisionnel
A65: =IF($B65="","",ROW()-56) | B65: =IFERROR(INDEX('03_Matrice_Roles'!$A$51:$A$67,MATCH(ROW()-56,'03_Matrice_Roles'!$K$51:$K$67,0)),"") | C65: =IF($B65="","",INDEX('02_Regles_Alertes'!$B$2:$B$18,MATCH($B65,'02_Regles_Alertes'!$A$2:$A$18,0))) | D65: =IF($B65="","",INDEX('02_Regles_Alertes'!$C$2:$C$18,MATCH($B65,'02_Regles_Alertes'!$A$2:$A$18,0))) | E65: =IF($B65="","",INDEX('02_Regles_Alertes'!$D$2:$D$18,MATCH($B65,'02_Regles_Alertes'!$A$2:$A$18,0))) | F65: =IF($B65="","",IF(INDEX('03_Matrice_Roles'!$E$51:$J$67,MATCH($B65,'03_Matrice_Roles'!$A$51:$A$67,0),$B$4)="D","Destinataire (action)","Informé")) | G65: =IF($B65="","",INDEX('02_Regles_Alertes'!$F$2:$F$18,MATCH($B65,'02_Regles_Alertes'!$A$2:$A$18,0))) | H65: =IF($B65="","",INDEX('02_Regles_Alertes'!$S$2:$S$18,MATCH($B65,'02_Regles_Alertes'!$A$2:$A$18,0))) | I65: =IF($B65="","",INDEX('02_Regles_Alertes'!$G$2:$G$18,MATCH($B65,'02_Regles_Alertes'!$A$2:$A$18,0))) | J65: =IF($B65="","",INDEX('02_Regles_Alertes'!$R$2:$R$18,MATCH($B65,'02_Regles_Alertes'!$A$2:$A$18,0)))
A66: =IF($B66="","",ROW()-56) | B66: =IFERROR(INDEX('03_Matrice_Roles'!$A$51:$A$67,MATCH(ROW()-56,'03_Matrice_Roles'!$K$51:$K$67,0)),"") | C66: =IF($B66="","",INDEX('02_Regles_Alertes'!$B$2:$B$18,MATCH($B66,'02_Regles_Alertes'!$A$2:$A$18,0))) | D66: =IF($B66="","",INDEX('02_Regles_Alertes'!$C$2:$C$18,MATCH($B66,'02_Regles_Alertes'!$A$2:$A$18,0))) | E66: =IF($B66="","",INDEX('02_Regles_Alertes'!$D$2:$D$18,MATCH($B66,'02_Regles_Alertes'!$A$2:$A$18,0))) | F66: =IF($B66="","",IF(INDEX('03_Matrice_Roles'!$E$51:$J$67,MATCH($B66,'03_Matrice_Roles'!$A$51:$A$67,0),$B$4)="D","Destinataire (action)","Informé")) | G66: =IF($B66="","",INDEX('02_Regles_Alertes'!$F$2:$F$18,MATCH($B66,'02_Regles_Alertes'!$A$2:$A$18,0))) | H66: =IF($B66="","",INDEX('02_Regles_Alertes'!$S$2:$S$18,MATCH($B66,'02_Regles_Alertes'!$A$2:$A$18,0))) | I66: =IF($B66="","",INDEX('02_Regles_Alertes'!$G$2:$G$18,MATCH($B66,'02_Regles_Alertes'!$A$2:$A$18,0))) | J66: =IF($B66="","",INDEX('02_Regles_Alertes'!$R$2:$R$18,MATCH($B66,'02_Regles_Alertes'!$A$2:$A$18,0)))
A67: =IF($B67="","",ROW()-56) | B67: =IFERROR(INDEX('03_Matrice_Roles'!$A$51:$A$67,MATCH(ROW()-56,'03_Matrice_Roles'!$K$51:$K$67,0)),"") | C67: =IF($B67="","",INDEX('02_Regles_Alertes'!$B$2:$B$18,MATCH($B67,'02_Regles_Alertes'!$A$2:$A$18,0))) | D67: =IF($B67="","",INDEX('02_Regles_Alertes'!$C$2:$C$18,MATCH($B67,'02_Regles_Alertes'!$A$2:$A$18,0))) | E67: =IF($B67="","",INDEX('02_Regles_Alertes'!$D$2:$D$18,MATCH($B67,'02_Regles_Alertes'!$A$2:$A$18,0))) | F67: =IF($B67="","",IF(INDEX('03_Matrice_Roles'!$E$51:$J$67,MATCH($B67,'03_Matrice_Roles'!$A$51:$A$67,0),$B$4)="D","Destinataire (action)","Informé")) | G67: =IF($B67="","",INDEX('02_Regles_Alertes'!$F$2:$F$18,MATCH($B67,'02_Regles_Alertes'!$A$2:$A$18,0))) | H67: =IF($B67="","",INDEX('02_Regles_Alertes'!$S$2:$S$18,MATCH($B67,'02_Regles_Alertes'!$A$2:$A$18,0))) | I67: =IF($B67="","",INDEX('02_Regles_Alertes'!$G$2:$G$18,MATCH($B67,'02_Regles_Alertes'!$A$2:$A$18,0))) | J67: =IF($B67="","",INDEX('02_Regles_Alertes'!$R$2:$R$18,MATCH($B67,'02_Regles_Alertes'!$A$2:$A$18,0)))
A68: =IF($B68="","",ROW()-56) | B68: =IFERROR(INDEX('03_Matrice_Roles'!$A$51:$A$67,MATCH(ROW()-56,'03_Matrice_Roles'!$K$51:$K$67,0)),"") | C68: =IF($B68="","",INDEX('02_Regles_Alertes'!$B$2:$B$18,MATCH($B68,'02_Regles_Alertes'!$A$2:$A$18,0))) | D68: =IF($B68="","",INDEX('02_Regles_Alertes'!$C$2:$C$18,MATCH($B68,'02_Regles_Alertes'!$A$2:$A$18,0))) | E68: =IF($B68="","",INDEX('02_Regles_Alertes'!$D$2:$D$18,MATCH($B68,'02_Regles_Alertes'!$A$2:$A$18,0))) | F68: =IF($B68="","",IF(INDEX('03_Matrice_Roles'!$E$51:$J$67,MATCH($B68,'03_Matrice_Roles'!$A$51:$A$67,0),$B$4)="D","Destinataire (action)","Informé")) | G68: =IF($B68="","",INDEX('02_Regles_Alertes'!$F$2:$F$18,MATCH($B68,'02_Regles_Alertes'!$A$2:$A$18,0))) | H68: =IF($B68="","",INDEX('02_Regles_Alertes'!$S$2:$S$18,MATCH($B68,'02_Regles_Alertes'!$A$2:$A$18,0))) | I68: =IF($B68="","",INDEX('02_Regles_Alertes'!$G$2:$G$18,MATCH($B68,'02_Regles_Alertes'!$A$2:$A$18,0))) | J68: =IF($B68="","",INDEX('02_Regles_Alertes'!$R$2:$R$18,MATCH($B68,'02_Regles_Alertes'!$A$2:$A$18,0)))
... A73: =IF($B73="","",ROW()-56) | B73: =IFERROR(INDEX('03_Matrice_Roles'!$A$51:$A$67,MATCH(ROW()-56,'03_Matrice_Roles'!$K$51:$K$67,0)),"") | C73: =IF($B73="","",INDEX('02_Regles_Alertes'!$B$2:$B$18,MATCH($B73,'02_Regles_Alertes'!$A$2:$A$18,0))) | D73: =IF($B73="","",INDEX('02_Regles_Alertes'!$C$2:$C$18,MATCH($B73,'02_Regles_Alertes'!$A$2:$A$18,0))) | E73: =IF($B73="","",INDEX('02_Regles_Alertes'!$D$2:$D$18,MATCH($B73,'02_Regles_Alertes'!$A$2:$A$18,0))) | F73: =IF($B73="","",IF(INDEX('03_Matrice_Roles'!$E$51:$J$67,MATCH($B73,'03_Matrice_Roles'!$A$51:$A$67,0),$B$4)="D","Destinataire (action)","Informé")) | G73: =IF($B73="","",INDEX('02_Regles_Alertes'!$F$2:$F$18,MATCH($B73,'02_Regles_Alertes'!$A$2:$A$18,0))) | H73: =IF($B73="","",INDEX('02_Regles_Alertes'!$S$2:$S$18,MATCH($B73,'02_Regles_Alertes'!$A$2:$A$18,0))) | I73: =IF($B73="","",INDEX('02_Regles_Alertes'!$G$2:$G$18,MATCH($B73,'02_Regles_Alertes'!$A$2:$A$18,0))) | J73: =IF($B73="","",INDEX('02_Regles_Alertes'!$R$2:$R$18,MATCH($B73,'02_Regles_Alertes'!$A$2:$A$18,0)))

Sheet 05_Synthese
A1: Synthèse du référentiel
A3: Famille | B3: [M] Obligatoire | C3: [A] Avancé | D3: [S] Stratégique | E3: Total
A4: AV – Avancement physique | B4: =SUMPRODUCT(('01_KPI'!$B$2:$B$44=$A4)*('01_KPI'!$D$2:$D$44="[M]")) -> 2 | C4: =SUMPRODUCT(('01_KPI'!$B$2:$B$44=$A4)*('01_KPI'!$D$2:$D$44="[A]")) -> 2 | D4: =SUMPRODUCT(('01_KPI'!$B$2:$B$44=$A4)*('01_KPI'!$D$2:$D$44="[S]")) -> 1 | E4: =SUM(B4:D4) -> 5
A5: FI – Finance | B5: =SUMPRODUCT(('01_KPI'!$B$2:$B$44=$A5)*('01_KPI'!$D$2:$D$44="[M]")) -> 3 | C5: =SUMPRODUCT(('01_KPI'!$B$2:$B$44=$A5)*('01_KPI'!$D$2:$D$44="[A]")) -> 2 | D5: =SUMPRODUCT(('01_KPI'!$B$2:$B$44=$A5)*('01_KPI'!$D$2:$D$44="[S]")) -> 2 | E5: =SUM(B5:D5) -> 7
A6: DL – Délais | B6: =SUMPRODUCT(('01_KPI'!$B$2:$B$44=$A6)*('01_KPI'!$D$2:$D$44="[M]")) -> 3 | C6: =SUMPRODUCT(('01_KPI'!$B$2:$B$44=$A6)*('01_KPI'!$D$2:$D$44="[A]")) -> 0 | D6: =SUMPRODUCT(('01_KPI'!$B$2:$B$44=$A6)*('01_KPI'!$D$2:$D$44="[S]")) -> 1 | E6: =SUM(B6:D6) -> 4
A7: BU – Coût et avenants | B7: =SUMPRODUCT(('01_KPI'!$B$2:$B$44=$A7)*('01_KPI'!$D$2:$D$44="[M]")) -> 1 | C7: =SUMPRODUCT(('01_KPI'!$B$2:$B$44=$A7)*('01_KPI'!$D$2:$D$44="[A]")) -> 1 | D7: =SUMPRODUCT(('01_KPI'!$B$2:$B$44=$A7)*('01_KPI'!$D$2:$D$44="[S]")) -> 1 | E7: =SUM(B7:D7) -> 3
A8: QR – Blocages, qualité, risques | B8: =SUMPRODUCT(('01_KPI'!$B$2:$B$44=$A8)*('01_KPI'!$D$2:$D$44="[M]")) -> 4 | C8: =SUMPRODUCT(('01_KPI'!$B$2:$B$44=$A8)*('01_KPI'!$D$2:$D$44="[A]")) -> 4 | D8: =SUMPRODUCT(('01_KPI'!$B$2:$B$44=$A8)*('01_KPI'!$D$2:$D$44="[S]")) -> 0 | E8: =SUM(B8:D8) -> 8
A9: DO – Fiabilité des données | B9: =SUMPRODUCT(('01_KPI'!$B$2:$B$44=$A9)*('01_KPI'!$D$2:$D$44="[M]")) -> 3 | C9: =SUMPRODUCT(('01_KPI'!$B$2:$B$44=$A9)*('01_KPI'!$D$2:$D$44="[A]")) -> 0 | D9: =SUMPRODUCT(('01_KPI'!$B$2:$B$44=$A9)*('01_KPI'!$D$2:$D$44="[S]")) -> 0 | E9: =SUM(B9:D9) -> 3
A10: PP – Terrain (planification fiable) | B10: =SUMPRODUCT(('01_KPI'!$B$2:$B$44=$A10)*('01_KPI'!$D$2:$D$44="[M]")) -> 0 | C10: =SUMPRODUCT(('01_KPI'!$B$2:$B$44=$A10)*('01_KPI'!$D$2:$D$44="[A]")) -> 3 | D10: =SUMPRODUCT(('01_KPI'!$B$2:$B$44=$A10)*('01_KPI'!$D$2:$D$44="[S]")) -> 0 | E10: =SUM(B10:D10) -> 3
A11: CO – Contractants et portefeuille | B11: =SUMPRODUCT(('01_KPI'!$B$2:$B$44=$A11)*('01_KPI'!$D$2:$D$44="[M]")) -> 2 | C11: =SUMPRODUCT(('01_KPI'!$B$2:$B$44=$A11)*('01_KPI'!$D$2:$D$44="[A]")) -> 0 | D11: =SUMPRODUCT(('01_KPI'!$B$2:$B$44=$A11)*('01_KPI'!$D$2:$D$44="[S]")) -> 4 | E11: =SUM(B11:D11) -> 6
A12: GV – Gouvernance | B12: =SUMPRODUCT(('01_KPI'!$B$2:$B$44=$A12)*('01_KPI'!$D$2:$D$44="[M]")) -> 2 | C12: =SUMPRODUCT(('01_KPI'!$B$2:$B$44=$A12)*('01_KPI'!$D$2:$D$44="[A]")) -> 2 | D12: =SUMPRODUCT(('01_KPI'!$B$2:$B$44=$A12)*('01_KPI'!$D$2:$D$44="[S]")) -> 0 | E12: =SUM(B12:D12) -> 4
A13: Total | B13: =SUM(B4:B12) -> 20 | C13: =SUM(C4:C12) -> 14 | D13: =SUM(D4:D12) -> 9 | E13: =SUM(E4:E12) -> 43
A16: Phase | B16: [M] Obligatoire | C16: [A] Avancé | D16: [S] Stratégique | E16: Total
A17: MVP | B17: =SUMPRODUCT(('01_KPI'!$E$2:$E$44=$A17)*('01_KPI'!$D$2:$D$44="[M]")) -> 20 | C17: =SUMPRODUCT(('01_KPI'!$E$2:$E$44=$A17)*('01_KPI'!$D$2:$D$44="[A]")) -> 3 | D17: =SUMPRODUCT(('01_KPI'!$E$2:$E$44=$A17)*('01_KPI'!$D$2:$D$44="[S]")) -> 3 | E17: =SUM(B17:D17) -> 26
A18: V2 | B18: =SUMPRODUCT(('01_KPI'!$E$2:$E$44=$A18)*('01_KPI'!$D$2:$D$44="[M]")) -> 0 | C18: =SUMPRODUCT(('01_KPI'!$E$2:$E$44=$A18)*('01_KPI'!$D$2:$D$44="[A]")) -> 10 | D18: =SUMPRODUCT(('01_KPI'!$E$2:$E$44=$A18)*('01_KPI'!$D$2:$D$44="[S]")) -> 6 | E18: =SUM(B18:D18) -> 16
A19: Vision | B19: =SUMPRODUCT(('01_KPI'!$E$2:$E$44=$A19)*('01_KPI'!$D$2:$D$44="[M]")) -> 0 | C19: =SUMPRODUCT(('01_KPI'!$E$2:$E$44=$A19)*('01_KPI'!$D$2:$D$44="[A]")) -> 1 | D19: =SUMPRODUCT(('01_KPI'!$E$2:$E$44=$A19)*('01_KPI'!$D$2:$D$44="[S]")) -> 0 | E19: =SUM(B19:D19) -> 1
A22: Calculabilité (début de libellé) | B22: Nombre de KPI
A23: Calculable sur fiches CNED | B23: =COUNTIF('01_KPI'!$F$2:$F$44,"Calculable sur fiches CNED") -> 8
A24: Calculable par la plateforme | B24: =COUNTIF('01_KPI'!$F$2:$F$44,"Calculable par la plateforme") -> 3
A25: Partiel (…) | B25: =COUNTIF('01_KPI'!$F$2:$F$44,"Partiel*") -> 16
A26: Saisie requise | B26: =COUNTIF('01_KPI'!$F$2:$F$44,"Saisie requise") -> 16
A28: Contrôle : total des KPI = 43 | B28: =IF(COUNTA('01_KPI'!$A$2:$A$44)=43,"OK","ÉCART") -> OK
A29: Contrôle : somme des familles = nombre de KPI | B29: =IF(E13=COUNTA('01_KPI'!$A$2:$A$44),"OK","ÉCART") -> OK
A32: Règles d'alertes | B32: [M] Obligatoire | C32: [A] Avancé | D32: [S] Stratégique | E32: Total
A33: ROUGE | B33: =SUMPRODUCT(('02_Regles_Alertes'!$C$2:$C$18=$A33)*('02_Regles_Alertes'!$D$2:$D$18="[M]")) -> 4 | C33: =SUMPRODUCT(('02_Regles_Alertes'!$C$2:$C$18=$A33)*('02_Regles_Alertes'!$D$2:$D$18="[A]")) -> 3 | D33: =SUMPRODUCT(('02_Regles_Alertes'!$C$2:$C$18=$A33)*('02_Regles_Alertes'!$D$2:$D$18="[S]")) -> 1 | E33: =SUM(B33:D33) -> 8
A34: ORANGE | B34: =SUMPRODUCT(('02_Regles_Alertes'!$C$2:$C$18=$A34)*('02_Regles_Alertes'!$D$2:$D$18="[M]")) -> 5 | C34: =SUMPRODUCT(('02_Regles_Alertes'!$C$2:$C$18=$A34)*('02_Regles_Alertes'!$D$2:$D$18="[A]")) -> 4 | D34: =SUMPRODUCT(('02_Regles_Alertes'!$C$2:$C$18=$A34)*('02_Regles_Alertes'!$D$2:$D$18="[S]")) -> 0 | E34: =SUM(B34:D34) -> 9
A35: Total | B35: =SUM(B33:B34) -> 9 | C35: =SUM(C33:C34) -> 7 | D35: =SUM(D33:D34) -> 1 | E35: =SUM(E33:E34) -> 17
A36: Contrôle : règles = 17 | B36: =IF(E35=17,"OK","ÉCART") -> OK
A39: Rôle | B39: R (responsable) | C39: S (alimente) | D39: V (consulte) | E39: Total KPI visibles | F39: Alertes : destinataire | G39: Alertes : informé
A40: Direction CNED (décideur) | B40: =COUNTIF('03_Matrice_Roles'!E$4:E$46,"R") -> 0 | C40: =COUNTIF('03_Matrice_Roles'!E$4:E$46,"S") -> 0 | D40: =COUNTIF('03_Matrice_Roles'!E$4:E$46,"V") -> 22 | E40: =SUM(B40:D40) -> 22 | F40: =COUNTIF('03_Matrice_Roles'!E$51:E$67,"D") -> 0 | G40: =COUNTIF('03_Matrice_Roles'!E$51:E$67,"I") -> 8
A41: CNED / PMO (analyste) | B41: =COUNTIF('03_Matrice_Roles'!F$4:F$46,"R") -> 18 | C41: =COUNTIF('03_Matrice_Roles'!F$4:F$46,"S") -> 2 | D41: =COUNTIF('03_Matrice_Roles'!F$4:F$46,"V") -> 23 | E41: =SUM(B41:D41) -> 43 | F41: =COUNTIF('03_Matrice_Roles'!F$51:F$67,"D") -> 10 | G41: =COUNTIF('03_Matrice_Roles'!F$51:F$67,"I") -> 7
A42: Maître d'ouvrage (MO) | B42: =COUNTIF('03_Matrice_Roles'!G$4:G$46,"R") -> 18 | C42: =COUNTIF('03_Matrice_Roles'!G$4:G$46,"S") -> 4 | D42: =COUNTIF('03_Matrice_Roles'!G$4:G$46,"V") -> 18 | E42: =SUM(B42:D42) -> 40 | F42: =COUNTIF('03_Matrice_Roles'!G$51:G$67,"D") -> 12 | G42: =COUNTIF('03_Matrice_Roles'!G$51:G$67,"I") -> 4
A43: Bureau d'études (BET) / contrôle | B43: =COUNTIF('03_Matrice_Roles'!H$4:H$46,"R") -> 3 | C43: =COUNTIF('03_Matrice_Roles'!H$4:H$46,"S") -> 4 | D43: =COUNTIF('03_Matrice_Roles'!H$4:H$46,"V") -> 17 | E43: =SUM(B43:D43) -> 24 | F43: =COUNTIF('03_Matrice_Roles'!H$51:H$67,"D") -> 2 | G43: =COUNTIF('03_Matrice_Roles'!H$51:H$67,"I") -> 1
A44: Contractant (entreprise) | B44: =COUNTIF('03_Matrice_Roles'!I$4:I$46,"R") -> 0 | C44: =COUNTIF('03_Matrice_Roles'!I$4:I$46,"S") -> 3 | D44: =COUNTIF('03_Matrice_Roles'!I$4:I$46,"V") -> 21 | E44: =SUM(B44:D44) -> 24 | F44: =COUNTIF('03_Matrice_Roles'!I$51:I$67,"D") -> 1 | G44: =COUNTIF('03_Matrice_Roles'!I$51:I$67,"I") -> 5
A45: Contrôleur budgétaire (Finance) | B45: =COUNTIF('03_Matrice_Roles'!J$4:J$46,"R") -> 4 | C45: =COUNTIF('03_Matrice_Roles'!J$4:J$46,"S") -> 3 | D45: =COUNTIF('03_Matrice_Roles'!J$4:J$46,"V") -> 10 | E45: =SUM(B45:D45) -> 17 | F45: =COUNTIF('03_Matrice_Roles'!J$51:J$67,"D") -> 3 | G45: =COUNTIF('03_Matrice_Roles'!J$51:J$67,"I") -> 0

Sheet 06_Simulateur
A1: Simulateur de seuils — saisir un KPI_ID (liste) et une valeur dans l'unité du KPI
A2: Les exemples ci-dessous utilisent des chiffres des fiches CNED (juin 2025). Les lignes sans KPI_ID sont libres (exemple : ajoutez votre cas). Valeurs en bleu = saisies.
A3: KPI_ID | B3: Cas / commentaire | C3: Valeur saisie | D3: Nom_KPI | E3: Importance | F3: Sens | G3: Seuil_Vert | H3: Seuil_Rouge | I3: Unité | J3: Statut
A4: AV2 | B4: Djendjen : avancement 62 % pour 91 % du délai consommé | C4: =62/91 -> 0.68131868 | D4: =IF($A4="","",IFERROR(IF(INDEX('01_KPI'!$C$2:$C$44,MATCH($A4,'01_KPI'!$A$2:$A$44,0))="","",INDEX('01_KPI'!$C$2:$C$44,MATCH($A4,'01_KPI'!$A$2:$A$44,0))),"KPI_ID inconnu")) -> Indice d'avancement | E4: =IF($A4="","",IFERROR(IF(INDEX('01_KPI'!$D$2:$D$44,MATCH($A4,'01_KPI'!$A$2:$A$44,0))="","",INDEX('01_KPI'!$D$2:$D$44,MATCH($A4,'01_KPI'!$A$2:$A$44,0))),"KPI_ID inconnu")) -> [M] | F4: =IF($A4="","",IFERROR(IF(INDEX('01_KPI'!$J$2:$J$44,MATCH($A4,'01_KPI'!$A$2:$A$44,0))="","",INDEX('01_KPI'!$J$2:$J$44,MATCH($A4,'01_KPI'!$A$2:$A$44,0))),"KPI_ID inconnu")) -> Plus haut = mieux | G4: =IF($A4="","",IFERROR(IF(INDEX('01_KPI'!$K$2:$K$44,MATCH($A4,'01_KPI'!$A$2:$A$44,0))="","",INDEX('01_KPI'!$K$2:$K$44,MATCH($A4,'01_KPI'!$A$2:$A$44,0))),"KPI_ID inconnu")) -> 0.9 | H4: =IF($A4="","",IFERROR(IF(INDEX('01_KPI'!$L$2:$L$44,MATCH($A4,'01_KPI'!$A$2:$A$44,0))="","",INDEX('01_KPI'!$L$2:$L$44,MATCH($A4,'01_KPI'!$A$2:$A$44,0))),"KPI_ID inconnu")) -> 0.7 | I4: =IF($A4="","",IFERROR(IF(INDEX('01_KPI'!$I$2:$I$44,MATCH($A4,'01_KPI'!$A$2:$A$44,0))="","",INDEX('01_KPI'!$I$2:$I$44,MATCH($A4,'01_KPI'!$A$2:$A$44,0))),"KPI_ID inconnu")) -> ratio | J4: =IF(OR($A4="",$C4=""),"",IF(OR($F4="Information",$F4="Règle spéciale"),"Hors seuil numérique",IF($F4="Plus haut = mieux",IF($C4>=$G4,"VERT",IF($C4>=$H4,"ORANGE","ROUGE")),IF($F4="Plus bas = mieux",IF($C4<=$G4,"VERT",IF($C4<=$H4,"ORANGE","ROUGE")),IF(ABS($C4)<=$G4,"VERT",IF(ABS($C4)<=$H4,"ORANGE","ROUGE")))))) -> ROUGE
A5: AV2 | B5: Liaison port d'Oran : avancement 99,98 % pour 95,5 % du délai | C5: =99.98/95.5 -> 1.046911 | D5: =IF($A5="","",IFERROR(IF(INDEX('01_KPI'!$C$2:$C$44,MATCH($A5,'01_KPI'!$A$2:$A$44,0))="","",INDEX('01_KPI'!$C$2:$C$44,MATCH($A5,'01_KPI'!$A$2:$A$44,0))),"KPI_ID inconnu")) -> Indice d'avancement | E5: =IF($A5="","",IFERROR(IF(INDEX('01_KPI'!$D$2:$D$44,MATCH($A5,'01_KPI'!$A$2:$A$44,0))="","",INDEX('01_KPI'!$D$2:$D$44,MATCH($A5,'01_KPI'!$A$2:$A$44,0))),"KPI_ID inconnu")) -> [M] | F5: =IF($A5="","",IFERROR(IF(INDEX('01_KPI'!$J$2:$J$44,MATCH($A5,'01_KPI'!$A$2:$A$44,0))="","",INDEX('01_KPI'!$J$2:$J$44,MATCH($A5,'01_KPI'!$A$2:$A$44,0))),"KPI_ID inconnu")) -> Plus haut = mieux | G5: =IF($A5="","",IFERROR(IF(INDEX('01_KPI'!$K$2:$K$44,MATCH($A5,'01_KPI'!$A$2:$A$44,0))="","",INDEX('01_KPI'!$K$2:$K$44,MATCH($A5,'01_KPI'!$A$2:$A$44,0))),"KPI_ID inconnu")) -> 0.9 | H5: =IF($A5="","",IFERROR(IF(INDEX('01_KPI'!$L$2:$L$44,MATCH($A5,'01_KPI'!$A$2:$A$44,0))="","",INDEX('01_KPI'!$L$2:$L$44,MATCH($A5,'01_KPI'!$A$2:$A$44,0))),"KPI_ID inconnu")) -> 0.7 | I5: =IF($A5="","",IFERROR(IF(INDEX('01_KPI'!$I$2:$I$44,MATCH($A5,'01_KPI'!$A$2:$A$44,0))="","",INDEX('01_KPI'!$I$2:$I$44,MATCH($A5,'01_KPI'!$A$2:$A$44,0))),"KPI_ID inconnu")) -> ratio | J5: =IF(OR($A5="",$C5=""),"",IF(OR($F5="Information",$F5="Règle spéciale"),"Hors seuil numérique",IF($F5="Plus haut = mieux",IF($C5>=$G5,"VERT",IF($C5>=$H5,"ORANGE","ROUGE")),IF($F5="Plus bas = mieux",IF($C5<=$G5,"VERT",IF($C5<=$H5,"ORANGE","ROUGE")),IF(ABS($C5)<=$G5,"VERT",IF(ABS($C5)<=$H5,"ORANGE","ROUGE")))))) -> VERT
A6: DL2 | B6: Djendjen : délai 36 mois initial → 138 mois en vigueur | C6: =138/36 -> 3.8333333 | D6: =IF($A6="","",IFERROR(IF(INDEX('01_KPI'!$C$2:$C$44,MATCH($A6,'01_KPI'!$A$2:$A$44,0))="","",INDEX('01_KPI'!$C$2:$C$44,MATCH($A6,'01_KPI'!$A$2:$A$44,0))),"KPI_ID inconnu")) -> Dérive de délai par avenants | E6: =IF($A6="","",IFERROR(IF(INDEX('01_KPI'!$D$2:$D$44,MATCH($A6,'01_KPI'!$A$2:$A$44,0))="","",INDEX('01_KPI'!$D$2:$D$44,MATCH($A6,'01_KPI'!$A$2:$A$44,0))),"KPI_ID inconnu")) -> [M] | F6: =IF($A6="","",IFERROR(IF(INDEX('01_KPI'!$J$2:$J$44,MATCH($A6,'01_KPI'!$A$2:$A$44,0))="","",INDEX('01_KPI'!$J$2:$J$44,MATCH($A6,'01_KPI'!$A$2:$A$44,0))),"KPI_ID inconnu")) -> Plus bas = mieux | G6: =IF($A6="","",IFERROR(IF(INDEX('01_KPI'!$K$2:$K$44,MATCH($A6,'01_KPI'!$A$2:$A$44,0))="","",INDEX('01_KPI'!$K$2:$K$44,MATCH($A6,'01_KPI'!$A$2:$A$44,0))),"KPI_ID inconnu")) -> 1.25 | H6: =IF($A6="","",IFERROR(IF(INDEX('01_KPI'!$L$2:$L$44,MATCH($A6,'01_KPI'!$A$2:$A$44,0))="","",INDEX('01_KPI'!$L$2:$L$44,MATCH($A6,'01_KPI'!$A$2:$A$44,0))),"KPI_ID inconnu")) -> 2 | I6: =IF($A6="","",IFERROR(IF(INDEX('01_KPI'!$I$2:$I$44,MATCH($A6,'01_KPI'!$A$2:$A$44,0))="","",INDEX('01_KPI'!$I$2:$I$44,MATCH($A6,'01_KPI'!$A$2:$A$44,0))),"KPI_ID inconnu")) -> ratio | J6: =IF(OR($A6="",$C6=""),"",IF(OR($F6="Information",$F6="Règle spéciale"),"Hors seuil numérique",IF($F6="Plus haut = mieux",IF($C6>=$G6,"VERT",IF($C6>=$H6,"ORANGE","ROUGE")),IF($F6="Plus bas = mieux",IF($C6<=$G6,"VERT",IF($C6<=$H6,"ORANGE","ROUGE")),IF(ABS($C6)<=$G6,"VERT",IF(ABS($C6)<=$H6,"ORANGE","ROUGE")))))) -> ROUGE
A7: DL2 | B7: Liaison port d'Oran : 30 mois → 131 mois | C7: =131/30 -> 4.3666667 | D7: =IF($A7="","",IFERROR(IF(INDEX('01_KPI'!$C$2:$C$44,MATCH($A7,'01_KPI'!$A$2:$A$44,0))="","",INDEX('01_KPI'!$C$2:$C$44,MATCH($A7,'01_KPI'!$A$2:$A$44,0))),"KPI_ID inconnu")) -> Dérive de délai par avenants | E7: =IF($A7="","",IFERROR(IF(INDEX('01_KPI'!$D$2:$D$44,MATCH($A7,'01_KPI'!$A$2:$A$44,0))="","",INDEX('01_KPI'!$D$2:$D$44,MATCH($A7,'01_KPI'!$A$2:$A$44,0))),"KPI_ID inconnu")) -> [M] | F7: =IF($A7="","",IFERROR(IF(INDEX('01_KPI'!$J$2:$J$44,MATCH($A7,'01_KPI'!$A$2:$A$44,0))="","",INDEX('01_KPI'!$J$2:$J$44,MATCH($A7,'01_KPI'!$A$2:$A$44,0))),"KPI_ID inconnu")) -> Plus bas = mieux | G7: =IF($A7="","",IFERROR(IF(INDEX('01_KPI'!$K$2:$K$44,MATCH($A7,'01_KPI'!$A$2:$A$44,0))="","",INDEX('01_KPI'!$K$2:$K$44,MATCH($A7,'01_KPI'!$A$2:$A$44,0))),"KPI_ID inconnu")) -> 1.25 | H7: =IF($A7="","",IFERROR(IF(INDEX('01_KPI'!$L$2:$L$44,MATCH($A7,'01_KPI'!$A$2:$A$44,0))="","",INDEX('01_KPI'!$L$2:$L$44,MATCH($A7,'01_KPI'!$A$2:$A$44,0))),"KPI_ID inconnu")) -> 2 | I7: =IF($A7="","",IFERROR(IF(INDEX('01_KPI'!$I$2:$I$44,MATCH($A7,'01_KPI'!$A$2:$A$44,0))="","",INDEX('01_KPI'!$I$2:$I$44,MATCH($A7,'01_KPI'!$A$2:$A$44,0))),"KPI_ID inconnu")) -> ratio | J7: =IF(OR($A7="",$C7=""),"",IF(OR($F7="Information",$F7="Règle spéciale"),"Hors seuil numérique",IF($F7="Plus haut = mieux",IF($C7>=$G7,"VERT",IF($C7>=$H7,"ORANGE","ROUGE")),IF($F7="Plus bas = mieux",IF($C7<=$G7,"VERT",IF($C7<=$H7,"ORANGE","ROUGE")),IF(ABS($C7)<=$G7,"VERT",IF(ABS($C7)<=$H7,"ORANGE","ROUGE")))))) -> ROUGE
A8: FI4 | B8: Djendjen : AE 90 → 214,375 Md DA | C8: =(214.375/90-1)*100 -> 138.19444 | D8: =IF($A8="","",IFERROR(IF(INDEX('01_KPI'!$C$2:$C$44,MATCH($A8,'01_KPI'!$A$2:$A$44,0))="","",INDEX('01_KPI'!$C$2:$C$44,MATCH($A8,'01_KPI'!$A$2:$A$44,0))),"KPI_ID inconnu")) -> Dérive d'AE ajustée | E8: =IF($A8="","",IFERROR(IF(INDEX('01_KPI'!$D$2:$D$44,MATCH($A8,'01_KPI'!$A$2:$A$44,0))="","",INDEX('01_KPI'!$D$2:$D$44,MATCH($A8,'01_KPI'!$A$2:$A$44,0))),"KPI_ID inconnu")) -> [M] | F8: =IF($A8="","",IFERROR(IF(INDEX('01_KPI'!$J$2:$J$44,MATCH($A8,'01_KPI'!$A$2:$A$44,0))="","",INDEX('01_KPI'!$J$2:$J$44,MATCH($A8,'01_KPI'!$A$2:$A$44,0))),"KPI_ID inconnu")) -> Plus bas = mieux | G8: =IF($A8="","",IFERROR(IF(INDEX('01_KPI'!$K$2:$K$44,MATCH($A8,'01_KPI'!$A$2:$A$44,0))="","",INDEX('01_KPI'!$K$2:$K$44,MATCH($A8,'01_KPI'!$A$2:$A$44,0))),"KPI_ID inconnu")) -> 20 | H8: =IF($A8="","",IFERROR(IF(INDEX('01_KPI'!$L$2:$L$44,MATCH($A8,'01_KPI'!$A$2:$A$44,0))="","",INDEX('01_KPI'!$L$2:$L$44,MATCH($A8,'01_KPI'!$A$2:$A$44,0))),"KPI_ID inconnu")) -> 60 | I8: =IF($A8="","",IFERROR(IF(INDEX('01_KPI'!$I$2:$I$44,MATCH($A8,'01_KPI'!$A$2:$A$44,0))="","",INDEX('01_KPI'!$I$2:$I$44,MATCH($A8,'01_KPI'!$A$2:$A$44,0))),"KPI_ID inconnu")) -> % | J8: =IF(OR($A8="",$C8=""),"",IF(OR($F8="Information",$F8="Règle spéciale"),"Hors seuil numérique",IF($F8="Plus haut = mieux",IF($C8>=$G8,"VERT",IF($C8>=$H8,"ORANGE","ROUGE")),IF($F8="Plus bas = mieux",IF($C8<=$G8,"VERT",IF($C8<=$H8,"ORANGE","ROUGE")),IF(ABS($C8)<=$G8,"VERT",IF(ABS($C8)<=$H8,"ORANGE","ROUGE")))))) -> ROUGE
A9: FI4 | B9: Pénétrante Béjaïa : AE 190 → 169,102 Md DA (baisse) | C9: =(169.102/190-1)*100 -> -10.998947 | D9: =IF($A9="","",IFERROR(IF(INDEX('01_KPI'!$C$2:$C$44,MATCH($A9,'01_KPI'!$A$2:$A$44,0))="","",INDEX('01_KPI'!$C$2:$C$44,MATCH($A9,'01_KPI'!$A$2:$A$44,0))),"KPI_ID inconnu")) -> Dérive d'AE ajustée | E9: =IF($A9="","",IFERROR(IF(INDEX('01_KPI'!$D$2:$D$44,MATCH($A9,'01_KPI'!$A$2:$A$44,0))="","",INDEX('01_KPI'!$D$2:$D$44,MATCH($A9,'01_KPI'!$A$2:$A$44,0))),"KPI_ID inconnu")) -> [M] | F9: =IF($A9="","",IFERROR(IF(INDEX('01_KPI'!$J$2:$J$44,MATCH($A9,'01_KPI'!$A$2:$A$44,0))="","",INDEX('01_KPI'!$J$2:$J$44,MATCH($A9,'01_KPI'!$A$2:$A$44,0))),"KPI_ID inconnu")) -> Plus bas = mieux | G9: =IF($A9="","",IFERROR(IF(INDEX('01_KPI'!$K$2:$K$44,MATCH($A9,'01_KPI'!$A$2:$A$44,0))="","",INDEX('01_KPI'!$K$2:$K$44,MATCH($A9,'01_KPI'!$A$2:$A$44,0))),"KPI_ID inconnu")) -> 20 | H9: =IF($A9="","",IFERROR(IF(INDEX('01_KPI'!$L$2:$L$44,MATCH($A9,'01_KPI'!$A$2:$A$44,0))="","",INDEX('01_KPI'!$L$2:$L$44,MATCH($A9,'01_KPI'!$A$2:$A$44,0))),"KPI_ID inconnu")) -> 60 | I9: =IF($A9="","",IFERROR(IF(INDEX('01_KPI'!$I$2:$I$44,MATCH($A9,'01_KPI'!$A$2:$A$44,0))="","",INDEX('01_KPI'!$I$2:$I$44,MATCH($A9,'01_KPI'!$A$2:$A$44,0))),"KPI_ID inconnu")) -> % | J9: =IF(OR($A9="",$C9=""),"",IF(OR($F9="Information",$F9="Règle spéciale"),"Hors seuil numérique",IF($F9="Plus haut = mieux",IF($C9>=$G9,"VERT",IF($C9>=$H9,"ORANGE","ROUGE")),IF($F9="Plus bas = mieux",IF($C9<=$G9,"VERT",IF($C9<=$H9,"ORANGE","ROUGE")),IF(ABS($C9)<=$G9,"VERT",IF(ABS($C9)<=$H9,"ORANGE","ROUGE")))))) -> VERT
A10: FI1 | B10: Djendjen : TAP 62 % vs taux financier 61,32 % | C10: =62-61.32 -> 0.68 | D10: =IF($A10="","",IFERROR(IF(INDEX('01_KPI'!$C$2:$C$44,MATCH($A10,'01_KPI'!$A$2:$A$44,0))="","",INDEX('01_KPI'!$C$2:$C$44,MATCH($A10,'01_KPI'!$A$2:$A$44,0))),"KPI_ID inconnu")) -> Écart physique–financier | E10: =IF($A10="","",IFERROR(IF(INDEX('01_KPI'!$D$2:$D$44,MATCH($A10,'01_KPI'!$A$2:$A$44,0))="","",INDEX('01_KPI'!$D$2:$D$44,MATCH($A10,'01_KPI'!$A$2:$A$44,0))),"KPI_ID inconnu")) -> [M] | F10: =IF($A10="","",IFERROR(IF(INDEX('01_KPI'!$J$2:$J$44,MATCH($A10,'01_KPI'!$A$2:$A$44,0))="","",INDEX('01_KPI'!$J$2:$J$44,MATCH($A10,'01_KPI'!$A$2:$A$44,0))),"KPI_ID inconnu")) -> Écart absolu | G10: =IF($A10="","",IFERROR(IF(INDEX('01_KPI'!$K$2:$K$44,MATCH($A10,'01_KPI'!$A$2:$A$44,0))="","",INDEX('01_KPI'!$K$2:$K$44,MATCH($A10,'01_KPI'!$A$2:$A$44,0))),"KPI_ID inconnu")) -> 5 | H10: =IF($A10="","",IFERROR(IF(INDEX('01_KPI'!$L$2:$L$44,MATCH($A10,'01_KPI'!$A$2:$A$44,0))="","",INDEX('01_KPI'!$L$2:$L$44,MATCH($A10,'01_KPI'!$A$2:$A$44,0))),"KPI_ID inconnu")) -> 10 | I10: =IF($A10="","",IFERROR(IF(INDEX('01_KPI'!$I$2:$I$44,MATCH($A10,'01_KPI'!$A$2:$A$44,0))="","",INDEX('01_KPI'!$I$2:$I$44,MATCH($A10,'01_KPI'!$A$2:$A$44,0))),"KPI_ID inconnu")) -> pts | J10: =IF(OR($A10="",$C10=""),"",IF(OR($F10="Information",$F10="Règle spéciale"),"Hors seuil numérique",IF($F10="Plus haut = mieux",IF($C10>=$G10,"VERT",IF($C10>=$H10,"ORANGE","ROUGE")),IF($F10="Plus bas = mieux",IF($C10<=$G10,"VERT",IF($C10<=$H10,"ORANGE","ROUGE")),IF(ABS($C10)<=$G10,"VERT",IF(ABS($C10)<=$H10,"ORANGE","ROUGE")))))) -> VERT
A11: BU1 | B11: Liaison port d'Oran : marché 17,5 → 68,017 Md DA | C11: =(68.017/17.5-1)*100 -> 288.66857 | D11: =IF($A11="","",IFERROR(IF(INDEX('01_KPI'!$C$2:$C$44,MATCH($A11,'01_KPI'!$A$2:$A$44,0))="","",INDEX('01_KPI'!$C$2:$C$44,MATCH($A11,'01_KPI'!$A$2:$A$44,0))),"KPI_ID inconnu")) -> Poids financier des avenants | E11: =IF($A11="","",IFERROR(IF(INDEX('01_KPI'!$D$2:$D$44,MATCH($A11,'01_KPI'!$A$2:$A$44,0))="","",INDEX('01_KPI'!$D$2:$D$44,MATCH($A11,'01_KPI'!$A$2:$A$44,0))),"KPI_ID inconnu")) -> [M] | F11: =IF($A11="","",IFERROR(IF(INDEX('01_KPI'!$J$2:$J$44,MATCH($A11,'01_KPI'!$A$2:$A$44,0))="","",INDEX('01_KPI'!$J$2:$J$44,MATCH($A11,'01_KPI'!$A$2:$A$44,0))),"KPI_ID inconnu")) -> Plus bas = mieux | G11: =IF($A11="","",IFERROR(IF(INDEX('01_KPI'!$K$2:$K$44,MATCH($A11,'01_KPI'!$A$2:$A$44,0))="","",INDEX('01_KPI'!$K$2:$K$44,MATCH($A11,'01_KPI'!$A$2:$A$44,0))),"KPI_ID inconnu")) -> 15 | H11: =IF($A11="","",IFERROR(IF(INDEX('01_KPI'!$L$2:$L$44,MATCH($A11,'01_KPI'!$A$2:$A$44,0))="","",INDEX('01_KPI'!$L$2:$L$44,MATCH($A11,'01_KPI'!$A$2:$A$44,0))),"KPI_ID inconnu")) -> 40 | I11: =IF($A11="","",IFERROR(IF(INDEX('01_KPI'!$I$2:$I$44,MATCH($A11,'01_KPI'!$A$2:$A$44,0))="","",INDEX('01_KPI'!$I$2:$I$44,MATCH($A11,'01_KPI'!$A$2:$A$44,0))),"KPI_ID inconnu")) -> % | J11: =IF(OR($A11="",$C11=""),"",IF(OR($F11="Information",$F11="Règle spéciale"),"Hors seuil numérique",IF($F11="Plus haut = mieux",IF($C11>=$G11,"VERT",IF($C11>=$H11,"ORANGE","ROUGE")),IF($F11="Plus bas = mieux",IF($C11<=$G11,"VERT",IF($C11<=$H11,"ORANGE","ROUGE")),IF(ABS($C11)<=$G11,"VERT",IF(ABS($C11)<=$H11,"ORANGE","ROUGE")))))) -> ROUGE
A12: DL3 | B12: Exemple : 120 jours après la date contractuelle | C12: 120 | D12: =IF($A12="","",IFERROR(IF(INDEX('01_KPI'!$C$2:$C$44,MATCH($A12,'01_KPI'!$A$2:$A$44,0))="","",INDEX('01_KPI'!$C$2:$C$44,MATCH($A12,'01_KPI'!$A$2:$A$44,0))),"KPI_ID inconnu")) -> Dépassement de la date contractuelle | E12: =IF($A12="","",IFERROR(IF(INDEX('01_KPI'!$D$2:$D$44,MATCH($A12,'01_KPI'!$A$2:$A$44,0))="","",INDEX('01_KPI'!$D$2:$D$44,MATCH($A12,'01_KPI'!$A$2:$A$44,0))),"KPI_ID inconnu")) -> [M] | F12: =IF($A12="","",IFERROR(IF(INDEX('01_KPI'!$J$2:$J$44,MATCH($A12,'01_KPI'!$A$2:$A$44,0))="","",INDEX('01_KPI'!$J$2:$J$44,MATCH($A12,'01_KPI'!$A$2:$A$44,0))),"KPI_ID inconnu")) -> Plus bas = mieux | G12: =IF($A12="","",IFERROR(IF(INDEX('01_KPI'!$K$2:$K$44,MATCH($A12,'01_KPI'!$A$2:$A$44,0))="","",INDEX('01_KPI'!$K$2:$K$44,MATCH($A12,'01_KPI'!$A$2:$A$44,0))),"KPI_ID inconnu")) -> 0 | H12: =IF($A12="","",IFERROR(IF(INDEX('01_KPI'!$L$2:$L$44,MATCH($A12,'01_KPI'!$A$2:$A$44,0))="","",INDEX('01_KPI'!$L$2:$L$44,MATCH($A12,'01_KPI'!$A$2:$A$44,0))),"KPI_ID inconnu")) -> 180 | I12: =IF($A12="","",IFERROR(IF(INDEX('01_KPI'!$I$2:$I$44,MATCH($A12,'01_KPI'!$A$2:$A$44,0))="","",INDEX('01_KPI'!$I$2:$I$44,MATCH($A12,'01_KPI'!$A$2:$A$44,0))),"KPI_ID inconnu")) -> j | J12: =IF(OR($A12="",$C12=""),"",IF(OR($F12="Information",$F12="Règle spéciale"),"Hors seuil numérique",IF($F12="Plus haut = mieux",IF($C12>=$G12,"VERT",IF($C12>=$H12,"ORANGE","ROUGE")),IF($F12="Plus bas = mieux",IF($C12<=$G12,"VERT",IF($C12<=$H12,"ORANGE","ROUGE")),IF(ABS($C12)<=$G12,"VERT",IF(ABS($C12)<=$H12,"ORANGE","ROUGE")))))) -> ORANGE
A13: QR1 | B13: Exemple : 70 % de l'emprise requise libérée | C13: 70 | D13: =IF($A13="","",IFERROR(IF(INDEX('01_KPI'!$C$2:$C$44,MATCH($A13,'01_KPI'!$A$2:$A$44,0))="","",INDEX('01_KPI'!$C$2:$C$44,MATCH($A13,'01_KPI'!$A$2:$A$44,0))),"KPI_ID inconnu")) -> Taux de libération des emprises | E13: =IF($A13="","",IFERROR(IF(INDEX('01_KPI'!$D$2:$D$44,MATCH($A13,'01_KPI'!$A$2:$A$44,0))="","",INDEX('01_KPI'!$D$2:$D$44,MATCH($A13,'01_KPI'!$A$2:$A$44,0))),"KPI_ID inconnu")) -> [M] | F13: =IF($A13="","",IFERROR(IF(INDEX('01_KPI'!$J$2:$J$44,MATCH($A13,'01_KPI'!$A$2:$A$44,0))="","",INDEX('01_KPI'!$J$2:$J$44,MATCH($A13,'01_KPI'!$A$2:$A$44,0))),"KPI_ID inconnu")) -> Plus haut = mieux | G13: =IF($A13="","",IFERROR(IF(INDEX('01_KPI'!$K$2:$K$44,MATCH($A13,'01_KPI'!$A$2:$A$44,0))="","",INDEX('01_KPI'!$K$2:$K$44,MATCH($A13,'01_KPI'!$A$2:$A$44,0))),"KPI_ID inconnu")) -> 95 | H13: =IF($A13="","",IFERROR(IF(INDEX('01_KPI'!$L$2:$L$44,MATCH($A13,'01_KPI'!$A$2:$A$44,0))="","",INDEX('01_KPI'!$L$2:$L$44,MATCH($A13,'01_KPI'!$A$2:$A$44,0))),"KPI_ID inconnu")) -> 80 | I13: =IF($A13="","",IFERROR(IF(INDEX('01_KPI'!$I$2:$I$44,MATCH($A13,'01_KPI'!$A$2:$A$44,0))="","",INDEX('01_KPI'!$I$2:$I$44,MATCH($A13,'01_KPI'!$A$2:$A$44,0))),"KPI_ID inconnu")) -> % | J13: =IF(OR($A13="",$C13=""),"",IF(OR($F13="Information",$F13="Règle spéciale"),"Hors seuil numérique",IF($F13="Plus haut = mieux",IF($C13>=$G13,"VERT",IF($C13>=$H13,"ORANGE","ROUGE")),IF($F13="Plus bas = mieux",IF($C13<=$G13,"VERT",IF($C13<=$H13,"ORANGE","ROUGE")),IF(ABS($C13)<=$G13,"VERT",IF(ABS($C13)<=$H13,"ORANGE","ROUGE")))))) -> ROUGE
B14: (ligne libre) | D14: =IF($A14="","",IFERROR(IF(INDEX('01_KPI'!$C$2:$C$44,MATCH($A14,'01_KPI'!$A$2:$A$44,0))="","",INDEX('01_KPI'!$C$2:$C$44,MATCH($A14,'01_KPI'!$A$2:$A$44,0))),"KPI_ID inconnu")) | E14: =IF($A14="","",IFERROR(IF(INDEX('01_KPI'!$D$2:$D$44,MATCH($A14,'01_KPI'!$A$2:$A$44,0))="","",INDEX('01_KPI'!$D$2:$D$44,MATCH($A14,'01_KPI'!$A$2:$A$44,0))),"KPI_ID inconnu")) | F14: =IF($A14="","",IFERROR(IF(INDEX('01_KPI'!$J$2:$J$44,MATCH($A14,'01_KPI'!$A$2:$A$44,0))="","",INDEX('01_KPI'!$J$2:$J$44,MATCH($A14,'01_KPI'!$A$2:$A$44,0))),"KPI_ID inconnu")) | G14: =IF($A14="","",IFERROR(IF(INDEX('01_KPI'!$K$2:$K$44,MATCH($A14,'01_KPI'!$A$2:$A$44,0))="","",INDEX('01_KPI'!$K$2:$K$44,MATCH($A14,'01_KPI'!$A$2:$A$44,0))),"KPI_ID inconnu")) | H14: =IF($A14="","",IFERROR(IF(INDEX('01_KPI'!$L$2:$L$44,MATCH($A14,'01_KPI'!$A$2:$A$44,0))="","",INDEX('01_KPI'!$L$2:$L$44,MATCH($A14,'01_KPI'!$A$2:$A$44,0))),"KPI_ID inconnu")) | I14: =IF($A14="","",IFERROR(IF(INDEX('01_KPI'!$I$2:$I$44,MATCH($A14,'01_KPI'!$A$2:$A$44,0))="","",INDEX('01_KPI'!$I$2:$I$44,MATCH($A14,'01_KPI'!$A$2:$A$44,0))),"KPI_ID inconnu")) | J14: =IF(OR($A14="",$C14=""),"",IF(OR($F14="Information",$F14="Règle spéciale"),"Hors seuil numérique",IF($F14="Plus haut = mieux",IF($C14>=$G14,"VERT",IF($C14>=$H14,"ORANGE","ROUGE")),IF($F14="Plus bas = mieux",IF($C14<=$G14,"VERT",IF($C14<=$H14,"ORANGE","ROUGE")),IF(ABS($C14)<=$G14,"VERT",IF(ABS($C14)<=$H14,"ORANGE","ROUGE"))))))
B15: (ligne libre) | D15: =IF($A15="","",IFERROR(IF(INDEX('01_KPI'!$C$2:$C$44,MATCH($A15,'01_KPI'!$A$2:$A$44,0))="","",INDEX('01_KPI'!$C$2:$C$44,MATCH($A15,'01_KPI'!$A$2:$A$44,0))),"KPI_ID inconnu")) | E15: =IF($A15="","",IFERROR(IF(INDEX('01_KPI'!$D$2:$D$44,MATCH($A15,'01_KPI'!$A$2:$A$44,0))="","",INDEX('01_KPI'!$D$2:$D$44,MATCH($A15,'01_KPI'!$A$2:$A$44,0))),"KPI_ID inconnu")) | F15: =IF($A15="","",IFERROR(IF(INDEX('01_KPI'!$J$2:$J$44,MATCH($A15,'01_KPI'!$A$2:$A$44,0))="","",INDEX('01_KPI'!$J$2:$J$44,MATCH($A15,'01_KPI'!$A$2:$A$44,0))),"KPI_ID inconnu")) | G15: =IF($A15="","",IFERROR(IF(INDEX('01_KPI'!$K$2:$K$44,MATCH($A15,'01_KPI'!$A$2:$A$44,0))="","",INDEX('01_KPI'!$K$2:$K$44,MATCH($A15,'01_KPI'!$A$2:$A$44,0))),"KPI_ID inconnu")) | H15: =IF($A15="","",IFERROR(IF(INDEX('01_KPI'!$L$2:$L$44,MATCH($A15,'01_KPI'!$A$2:$A$44,0))="","",INDEX('01_KPI'!$L$2:$L$44,MATCH($A15,'01_KPI'!$A$2:$A$44,0))),"KPI_ID inconnu")) | I15: =IF($A15="","",IFERROR(IF(INDEX('01_KPI'!$I$2:$I$44,MATCH($A15,'01_KPI'!$A$2:$A$44,0))="","",INDEX('01_KPI'!$I$2:$I$44,MATCH($A15,'01_KPI'!$A$2:$A$44,0))),"KPI_ID inconnu")) | J15: =IF(OR($A15="",$C15=""),"",IF(OR($F15="Information",$F15="Règle spéciale"),"Hors seuil numérique",IF($F15="Plus haut = mieux",IF($C15>=$G15,"VERT",IF($C15>=$H15,"ORANGE","ROUGE")),IF($F15="Plus bas = mieux",IF($C15<=$G15,"VERT",IF($C15<=$H15,"ORANGE","ROUGE")),IF(ABS($C15)<=$G15,"VERT",IF(ABS($C15)<=$H15,"ORANGE","ROUGE"))))))

Sheet 07_Correspondance
A1: Ancien_ID | B1: Ancien_KPI | C1: Devenir | D1: Nouveau_KPI | E1: Motif | G1: Bilan des 55 anciens KPI
A2: CN01 | B2: Score Santé Portefeuille | C2: Remplacé | D2: CO6 | E2: Poids à valider ; calculé à partir des KPI de projet. | G2: Remplacé | H2: =COUNTIF($C$2:$C$56,G2) -> 25
A3: CN02 | B3: Taux projets en retard | C3: Remplacé | D3: CO4 | E3: « Retard important » reçoit une définition (DL1 > 100 % et AV2 < 0,90) ; seuils recalibrés. | G3: Fusionné | H3: =COUNTIF($C$2:$C$56,G3) -> 20
A4: CN03 | B4: Taux projets à l'arrêt | C4: Remplacé | D4: CO5 | E4: Seuil d'arrêt précisé (> 60 jours). | G4: Supprimé | H4: =COUNTIF($C$2:$C$56,G4) -> 4
A5: CN04 | B5: Avancement physique portefeuille | C5: Remplacé | D5: AV1; AV2 | E5: Seuil absolu (≥ 80 %) supprimé : l'avancement est jugé par rapport au temps écoulé. | G5: Reporté (Vision) | H5: =COUNTIF($C$2:$C$56,G5) -> 6
A6: CN05 | B6: Projets sous contrainte foncière | C6: Remplacé | D6: QR1 | E6: Devient un KPI de projet (taux de libération), agrégeable au portefeuille. | G6: Total | H6: =SUM(H2:H5) -> 55
A7: CN06 | B7: Projets sous contrainte réseaux | C7: Remplacé | D7: QR2 | E7: Même logique que QR1.
A8: CN07 | B8: Projets à maturation insuffisante | C8: Remplacé | D8: QR6 | E8: Drapeau de maturation (modification de consistance).
A9: CN08 | B9: Indice Santé Contractants portefeuille | C9: Remplacé | D9: CO1 | E9: Note par contractant ; agrégation pondérée par l'AE possible.
A10: CN09 | B10: Dérive AE portefeuille | C10: Fusionné | D10: FI4 | E10: Triple emploi avec CB07 et CB08 ; AE initiale ajustée ; seuils recalibrés.
A11: CN10 | B11: Taux projets réévalués | C11: Supprimé | D11: — | E11: Période non définie ; la réévaluation est suivie via FI4 et FI5.
A12: CN11 | B12: Taux d'achèvement | C12: Supprimé | D12: — | E12: Indicateur de stock lié à l'âge du portefeuille ; affichage informatif possible.
A13: CN12 | B13: Retard moyen portefeuille | C13: Remplacé | D13: DL3 | E13: Médiane au lieu de moyenne ; le Vert ≤ 0 j devient atteignable.
A14: CN13 | B14: Âge moyen des blocages | C14: Remplacé | D14: QR3 | E14: Médiane au lieu de moyenne.
A15: CN14 | B15: Responsabilités de déblocage | C15: Remplacé | D15: GV1 | E15: Échéance ajoutée au critère.
A16: CN15 | B16: Décisions/arbitrages en attente | C16: Remplacé | D16: GV3 | E16: Critère d'échéance explicite.
A17: MO01 | B17: TAP | C17: Fusionné | D17: AV2 | E17: Seuil absolu remplacé par un indice rapporté au délai.
A18: MO02 | B18: Consommation délai | C18: Remplacé | D18: DL1 | E18: Non plafonnée ; délai en vigueur.
... A56: CB10 | B56: Réévaluations en attente | C56: Fusionné | D56: FI5 | E56: Seuils incohérents (> 2 vs règle AL03 > 3) ; nombre affiché à côté.

Sheet 08_Glossaire
A1: Terme | B1: Signification
A2: AE | B2: Autorisation d'engagement : enveloppe financière autorisant à engager une opération.
A3: CP | B3: Crédits de paiement : crédits annuels permettant de payer les situations.
A4: TAP | B4: Taux d'avancement physique.
A5: TAF | B5: Taux d'avancement financier (consommation financière des travaux).
A6: MO | B6: Maître d'ouvrage. (Dans le modèle de données, la main-d'œuvre doit s'écrire « Main_Oeuvre » pour éviter toute confusion.)
A7: BET | B7: Bureau d'études (contrôle et surveillance des travaux).
A8: ODS | B8: Ordre de service (démarrage, arrêt, reprise).
A9: CSM | B9: Commission sectorielle des marchés (visa des marchés et avenants).
A10: CNED | B10: Caisse Nationale d'Équipement pour le Développement.
A11: PMO | B11: Bureau de pilotage de projet (Project Monitoring Office).
A12: PPC | B12: Pourcentage de plan complété : fiabilité du planning hebdomadaire (approche Last Planner).
... A17: Parachèvement | B17: Marché conclu pour terminer les travaux après résiliation du marché initial.

Sheet 09_Roles_Interfaces
A1: Rôles × interfaces — implémentation de chaque rôle dans chaque interface
A2: Les compteurs et les modes se calculent à partir de 03_Matrice_Roles (codes R/S/V et D/I) et des correspondances des sections 6 et 7 (croix « X » en bleu, modifiables). Les cellules grises/colorées se mettent à jour seules.
A4: 1. Interfaces
A5: Rôle visé = proposition à valider. Interfaces I1 à I6 : six espaces du fichier TAQADDUM_Interfaces_Roles.html ; I7 regroupe les deux tableaux de bord (sans lui, Direction et PMO n'auraient aucune interface).
A6: Interface | B6: Usage | C6: Rôle(s) visé(s) | D6: Prototype (fichier)
A7: I1 · Terrain (mobile-first) | B7: Saisie sur site depuis un mobile : planning hebdomadaire, moyens mobilisés, emprises, réseaux, arrêts de chantier. | C7: MO (saisie site) · Contractant | D7: TAQADDUM_Interfaces_Roles.html
A8: I2 · MO local | B8: Pilotage local des projets du maître d'ouvrage : avancement, délais, blocages, avenants, réceptions. | C8: Maître d'ouvrage | D8: TAQADDUM_Interfaces_Roles.html
A9: I3 · Financier | B9: AE, crédits de paiement, situations de travaux, réévaluations et dérive financière. | C9: Contrôleur budgétaire | D9: TAQADDUM_Interfaces_Roles.html
A10: I4 · BET / CTC | B10: Contrôle technique : non-conformités, aléas, consistance, cadence, réceptions. | C10: Bureau d'études | D10: TAQADDUM_Interfaces_Roles.html
A11: I5 · HSE | B11: Incidents de sécurité graves. Hors périmètre du pilote (phase Vision). | C11: BET / HSE | D11: TAQADDUM_Interfaces_Roles.html
A12: I6 · Juridique | B12: Suivi contractuel : avenants et visas, dépassements de délai, parachèvements après résiliation. Aucune mise en demeure automatisée. | C12: CNED · MO (volet contractuel) | D12: TAQADDUM_Interfaces_Roles.html
A13: I7 · Pilotage CNED | B13: Tableaux de bord portefeuille et Catalogue KPI : l'ensemble des KPI, filtrables par rôle. | C13: Direction CNED · CNED / PMO | D13: TAQADDUM_hybride.html · TAQADDUM_CNED_pov_directeur_technique.html
A15: 2. Mode d'implémentation du rôle dans l'interface
A16: Pilote = le rôle est responsable (R) d'au moins un KPI affiché · Saisie = il alimente (S) la donnée · Consultation = lecture seule (V) · — = aucun KPI de l'interface n'est visible pour ce rôle.
A17: Rôle | B17: Périmètre de données | C17: =$A$7 -> I1 · Terrain (mobile-first) | D17: =$A$8 -> I2 · MO local | E17: =$A$9 -> I3 · Financier | F17: =$A$10 -> I4 · BET / CTC | G17: =$A$11 -> I5 · HSE | H17: =$A$12 -> I6 · Juridique | I17: =$A$13 -> I7 · Pilotage CNED
A18: ='03_Matrice_Roles'!$M$4 -> Direction CNED (décideur) | B18: ='03_Matrice_Roles'!$N$4 -> Portefeuille national (tous les projets) | C18: =IF(SUMPRODUCT((C$57:C$99="X")*('03_Matrice_Roles'!E$4:E$46="R"))>0,"Pilote",IF(SUMPRODUCT((C$57:C$99="X")*('03_Matrice_Roles'!E$4:E$46="S"))>0,"Saisie",IF(SUMPRODUCT((C$57:C$99="X")*('03_Matrice_Roles'!E$4:E$46="V"))>0,"Consultation","—"))) -> Consultation | D18: =IF(SUMPRODUCT((D$57:D$99="X")*('03_Matrice_Roles'!E$4:E$46="R"))>0,"Pilote",IF(SUMPRODUCT((D$57:D$99="X")*('03_Matrice_Roles'!E$4:E$46="S"))>0,"Saisie",IF(SUMPRODUCT((D$57:D$99="X")*('03_Matrice_Roles'!E$4:E$46="V"))>0,"Consultation","—"))) -> Consultation | E18: =IF(SUMPRODUCT((E$57:E$99="X")*('03_Matrice_Roles'!E$4:E$46="R"))>0,"Pilote",IF(SUMPRODUCT((E$57:E$99="X")*('03_Matrice_Roles'!E$4:E$46="S"))>0,"Saisie",IF(SUMPRODUCT((E$57:E$99="X")*('03_Matrice_Roles'!E$4:E$46="V"))>0,"Consultation","—"))) -> Consultation | F18: =IF(SUMPRODUCT((F$57:F$99="X")*('03_Matrice_Roles'!E$4:E$46="R"))>0,"Pilote",IF(SUMPRODUCT((F$57:F$99="X")*('03_Matrice_Roles'!E$4:E$46="S"))>0,"Saisie",IF(SUMPRODUCT((F$57:F$99="X")*('03_Matrice_Roles'!E$4:E$46="V"))>0,"Consultation","—"))) -> — | G18: =IF(SUMPRODUCT((G$57:G$99="X")*('03_Matrice_Roles'!E$4:E$46="R"))>0,"Pilote",IF(SUMPRODUCT((G$57:G$99="X")*('03_Matrice_Roles'!E$4:E$46="S"))>0,"Saisie",IF(SUMPRODUCT((G$57:G$99="X")*('03_Matrice_Roles'!E$4:E$46="V"))>0,"Consultation","—"))) -> — | H18: =IF(SUMPRODUCT((H$57:H$99="X")*('03_Matrice_Roles'!E$4:E$46="R"))>0,"Pilote",IF(SUMPRODUCT((H$57:H$99="X")*('03_Matrice_Roles'!E$4:E$46="S"))>0,"Saisie",IF(SUMPRODUCT((H$57:H$99="X")*('03_Matrice_Roles'!E$4:E$46="V"))>0,"Consultation","—"))) -> Consultation | I18: =IF(SUMPRODUCT((I$57:I$99="X")*('03_Matrice_Roles'!E$4:E$46="R"))>0,"Pilote",IF(SUMPRODUCT((I$57:I$99="X")*('03_Matrice_Roles'!E$4:E$46="S"))>0,"Saisie",IF(SUMPRODUCT((I$57:I$99="X")*('03_Matrice_Roles'!E$4:E$46="V"))>0,"Consultation","—"))) -> Consultation
A19: ='03_Matrice_Roles'!$M$5 -> CNED / PMO (analyste) | B19: ='03_Matrice_Roles'!$N$5 -> Portefeuille national (tous les projets) | C19: =IF(SUMPRODUCT((C$57:C$99="X")*('03_Matrice_Roles'!F$4:F$46="R"))>0,"Pilote",IF(SUMPRODUCT((C$57:C$99="X")*('03_Matrice_Roles'!F$4:F$46="S"))>0,"Saisie",IF(SUMPRODUCT((C$57:C$99="X")*('03_Matrice_Roles'!F$4:F$46="V"))>0,"Consultation","—"))) -> Saisie | D19: =IF(SUMPRODUCT((D$57:D$99="X")*('03_Matrice_Roles'!F$4:F$46="R"))>0,"Pilote",IF(SUMPRODUCT((D$57:D$99="X")*('03_Matrice_Roles'!F$4:F$46="S"))>0,"Saisie",IF(SUMPRODUCT((D$57:D$99="X")*('03_Matrice_Roles'!F$4:F$46="V"))>0,"Consultation","—"))) -> Pilote | E19: =IF(SUMPRODUCT((E$57:E$99="X")*('03_Matrice_Roles'!F$4:F$46="R"))>0,"Pilote",IF(SUMPRODUCT((E$57:E$99="X")*('03_Matrice_Roles'!F$4:F$46="S"))>0,"Saisie",IF(SUMPRODUCT((E$57:E$99="X")*('03_Matrice_Roles'!F$4:F$46="V"))>0,"Consultation","—"))) -> Pilote | F19: =IF(SUMPRODUCT((F$57:F$99="X")*('03_Matrice_Roles'!F$4:F$46="R"))>0,"Pilote",IF(SUMPRODUCT((F$57:F$99="X")*('03_Matrice_Roles'!F$4:F$46="S"))>0,"Saisie",IF(SUMPRODUCT((F$57:F$99="X")*('03_Matrice_Roles'!F$4:F$46="V"))>0,"Consultation","—"))) -> Saisie | G19: =IF(SUMPRODUCT((G$57:G$99="X")*('03_Matrice_Roles'!F$4:F$46="R"))>0,"Pilote",IF(SUMPRODUCT((G$57:G$99="X")*('03_Matrice_Roles'!F$4:F$46="S"))>0,"Saisie",IF(SUMPRODUCT((G$57:G$99="X")*('03_Matrice_Roles'!F$4:F$46="V"))>0,"Consultation","—"))) -> Consultation | H19: =IF(SUMPRODUCT((H$57:H$99="X")*('03_Matrice_Roles'!F$4:F$46="R"))>0,"Pilote",IF(SUMPRODUCT((H$57:H$99="X")*('03_Matrice_Roles'!F$4:F$46="S"))>0,"Saisie",IF(SUMPRODUCT((H$57:H$99="X")*('03_Matrice_Roles'!F$4:F$46="V"))>0,"Consultation","—"))) -> Pilote | I19: =IF(SUMPRODUCT((I$57:I$99="X")*('03_Matrice_Roles'!F$4:F$46="R"))>0,"Pilote",IF(SUMPRODUCT((I$57:I$99="X")*('03_Matrice_Roles'!F$4:F$46="S"))>0,"Saisie",IF(SUMPRODUCT((I$57:I$99="X")*('03_Matrice_Roles'!F$4:F$46="V"))>0,"Consultation","—"))) -> Pilote
A20: ='03_Matrice_Roles'!$M$6 -> Maître d'ouvrage (MO) | B20: ='03_Matrice_Roles'!$N$6 -> Ses projets uniquement | C20: =IF(SUMPRODUCT((C$57:C$99="X")*('03_Matrice_Roles'!G$4:G$46="R"))>0,"Pilote",IF(SUMPRODUCT((C$57:C$99="X")*('03_Matrice_Roles'!G$4:G$46="S"))>0,"Saisie",IF(SUMPRODUCT((C$57:C$99="X")*('03_Matrice_Roles'!G$4:G$46="V"))>0,"Consultation","—"))) -> Pilote | D20: =IF(SUMPRODUCT((D$57:D$99="X")*('03_Matrice_Roles'!G$4:G$46="R"))>0,"Pilote",IF(SUMPRODUCT((D$57:D$99="X")*('03_Matrice_Roles'!G$4:G$46="S"))>0,"Saisie",IF(SUMPRODUCT((D$57:D$99="X")*('03_Matrice_Roles'!G$4:G$46="V"))>0,"Consultation","—"))) -> Pilote | E20: =IF(SUMPRODUCT((E$57:E$99="X")*('03_Matrice_Roles'!G$4:G$46="R"))>0,"Pilote",IF(SUMPRODUCT((E$57:E$99="X")*('03_Matrice_Roles'!G$4:G$46="S"))>0,"Saisie",IF(SUMPRODUCT((E$57:E$99="X")*('03_Matrice_Roles'!G$4:G$46="V"))>0,"Consultation","—"))) -> Pilote | F20: =IF(SUMPRODUCT((F$57:F$99="X")*('03_Matrice_Roles'!G$4:G$46="R"))>0,"Pilote",IF(SUMPRODUCT((F$57:F$99="X")*('03_Matrice_Roles'!G$4:G$46="S"))>0,"Saisie",IF(SUMPRODUCT((F$57:F$99="X")*('03_Matrice_Roles'!G$4:G$46="V"))>0,"Consultation","—"))) -> Pilote | G20: =IF(SUMPRODUCT((G$57:G$99="X")*('03_Matrice_Roles'!G$4:G$46="R"))>0,"Pilote",IF(SUMPRODUCT((G$57:G$99="X")*('03_Matrice_Roles'!G$4:G$46="S"))>0,"Saisie",IF(SUMPRODUCT((G$57:G$99="X")*('03_Matrice_Roles'!G$4:G$46="V"))>0,"Consultation","—"))) -> Consultation | H20: =IF(SUMPRODUCT((H$57:H$99="X")*('03_Matrice_Roles'!G$4:G$46="R"))>0,"Pilote",IF(SUMPRODUCT((H$57:H$99="X")*('03_Matrice_Roles'!G$4:G$46="S"))>0,"Saisie",IF(SUMPRODUCT((H$57:H$99="X")*('03_Matrice_Roles'!G$4:G$46="V"))>0,"Consultation","—"))) -> Pilote | I20: =IF(SUMPRODUCT((I$57:I$99="X")*('03_Matrice_Roles'!G$4:G$46="R"))>0,"Pilote",IF(SUMPRODUCT((I$57:I$99="X")*('03_Matrice_Roles'!G$4:G$46="S"))>0,"Saisie",IF(SUMPRODUCT((I$57:I$99="X")*('03_Matrice_Roles'!G$4:G$46="V"))>0,"Consultation","—"))) -> Pilote
A21: ='03_Matrice_Roles'!$M$7 -> Bureau d'études (BET) / contrôle | B21: ='03_Matrice_Roles'!$N$7 -> Projets et marchés qu'il surveille | C21: =IF(SUMPRODUCT((C$57:C$99="X")*('03_Matrice_Roles'!H$4:H$46="R"))>0,"Pilote",IF(SUMPRODUCT((C$57:C$99="X")*('03_Matrice_Roles'!H$4:H$46="S"))>0,"Saisie",IF(SUMPRODUCT((C$57:C$99="X")*('03_Matrice_Roles'!H$4:H$46="V"))>0,"Consultation","—"))) -> Saisie | D21: =IF(SUMPRODUCT((D$57:D$99="X")*('03_Matrice_Roles'!H$4:H$46="R"))>0,"Pilote",IF(SUMPRODUCT((D$57:D$99="X")*('03_Matrice_Roles'!H$4:H$46="S"))>0,"Saisie",IF(SUMPRODUCT((D$57:D$99="X")*('03_Matrice_Roles'!H$4:H$46="V"))>0,"Consultation","—"))) -> Pilote | E21: =IF(SUMPRODUCT((E$57:E$99="X")*('03_Matrice_Roles'!H$4:H$46="R"))>0,"Pilote",IF(SUMPRODUCT((E$57:E$99="X")*('03_Matrice_Roles'!H$4:H$46="S"))>0,"Saisie",IF(SUMPRODUCT((E$57:E$99="X")*('03_Matrice_Roles'!H$4:H$46="V"))>0,"Consultation","—"))) -> Saisie | F21: =IF(SUMPRODUCT((F$57:F$99="X")*('03_Matrice_Roles'!H$4:H$46="R"))>0,"Pilote",IF(SUMPRODUCT((F$57:F$99="X")*('03_Matrice_Roles'!H$4:H$46="S"))>0,"Saisie",IF(SUMPRODUCT((F$57:F$99="X")*('03_Matrice_Roles'!H$4:H$46="V"))>0,"Consultation","—"))) -> Pilote | G21: =IF(SUMPRODUCT((G$57:G$99="X")*('03_Matrice_Roles'!H$4:H$46="R"))>0,"Pilote",IF(SUMPRODUCT((G$57:G$99="X")*('03_Matrice_Roles'!H$4:H$46="S"))>0,"Saisie",IF(SUMPRODUCT((G$57:G$99="X")*('03_Matrice_Roles'!H$4:H$46="V"))>0,"Consultation","—"))) -> Pilote | H21: =IF(SUMPRODUCT((H$57:H$99="X")*('03_Matrice_Roles'!H$4:H$46="R"))>0,"Pilote",IF(SUMPRODUCT((H$57:H$99="X")*('03_Matrice_Roles'!H$4:H$46="S"))>0,"Saisie",IF(SUMPRODUCT((H$57:H$99="X")*('03_Matrice_Roles'!H$4:H$46="V"))>0,"Consultation","—"))) -> Consultation | I21: =IF(SUMPRODUCT((I$57:I$99="X")*('03_Matrice_Roles'!H$4:H$46="R"))>0,"Pilote",IF(SUMPRODUCT((I$57:I$99="X")*('03_Matrice_Roles'!H$4:H$46="S"))>0,"Saisie",IF(SUMPRODUCT((I$57:I$99="X")*('03_Matrice_Roles'!H$4:H$46="V"))>0,"Consultation","—"))) -> Pilote
A22: ='03_Matrice_Roles'!$M$8 -> Contractant (entreprise) | B22: ='03_Matrice_Roles'!$N$8 -> Ses propres marchés uniquement | C22: =IF(SUMPRODUCT((C$57:C$99="X")*('03_Matrice_Roles'!I$4:I$46="R"))>0,"Pilote",IF(SUMPRODUCT((C$57:C$99="X")*('03_Matrice_Roles'!I$4:I$46="S"))>0,"Saisie",IF(SUMPRODUCT((C$57:C$99="X")*('03_Matrice_Roles'!I$4:I$46="V"))>0,"Consultation","—"))) -> Saisie | D22: =IF(SUMPRODUCT((D$57:D$99="X")*('03_Matrice_Roles'!I$4:I$46="R"))>0,"Pilote",IF(SUMPRODUCT((D$57:D$99="X")*('03_Matrice_Roles'!I$4:I$46="S"))>0,"Saisie",IF(SUMPRODUCT((D$57:D$99="X")*('03_Matrice_Roles'!I$4:I$46="V"))>0,"Consultation","—"))) -> Saisie | E22: =IF(SUMPRODUCT((E$57:E$99="X")*('03_Matrice_Roles'!I$4:I$46="R"))>0,"Pilote",IF(SUMPRODUCT((E$57:E$99="X")*('03_Matrice_Roles'!I$4:I$46="S"))>0,"Saisie",IF(SUMPRODUCT((E$57:E$99="X")*('03_Matrice_Roles'!I$4:I$46="V"))>0,"Consultation","—"))) -> Consultation | F22: =IF(SUMPRODUCT((F$57:F$99="X")*('03_Matrice_Roles'!I$4:I$46="R"))>0,"Pilote",IF(SUMPRODUCT((F$57:F$99="X")*('03_Matrice_Roles'!I$4:I$46="S"))>0,"Saisie",IF(SUMPRODUCT((F$57:F$99="X")*('03_Matrice_Roles'!I$4:I$46="V"))>0,"Consultation","—"))) -> Consultation | G22: =IF(SUMPRODUCT((G$57:G$99="X")*('03_Matrice_Roles'!I$4:I$46="R"))>0,"Pilote",IF(SUMPRODUCT((G$57:G$99="X")*('03_Matrice_Roles'!I$4:I$46="S"))>0,"Saisie",IF(SUMPRODUCT((G$57:G$99="X")*('03_Matrice_Roles'!I$4:I$46="V"))>0,"Consultation","—"))) -> Consultation | H22: =IF(SUMPRODUCT((H$57:H$99="X")*('03_Matrice_Roles'!I$4:I$46="R"))>0,"Pilote",IF(SUMPRODUCT((H$57:H$99="X")*('03_Matrice_Roles'!I$4:I$46="S"))>0,"Saisie",IF(SUMPRODUCT((H$57:H$99="X")*('03_Matrice_Roles'!I$4:I$46="V"))>0,"Consultation","—"))) -> Consultation | I22: =IF(SUMPRODUCT((I$57:I$99="X")*('03_Matrice_Roles'!I$4:I$46="R"))>0,"Pilote",IF(SUMPRODUCT((I$57:I$99="X")*('03_Matrice_Roles'!I$4:I$46="S"))>0,"Saisie",IF(SUMPRODUCT((I$57:I$99="X")*('03_Matrice_Roles'!I$4:I$46="V"))>0,"Consultation","—"))) -> Saisie
A23: ='03_Matrice_Roles'!$M$9 -> Contrôleur budgétaire (Finance) | B23: ='03_Matrice_Roles'!$N$9 -> Projets de son périmètre budgétaire | C23: =IF(SUMPRODUCT((C$57:C$99="X")*('03_Matrice_Roles'!J$4:J$46="R"))>0,"Pilote",IF(SUMPRODUCT((C$57:C$99="X")*('03_Matrice_Roles'!J$4:J$46="S"))>0,"Saisie",IF(SUMPRODUCT((C$57:C$99="X")*('03_Matrice_Roles'!J$4:J$46="V"))>0,"Consultation","—"))) -> Consultation | D23: =IF(SUMPRODUCT((D$57:D$99="X")*('03_Matrice_Roles'!J$4:J$46="R"))>0,"Pilote",IF(SUMPRODUCT((D$57:D$99="X")*('03_Matrice_Roles'!J$4:J$46="S"))>0,"Saisie",IF(SUMPRODUCT((D$57:D$99="X")*('03_Matrice_Roles'!J$4:J$46="V"))>0,"Consultation","—"))) -> Saisie | E23: =IF(SUMPRODUCT((E$57:E$99="X")*('03_Matrice_Roles'!J$4:J$46="R"))>0,"Pilote",IF(SUMPRODUCT((E$57:E$99="X")*('03_Matrice_Roles'!J$4:J$46="S"))>0,"Saisie",IF(SUMPRODUCT((E$57:E$99="X")*('03_Matrice_Roles'!J$4:J$46="V"))>0,"Consultation","—"))) -> Pilote | F23: =IF(SUMPRODUCT((F$57:F$99="X")*('03_Matrice_Roles'!J$4:J$46="R"))>0,"Pilote",IF(SUMPRODUCT((F$57:F$99="X")*('03_Matrice_Roles'!J$4:J$46="S"))>0,"Saisie",IF(SUMPRODUCT((F$57:F$99="X")*('03_Matrice_Roles'!J$4:J$46="V"))>0,"Consultation","—"))) -> Consultation | G23: =IF(SUMPRODUCT((G$57:G$99="X")*('03_Matrice_Roles'!J$4:J$46="R"))>0,"Pilote",IF(SUMPRODUCT((G$57:G$99="X")*('03_Matrice_Roles'!J$4:J$46="S"))>0,"Saisie",IF(SUMPRODUCT((G$57:G$99="X")*('03_Matrice_Roles'!J$4:J$46="V"))>0,"Consultation","—"))) -> — | H23: =IF(SUMPRODUCT((H$57:H$99="X")*('03_Matrice_Roles'!J$4:J$46="R"))>0,"Pilote",IF(SUMPRODUCT((H$57:H$99="X")*('03_Matrice_Roles'!J$4:J$46="S"))>0,"Saisie",IF(SUMPRODUCT((H$57:H$99="X")*('03_Matrice_Roles'!J$4:J$46="V"))>0,"Consultation","—"))) -> Consultation | I23: =IF(SUMPRODUCT((I$57:I$99="X")*('03_Matrice_Roles'!J$4:J$46="R"))>0,"Pilote",IF(SUMPRODUCT((I$57:I$99="X")*('03_Matrice_Roles'!J$4:J$46="S"))>0,"Saisie",IF(SUMPRODUCT((I$57:I$99="X")*('03_Matrice_Roles'!J$4:J$46="V"))>0,"Consultation","—"))) -> Pilote
A25: 3. KPI par interface : R (responsable) · S (alimente) · V (consulte)
A26: Nombre de KPI de l'interface selon le droit du rôle. La colonne J rappelle le total de KPI visibles par le rôle dans le référentiel (toutes interfaces confondues).
A27: Rôle | B27: Périmètre de données | C27: =$A$7 -> I1 · Terrain (mobile-first) | D27: =$A$8 -> I2 · MO local | E27: =$A$9 -> I3 · Financier | F27: =$A$10 -> I4 · BET / CTC | G27: =$A$11 -> I5 · HSE | H27: =$A$12 -> I6 · Juridique | I27: =$A$13 -> I7 · Pilotage CNED | J27: KPI visibles (total)
A28: ='03_Matrice_Roles'!$M$4 -> Direction CNED (décideur) | B28: ='03_Matrice_Roles'!$N$4 -> Portefeuille national (tous les projets) | C28: ="R "&SUMPRODUCT((C$57:C$99="X")*('03_Matrice_Roles'!E$4:E$46="R"))&" · S "&SUMPRODUCT((C$57:C$99="X")*('03_Matrice_Roles'!E$4:E$46="S"))&" · V "&SUMPRODUCT((C$57:C$99="X")*('03_Matrice_Roles'!E$4:E$46="V")) -> R 0 · S 0 · V 2 | D28: ="R "&SUMPRODUCT((D$57:D$99="X")*('03_Matrice_Roles'!E$4:E$46="R"))&" · S "&SUMPRODUCT((D$57:D$99="X")*('03_Matrice_Roles'!E$4:E$46="S"))&" · V "&SUMPRODUCT((D$57:D$99="X")*('03_Matrice_Roles'!E$4:E$46="V")) -> R 0 · S 0 · V 10 | E28: ="R "&SUMPRODUCT((E$57:E$99="X")*('03_Matrice_Roles'!E$4:E$46="R"))&" · S "&SUMPRODUCT((E$57:E$99="X")*('03_Matrice_Roles'!E$4:E$46="S"))&" · V "&SUMPRODUCT((E$57:E$99="X")*('03_Matrice_Roles'!E$4:E$46="V")) -> R 0 · S 0 · V 7 | F28: ="R "&SUMPRODUCT((F$57:F$99="X")*('03_Matrice_Roles'!E$4:E$46="R"))&" · S "&SUMPRODUCT((F$57:F$99="X")*('03_Matrice_Roles'!E$4:E$46="S"))&" · V "&SUMPRODUCT((F$57:F$99="X")*('03_Matrice_Roles'!E$4:E$46="V")) -> R 0 · S 0 · V 0 | G28: ="R "&SUMPRODUCT((G$57:G$99="X")*('03_Matrice_Roles'!E$4:E$46="R"))&" · S "&SUMPRODUCT((G$57:G$99="X")*('03_Matrice_Roles'!E$4:E$46="S"))&" · V "&SUMPRODUCT((G$57:G$99="X")*('03_Matrice_Roles'!E$4:E$46="V")) -> R 0 · S 0 · V 0 | H28: ="R "&SUMPRODUCT((H$57:H$99="X")*('03_Matrice_Roles'!E$4:E$46="R"))&" · S "&SUMPRODUCT((H$57:H$99="X")*('03_Matrice_Roles'!E$4:E$46="S"))&" · V "&SUMPRODUCT((H$57:H$99="X")*('03_Matrice_Roles'!E$4:E$46="V")) -> R 0 · S 0 · V 5 | I28: ="R "&SUMPRODUCT((I$57:I$99="X")*('03_Matrice_Roles'!E$4:E$46="R"))&" · S "&SUMPRODUCT((I$57:I$99="X")*('03_Matrice_Roles'!E$4:E$46="S"))&" · V "&SUMPRODUCT((I$57:I$99="X")*('03_Matrice_Roles'!E$4:E$46="V")) -> R 0 · S 0 · V 22 | J28: =COUNTA('03_Matrice_Roles'!E$4:E$46) -> 22
A29: ='03_Matrice_Roles'!$M$5 -> CNED / PMO (analyste) | B29: ='03_Matrice_Roles'!$N$5 -> Portefeuille national (tous les projets) | C29: ="R "&SUMPRODUCT((C$57:C$99="X")*('03_Matrice_Roles'!F$4:F$46="R"))&" · S "&SUMPRODUCT((C$57:C$99="X")*('03_Matrice_Roles'!F$4:F$46="S"))&" · V "&SUMPRODUCT((C$57:C$99="X")*('03_Matrice_Roles'!F$4:F$46="V")) -> R 0 · S 1 · V 8 | D29: ="R "&SUMPRODUCT((D$57:D$99="X")*('03_Matrice_Roles'!F$4:F$46="R"))&" · S "&SUMPRODUCT((D$57:D$99="X")*('03_Matrice_Roles'!F$4:F$46="S"))&" · V "&SUMPRODUCT((D$57:D$99="X")*('03_Matrice_Roles'!F$4:F$46="V")) -> R 7 · S 1 · V 16 | E29: ="R "&SUMPRODUCT((E$57:E$99="X")*('03_Matrice_Roles'!F$4:F$46="R"))&" · S "&SUMPRODUCT((E$57:E$99="X")*('03_Matrice_Roles'!F$4:F$46="S"))&" · V "&SUMPRODUCT((E$57:E$99="X")*('03_Matrice_Roles'!F$4:F$46="V")) -> R 2 · S 1 · V 7 | F29: ="R "&SUMPRODUCT((F$57:F$99="X")*('03_Matrice_Roles'!F$4:F$46="R"))&" · S "&SUMPRODUCT((F$57:F$99="X")*('03_Matrice_Roles'!F$4:F$46="S"))&" · V "&SUMPRODUCT((F$57:F$99="X")*('03_Matrice_Roles'!F$4:F$46="V")) -> R 0 · S 1 · V 8 | G29: ="R "&SUMPRODUCT((G$57:G$99="X")*('03_Matrice_Roles'!F$4:F$46="R"))&" · S "&SUMPRODUCT((G$57:G$99="X")*('03_Matrice_Roles'!F$4:F$46="S"))&" · V "&SUMPRODUCT((G$57:G$99="X")*('03_Matrice_Roles'!F$4:F$46="V")) -> R 0 · S 0 · V 1 | H29: ="R "&SUMPRODUCT((H$57:H$99="X")*('03_Matrice_Roles'!F$4:F$46="R"))&" · S "&SUMPRODUCT((H$57:H$99="X")*('03_Matrice_Roles'!F$4:F$46="S"))&" · V "&SUMPRODUCT((H$57:H$99="X")*('03_Matrice_Roles'!F$4:F$46="V")) -> R 5 · S 0 · V 1 | I29: ="R "&SUMPRODUCT((I$57:I$99="X")*('03_Matrice_Roles'!F$4:F$46="R"))&" · S "&SUMPRODUCT((I$57:I$99="X")*('03_Matrice_Roles'!F$4:F$46="S"))&" · V "&SUMPRODUCT((I$57:I$99="X")*('03_Matrice_Roles'!F$4:F$46="V")) -> R 18 · S 2 · V 23 | J29: =COUNTA('03_Matrice_Roles'!F$4:F$46) -> 43
A30: ='03_Matrice_Roles'!$M$6 -> Maître d'ouvrage (MO) | B30: ='03_Matrice_Roles'!$N$6 -> Ses projets uniquement | C30: ="R "&SUMPRODUCT((C$57:C$99="X")*('03_Matrice_Roles'!G$4:G$46="R"))&" · S "&SUMPRODUCT((C$57:C$99="X")*('03_Matrice_Roles'!G$4:G$46="S"))&" · V "&SUMPRODUCT((C$57:C$99="X")*('03_Matrice_Roles'!G$4:G$46="V")) -> R 9 · S 0 · V 0 | D30: ="R "&SUMPRODUCT((D$57:D$99="X")*('03_Matrice_Roles'!G$4:G$46="R"))&" · S "&SUMPRODUCT((D$57:D$99="X")*('03_Matrice_Roles'!G$4:G$46="S"))&" · V "&SUMPRODUCT((D$57:D$99="X")*('03_Matrice_Roles'!G$4:G$46="V")) -> R 16 · S 4 · V 4 | E30: ="R "&SUMPRODUCT((E$57:E$99="X")*('03_Matrice_Roles'!G$4:G$46="R"))&" · S "&SUMPRODUCT((E$57:E$99="X")*('03_Matrice_Roles'!G$4:G$46="S"))&" · V "&SUMPRODUCT((E$57:E$99="X")*('03_Matrice_Roles'!G$4:G$46="V")) -> R 4 · S 2 · V 4 | F30: ="R "&SUMPRODUCT((F$57:F$99="X")*('03_Matrice_Roles'!G$4:G$46="R"))&" · S "&SUMPRODUCT((F$57:F$99="X")*('03_Matrice_Roles'!G$4:G$46="S"))&" · V "&SUMPRODUCT((F$57:F$99="X")*('03_Matrice_Roles'!G$4:G$46="V")) -> R 6 · S 1 · V 2 | G30: ="R "&SUMPRODUCT((G$57:G$99="X")*('03_Matrice_Roles'!G$4:G$46="R"))&" · S "&SUMPRODUCT((G$57:G$99="X")*('03_Matrice_Roles'!G$4:G$46="S"))&" · V "&SUMPRODUCT((G$57:G$99="X")*('03_Matrice_Roles'!G$4:G$46="V")) -> R 0 · S 0 · V 1 | H30: ="R "&SUMPRODUCT((H$57:H$99="X")*('03_Matrice_Roles'!G$4:G$46="R"))&" · S "&SUMPRODUCT((H$57:H$99="X")*('03_Matrice_Roles'!G$4:G$46="S"))&" · V "&SUMPRODUCT((H$57:H$99="X")*('03_Matrice_Roles'!G$4:G$46="V")) -> R 1 · S 2 · V 2 | I30: ="R "&SUMPRODUCT((I$57:I$99="X")*('03_Matrice_Roles'!G$4:G$46="R"))&" · S "&SUMPRODUCT((I$57:I$99="X")*('03_Matrice_Roles'!G$4:G$46="S"))&" · V "&SUMPRODUCT((I$57:I$99="X")*('03_Matrice_Roles'!G$4:G$46="V")) -> R 18 · S 4 · V 18 | J30: =COUNTA('03_Matrice_Roles'!G$4:G$46) -> 40
A31: ='03_Matrice_Roles'!$M$7 -> Bureau d'études (BET) / contrôle | B31: ='03_Matrice_Roles'!$N$7 -> Projets et marchés qu'il surveille | C31: ="R "&SUMPRODUCT((C$57:C$99="X")*('03_Matrice_Roles'!H$4:H$46="R"))&" · S "&SUMPRODUCT((C$57:C$99="X")*('03_Matrice_Roles'!H$4:H$46="S"))&" · V "&SUMPRODUCT((C$57:C$99="X")*('03_Matrice_Roles'!H$4:H$46="V")) -> R 0 · S 2 · V 7 | D31: ="R "&SUMPRODUCT((D$57:D$99="X")*('03_Matrice_Roles'!H$4:H$46="R"))&" · S "&SUMPRODUCT((D$57:D$99="X")*('03_Matrice_Roles'!H$4:H$46="S"))&" · V "&SUMPRODUCT((D$57:D$99="X")*('03_Matrice_Roles'!H$4:H$46="V")) -> R 1 · S 3 · V 14 | E31: ="R "&SUMPRODUCT((E$57:E$99="X")*('03_Matrice_Roles'!H$4:H$46="R"))&" · S "&SUMPRODUCT((E$57:E$99="X")*('03_Matrice_Roles'!H$4:H$46="S"))&" · V "&SUMPRODUCT((E$57:E$99="X")*('03_Matrice_Roles'!H$4:H$46="V")) -> R 0 · S 1 · V 0 | F31: ="R "&SUMPRODUCT((F$57:F$99="X")*('03_Matrice_Roles'!H$4:H$46="R"))&" · S "&SUMPRODUCT((F$57:F$99="X")*('03_Matrice_Roles'!H$4:H$46="S"))&" · V "&SUMPRODUCT((F$57:F$99="X")*('03_Matrice_Roles'!H$4:H$46="V")) -> R 3 · S 2 · V 4 | G31: ="R "&SUMPRODUCT((G$57:G$99="X")*('03_Matrice_Roles'!H$4:H$46="R"))&" · S "&SUMPRODUCT((G$57:G$99="X")*('03_Matrice_Roles'!H$4:H$46="S"))&" · V "&SUMPRODUCT((G$57:G$99="X")*('03_Matrice_Roles'!H$4:H$46="V")) -> R 1 · S 0 · V 0 | H31: ="R "&SUMPRODUCT((H$57:H$99="X")*('03_Matrice_Roles'!H$4:H$46="R"))&" · S "&SUMPRODUCT((H$57:H$99="X")*('03_Matrice_Roles'!H$4:H$46="S"))&" · V "&SUMPRODUCT((H$57:H$99="X")*('03_Matrice_Roles'!H$4:H$46="V")) -> R 0 · S 0 · V 3 | I31: ="R "&SUMPRODUCT((I$57:I$99="X")*('03_Matrice_Roles'!H$4:H$46="R"))&" · S "&SUMPRODUCT((I$57:I$99="X")*('03_Matrice_Roles'!H$4:H$46="S"))&" · V "&SUMPRODUCT((I$57:I$99="X")*('03_Matrice_Roles'!H$4:H$46="V")) -> R 3 · S 4 · V 17 | J31: =COUNTA('03_Matrice_Roles'!H$4:H$46) -> 24
A32: ='03_Matrice_Roles'!$M$8 -> Contractant (entreprise) | B32: ='03_Matrice_Roles'!$N$8 -> Ses propres marchés uniquement | C32: ="R "&SUMPRODUCT((C$57:C$99="X")*('03_Matrice_Roles'!I$4:I$46="R"))&" · S "&SUMPRODUCT((C$57:C$99="X")*('03_Matrice_Roles'!I$4:I$46="S"))&" · V "&SUMPRODUCT((C$57:C$99="X")*('03_Matrice_Roles'!I$4:I$46="V")) -> R 0 · S 3 · V 6 | D32: ="R "&SUMPRODUCT((D$57:D$99="X")*('03_Matrice_Roles'!I$4:I$46="R"))&" · S "&SUMPRODUCT((D$57:D$99="X")*('03_Matrice_Roles'!I$4:I$46="S"))&" · V "&SUMPRODUCT((D$57:D$99="X")*('03_Matrice_Roles'!I$4:I$46="V")) -> R 0 · S 3 · V 17 | E32: ="R "&SUMPRODUCT((E$57:E$99="X")*('03_Matrice_Roles'!I$4:I$46="R"))&" · S "&SUMPRODUCT((E$57:E$99="X")*('03_Matrice_Roles'!I$4:I$46="S"))&" · V "&SUMPRODUCT((E$57:E$99="X")*('03_Matrice_Roles'!I$4:I$46="V")) -> R 0 · S 0 · V 5 | F32: ="R "&SUMPRODUCT((F$57:F$99="X")*('03_Matrice_Roles'!I$4:I$46="R"))&" · S "&SUMPRODUCT((F$57:F$99="X")*('03_Matrice_Roles'!I$4:I$46="S"))&" · V "&SUMPRODUCT((F$57:F$99="X")*('03_Matrice_Roles'!I$4:I$46="V")) -> R 0 · S 0 · V 7 | G32: ="R "&SUMPRODUCT((G$57:G$99="X")*('03_Matrice_Roles'!I$4:I$46="R"))&" · S "&SUMPRODUCT((G$57:G$99="X")*('03_Matrice_Roles'!I$4:I$46="S"))&" · V "&SUMPRODUCT((G$57:G$99="X")*('03_Matrice_Roles'!I$4:I$46="V")) -> R 0 · S 0 · V 1 | H32: ="R "&SUMPRODUCT((H$57:H$99="X")*('03_Matrice_Roles'!I$4:I$46="R"))&" · S "&SUMPRODUCT((H$57:H$99="X")*('03_Matrice_Roles'!I$4:I$46="S"))&" · V "&SUMPRODUCT((H$57:H$99="X")*('03_Matrice_Roles'!I$4:I$46="V")) -> R 0 · S 0 · V 5 | I32: ="R "&SUMPRODUCT((I$57:I$99="X")*('03_Matrice_Roles'!I$4:I$46="R"))&" · S "&SUMPRODUCT((I$57:I$99="X")*('03_Matrice_Roles'!I$4:I$46="S"))&" · V "&SUMPRODUCT((I$57:I$99="X")*('03_Matrice_Roles'!I$4:I$46="V")) -> R 0 · S 3 · V 21 | J32: =COUNTA('03_Matrice_Roles'!I$4:I$46) -> 24
A33: ='03_Matrice_Roles'!$M$9 -> Contrôleur budgétaire (Finance) | B33: ='03_Matrice_Roles'!$N$9 -> Projets de son périmètre budgétaire | C33: ="R "&SUMPRODUCT((C$57:C$99="X")*('03_Matrice_Roles'!J$4:J$46="R"))&" · S "&SUMPRODUCT((C$57:C$99="X")*('03_Matrice_Roles'!J$4:J$46="S"))&" · V "&SUMPRODUCT((C$57:C$99="X")*('03_Matrice_Roles'!J$4:J$46="V")) -> R 0 · S 0 · V 1 | D33: ="R "&SUMPRODUCT((D$57:D$99="X")*('03_Matrice_Roles'!J$4:J$46="R"))&" · S "&SUMPRODUCT((D$57:D$99="X")*('03_Matrice_Roles'!J$4:J$46="S"))&" · V "&SUMPRODUCT((D$57:D$99="X")*('03_Matrice_Roles'!J$4:J$46="V")) -> R 0 · S 2 · V 7 | E33: ="R "&SUMPRODUCT((E$57:E$99="X")*('03_Matrice_Roles'!J$4:J$46="R"))&" · S "&SUMPRODUCT((E$57:E$99="X")*('03_Matrice_Roles'!J$4:J$46="S"))&" · V "&SUMPRODUCT((E$57:E$99="X")*('03_Matrice_Roles'!J$4:J$46="V")) -> R 4 · S 3 · V 3 | F33: ="R "&SUMPRODUCT((F$57:F$99="X")*('03_Matrice_Roles'!J$4:J$46="R"))&" · S "&SUMPRODUCT((F$57:F$99="X")*('03_Matrice_Roles'!J$4:J$46="S"))&" · V "&SUMPRODUCT((F$57:F$99="X")*('03_Matrice_Roles'!J$4:J$46="V")) -> R 0 · S 0 · V 2 | G33: ="R "&SUMPRODUCT((G$57:G$99="X")*('03_Matrice_Roles'!J$4:J$46="R"))&" · S "&SUMPRODUCT((G$57:G$99="X")*('03_Matrice_Roles'!J$4:J$46="S"))&" · V "&SUMPRODUCT((G$57:G$99="X")*('03_Matrice_Roles'!J$4:J$46="V")) -> R 0 · S 0 · V 0 | H33: ="R "&SUMPRODUCT((H$57:H$99="X")*('03_Matrice_Roles'!J$4:J$46="R"))&" · S "&SUMPRODUCT((H$57:H$99="X")*('03_Matrice_Roles'!J$4:J$46="S"))&" · V "&SUMPRODUCT((H$57:H$99="X")*('03_Matrice_Roles'!J$4:J$46="V")) -> R 0 · S 0 · V 4 | I33: ="R "&SUMPRODUCT((I$57:I$99="X")*('03_Matrice_Roles'!J$4:J$46="R"))&" · S "&SUMPRODUCT((I$57:I$99="X")*('03_Matrice_Roles'!J$4:J$46="S"))&" · V "&SUMPRODUCT((I$57:I$99="X")*('03_Matrice_Roles'!J$4:J$46="V")) -> R 4 · S 3 · V 10 | J33: =COUNTA('03_Matrice_Roles'!J$4:J$46) -> 17
A35: 4. Alertes par interface : D (destinataire) · I (informé)
A36: Nombre de règles d'alerte affichées dans l'interface, selon le rôle (matrice « Alertes par rôle » de 03_Matrice_Roles).
A37: Rôle | B37: Périmètre de données | C37: =$A$7 -> I1 · Terrain (mobile-first) | D37: =$A$8 -> I2 · MO local | E37: =$A$9 -> I3 · Financier | F37: =$A$10 -> I4 · BET / CTC | G37: =$A$11 -> I5 · HSE | H37: =$A$12 -> I6 · Juridique | I37: =$A$13 -> I7 · Pilotage CNED | J37: Alertes visibles (total)
A38: ='03_Matrice_Roles'!$M$4 -> Direction CNED (décideur) | B38: ='03_Matrice_Roles'!$N$4 -> Portefeuille national (tous les projets) | C38: ="D "&SUMPRODUCT((C$104:C$120="X")*('03_Matrice_Roles'!E$51:E$67="D"))&" · I "&SUMPRODUCT((C$104:C$120="X")*('03_Matrice_Roles'!E$51:E$67="I")) -> D 0 · I 2 | D38: ="D "&SUMPRODUCT((D$104:D$120="X")*('03_Matrice_Roles'!E$51:E$67="D"))&" · I "&SUMPRODUCT((D$104:D$120="X")*('03_Matrice_Roles'!E$51:E$67="I")) -> D 0 · I 6 | E38: ="D "&SUMPRODUCT((E$104:E$120="X")*('03_Matrice_Roles'!E$51:E$67="D"))&" · I "&SUMPRODUCT((E$104:E$120="X")*('03_Matrice_Roles'!E$51:E$67="I")) -> D 0 · I 3 | F38: ="D "&SUMPRODUCT((F$104:F$120="X")*('03_Matrice_Roles'!E$51:E$67="D"))&" · I "&SUMPRODUCT((F$104:F$120="X")*('03_Matrice_Roles'!E$51:E$67="I")) -> D 0 · I 0 | G38: ="D "&SUMPRODUCT((G$104:G$120="X")*('03_Matrice_Roles'!E$51:E$67="D"))&" · I "&SUMPRODUCT((G$104:G$120="X")*('03_Matrice_Roles'!E$51:E$67="I")) -> D 0 · I 0 | H38: ="D "&SUMPRODUCT((H$104:H$120="X")*('03_Matrice_Roles'!E$51:E$67="D"))&" · I "&SUMPRODUCT((H$104:H$120="X")*('03_Matrice_Roles'!E$51:E$67="I")) -> D 0 · I 1 | I38: ="D "&SUMPRODUCT((I$104:I$120="X")*('03_Matrice_Roles'!E$51:E$67="D"))&" · I "&SUMPRODUCT((I$104:I$120="X")*('03_Matrice_Roles'!E$51:E$67="I")) -> D 0 · I 8 | J38: =COUNTA('03_Matrice_Roles'!E$51:E$67) -> 8
A39: ='03_Matrice_Roles'!$M$5 -> CNED / PMO (analyste) | B39: ='03_Matrice_Roles'!$N$5 -> Portefeuille national (tous les projets) | C39: ="D "&SUMPRODUCT((C$104:C$120="X")*('03_Matrice_Roles'!F$51:F$67="D"))&" · I "&SUMPRODUCT((C$104:C$120="X")*('03_Matrice_Roles'!F$51:F$67="I")) -> D 2 · I 2 | D39: ="D "&SUMPRODUCT((D$104:D$120="X")*('03_Matrice_Roles'!F$51:F$67="D"))&" · I "&SUMPRODUCT((D$104:D$120="X")*('03_Matrice_Roles'!F$51:F$67="I")) -> D 6 · I 7 | E39: ="D "&SUMPRODUCT((E$104:E$120="X")*('03_Matrice_Roles'!F$51:F$67="D"))&" · I "&SUMPRODUCT((E$104:E$120="X")*('03_Matrice_Roles'!F$51:F$67="I")) -> D 2 · I 2 | F39: ="D "&SUMPRODUCT((F$104:F$120="X")*('03_Matrice_Roles'!F$51:F$67="D"))&" · I "&SUMPRODUCT((F$104:F$120="X")*('03_Matrice_Roles'!F$51:F$67="I")) -> D 0 · I 2 | G39: ="D "&SUMPRODUCT((G$104:G$120="X")*('03_Matrice_Roles'!F$51:F$67="D"))&" · I "&SUMPRODUCT((G$104:G$120="X")*('03_Matrice_Roles'!F$51:F$67="I")) -> D 0 · I 0 | H39: ="D "&SUMPRODUCT((H$104:H$120="X")*('03_Matrice_Roles'!F$51:F$67="D"))&" · I "&SUMPRODUCT((H$104:H$120="X")*('03_Matrice_Roles'!F$51:F$67="I")) -> D 2 · I 0 | I39: ="D "&SUMPRODUCT((I$104:I$120="X")*('03_Matrice_Roles'!F$51:F$67="D"))&" · I "&SUMPRODUCT((I$104:I$120="X")*('03_Matrice_Roles'!F$51:F$67="I")) -> D 10 · I 7 | J39: =COUNTA('03_Matrice_Roles'!F$51:F$67) -> 17
A40: ='03_Matrice_Roles'!$M$6 -> Maître d'ouvrage (MO) | B40: ='03_Matrice_Roles'!$N$6 -> Ses projets uniquement | C40: ="D "&SUMPRODUCT((C$104:C$120="X")*('03_Matrice_Roles'!G$51:G$67="D"))&" · I "&SUMPRODUCT((C$104:C$120="X")*('03_Matrice_Roles'!G$51:G$67="I")) -> D 4 · I 0 | D40: ="D "&SUMPRODUCT((D$104:D$120="X")*('03_Matrice_Roles'!G$51:G$67="D"))&" · I "&SUMPRODUCT((D$104:D$120="X")*('03_Matrice_Roles'!G$51:G$67="I")) -> D 12 · I 1 | E40: ="D "&SUMPRODUCT((E$104:E$120="X")*('03_Matrice_Roles'!G$51:G$67="D"))&" · I "&SUMPRODUCT((E$104:E$120="X")*('03_Matrice_Roles'!G$51:G$67="I")) -> D 3 · I 1 | F40: ="D "&SUMPRODUCT((F$104:F$120="X")*('03_Matrice_Roles'!G$51:G$67="D"))&" · I "&SUMPRODUCT((F$104:F$120="X")*('03_Matrice_Roles'!G$51:G$67="I")) -> D 2 · I 0 | G40: ="D "&SUMPRODUCT((G$104:G$120="X")*('03_Matrice_Roles'!G$51:G$67="D"))&" · I "&SUMPRODUCT((G$104:G$120="X")*('03_Matrice_Roles'!G$51:G$67="I")) -> D 0 · I 0 | H40: ="D "&SUMPRODUCT((H$104:H$120="X")*('03_Matrice_Roles'!G$51:G$67="D"))&" · I "&SUMPRODUCT((H$104:H$120="X")*('03_Matrice_Roles'!G$51:G$67="I")) -> D 1 · I 1 | I40: ="D "&SUMPRODUCT((I$104:I$120="X")*('03_Matrice_Roles'!G$51:G$67="D"))&" · I "&SUMPRODUCT((I$104:I$120="X")*('03_Matrice_Roles'!G$51:G$67="I")) -> D 12 · I 4 | J40: =COUNTA('03_Matrice_Roles'!G$51:G$67) -> 16
A41: ='03_Matrice_Roles'!$M$7 -> Bureau d'études (BET) / contrôle | B41: ='03_Matrice_Roles'!$N$7 -> Projets et marchés qu'il surveille | C41: ="D "&SUMPRODUCT((C$104:C$120="X")*('03_Matrice_Roles'!H$51:H$67="D"))&" · I "&SUMPRODUCT((C$104:C$120="X")*('03_Matrice_Roles'!H$51:H$67="I")) -> D 0 · I 0 | D41: ="D "&SUMPRODUCT((D$104:D$120="X")*('03_Matrice_Roles'!H$51:H$67="D"))&" · I "&SUMPRODUCT((D$104:D$120="X")*('03_Matrice_Roles'!H$51:H$67="I")) -> D 2 · I 0 | E41: ="D "&SUMPRODUCT((E$104:E$120="X")*('03_Matrice_Roles'!H$51:H$67="D"))&" · I "&SUMPRODUCT((E$104:E$120="X")*('03_Matrice_Roles'!H$51:H$67="I")) -> D 0 · I 0 | F41: ="D "&SUMPRODUCT((F$104:F$120="X")*('03_Matrice_Roles'!H$51:H$67="D"))&" · I "&SUMPRODUCT((F$104:F$120="X")*('03_Matrice_Roles'!H$51:H$67="I")) -> D 2 · I 0 | G41: ="D "&SUMPRODUCT((G$104:G$120="X")*('03_Matrice_Roles'!H$51:H$67="D"))&" · I "&SUMPRODUCT((G$104:G$120="X")*('03_Matrice_Roles'!H$51:H$67="I")) -> D 0 · I 0 | H41: ="D "&SUMPRODUCT((H$104:H$120="X")*('03_Matrice_Roles'!H$51:H$67="D"))&" · I "&SUMPRODUCT((H$104:H$120="X")*('03_Matrice_Roles'!H$51:H$67="I")) -> D 0 · I 0 | I41: ="D "&SUMPRODUCT((I$104:I$120="X")*('03_Matrice_Roles'!H$51:H$67="D"))&" · I "&SUMPRODUCT((I$104:I$120="X")*('03_Matrice_Roles'!H$51:H$67="I")) -> D 2 · I 1 | J41: =COUNTA('03_Matrice_Roles'!H$51:H$67) -> 3
A42: ='03_Matrice_Roles'!$M$8 -> Contractant (entreprise) | B42: ='03_Matrice_Roles'!$N$8 -> Ses propres marchés uniquement | C42: ="D "&SUMPRODUCT((C$104:C$120="X")*('03_Matrice_Roles'!I$51:I$67="D"))&" · I "&SUMPRODUCT((C$104:C$120="X")*('03_Matrice_Roles'!I$51:I$67="I")) -> D 1 · I 1 | D42: ="D "&SUMPRODUCT((D$104:D$120="X")*('03_Matrice_Roles'!I$51:I$67="D"))&" · I "&SUMPRODUCT((D$104:D$120="X")*('03_Matrice_Roles'!I$51:I$67="I")) -> D 1 · I 5 | E42: ="D "&SUMPRODUCT((E$104:E$120="X")*('03_Matrice_Roles'!I$51:I$67="D"))&" · I "&SUMPRODUCT((E$104:E$120="X")*('03_Matrice_Roles'!I$51:I$67="I")) -> D 0 · I 1 | F42: ="D "&SUMPRODUCT((F$104:F$120="X")*('03_Matrice_Roles'!I$51:I$67="D"))&" · I "&SUMPRODUCT((F$104:F$120="X")*('03_Matrice_Roles'!I$51:I$67="I")) -> D 0 · I 1 | G42: ="D "&SUMPRODUCT((G$104:G$120="X")*('03_Matrice_Roles'!I$51:I$67="D"))&" · I "&SUMPRODUCT((G$104:G$120="X")*('03_Matrice_Roles'!I$51:I$67="I")) -> D 0 · I 0 | H42: ="D "&SUMPRODUCT((H$104:H$120="X")*('03_Matrice_Roles'!I$51:I$67="D"))&" · I "&SUMPRODUCT((H$104:H$120="X")*('03_Matrice_Roles'!I$51:I$67="I")) -> D 0 · I 1 | I42: ="D "&SUMPRODUCT((I$104:I$120="X")*('03_Matrice_Roles'!I$51:I$67="D"))&" · I "&SUMPRODUCT((I$104:I$120="X")*('03_Matrice_Roles'!I$51:I$67="I")) -> D 1 · I 5 | J42: =COUNTA('03_Matrice_Roles'!I$51:I$67) -> 6
A43: ='03_Matrice_Roles'!$M$9 -> Contrôleur budgétaire (Finance) | B43: ='03_Matrice_Roles'!$N$9 -> Projets de son périmètre budgétaire | C43: ="D "&SUMPRODUCT((C$104:C$120="X")*('03_Matrice_Roles'!J$51:J$67="D"))&" · I "&SUMPRODUCT((C$104:C$120="X")*('03_Matrice_Roles'!J$51:J$67="I")) -> D 0 · I 0 | D43: ="D "&SUMPRODUCT((D$104:D$120="X")*('03_Matrice_Roles'!J$51:J$67="D"))&" · I "&SUMPRODUCT((D$104:D$120="X")*('03_Matrice_Roles'!J$51:J$67="I")) -> D 2 · I 0 | E43: ="D "&SUMPRODUCT((E$104:E$120="X")*('03_Matrice_Roles'!J$51:J$67="D"))&" · I "&SUMPRODUCT((E$104:E$120="X")*('03_Matrice_Roles'!J$51:J$67="I")) -> D 3 · I 0 | F43: ="D "&SUMPRODUCT((F$104:F$120="X")*('03_Matrice_Roles'!J$51:J$67="D"))&" · I "&SUMPRODUCT((F$104:F$120="X")*('03_Matrice_Roles'!J$51:J$67="I")) -> D 0 · I 0 | G43: ="D "&SUMPRODUCT((G$104:G$120="X")*('03_Matrice_Roles'!J$51:J$67="D"))&" · I "&SUMPRODUCT((G$104:G$120="X")*('03_Matrice_Roles'!J$51:J$67="I")) -> D 0 · I 0 | H43: ="D "&SUMPRODUCT((H$104:H$120="X")*('03_Matrice_Roles'!J$51:J$67="D"))&" · I "&SUMPRODUCT((H$104:H$120="X")*('03_Matrice_Roles'!J$51:J$67="I")) -> D 0 · I 0 | I43: ="D "&SUMPRODUCT((I$104:I$120="X")*('03_Matrice_Roles'!J$51:J$67="D"))&" · I "&SUMPRODUCT((I$104:I$120="X")*('03_Matrice_Roles'!J$51:J$67="I")) -> D 3 · I 0 | J43: =COUNTA('03_Matrice_Roles'!J$51:J$67) -> 3
A45: 5. Constats (v1, d'après les codes R/S/V, D/I et X actuels — à relire si ces codes sont modifiés)
A46: Direction CNED : consultation seule, aucun accès à I4 (BET / CTC) ni à I5 (HSE) ; jamais destinataire (D) d'une alerte, seulement informée (8 alertes).
A47: Contractant : n'est responsable (R) d'aucun KPI, donc jamais « Pilote ». Il alimente I1, I2 et I7 (les trois KPI de planification terrain PP) et consulte le reste.
A48: Contrôleur budgétaire : pilote I3 (4 KPI) et I7 ; voit un seul KPI dans I1 et n'a aucun accès à I5.
A49: I5 · HSE : un seul KPI (QR8, phase Vision), aucune alerte reliée, un seul rôle pilote (BET). Interface à garder hors périmètre du pilote.
A50: I6 · Juridique : piloté par le MO et la PMO (via BU1, DL2, DL3, CO3, GV2) ; le BET et le contractant n'y font que consulter.
A51: BET : seulement 3 alertes visibles au total (dont 2 en tant que destinataire, AL09 et AL12, toutes dans I4 et I2).
A54: 6. Correspondance KPI → interface (à valider en équipe)
A55: X = le KPI est affiché ou saisi dans l'interface. Proposition de départ, à ajuster ; seules les croix en bleu sont des saisies. I7 affiche les 43 KPI (Catalogue KPI).
A56: KPI_ID | B56: Nom_KPI | C56: =$A$7 -> I1 · Terrain (mobile-first) | D56: =$A$8 -> I2 · MO local | E56: =$A$9 -> I3 · Financier | F56: =$A$10 -> I4 · BET / CTC | G56: =$A$11 -> I5 · HSE | H56: =$A$12 -> I6 · Juridique | I56: =$A$13 -> I7 · Pilotage CNED | J56: Importance | K56: Phase
A57: ='03_Matrice_Roles'!$A$4 -> AV1 | B57: ='03_Matrice_Roles'!$B$4 -> Avancement physique consolidé | C57: X | D57: X | F57: X | I57: X | J57: ='03_Matrice_Roles'!$C$4 -> [M] | K57: ='03_Matrice_Roles'!$D$4 -> MVP
A58: ='03_Matrice_Roles'!$A$5 -> AV2 | B58: ='03_Matrice_Roles'!$B$5 -> Indice d'avancement | D58: X | I58: X | J58: ='03_Matrice_Roles'!$C$5 -> [M] | K58: ='03_Matrice_Roles'!$D$5 -> MVP
A59: ='03_Matrice_Roles'!$A$6 -> AV3 | B59: ='03_Matrice_Roles'!$B$6 -> Cadence récente | C59: X | D59: X | F59: X | I59: X | J59: ='03_Matrice_Roles'!$C$6 -> [A] | K59: ='03_Matrice_Roles'!$D$6 -> V2
A60: ='03_Matrice_Roles'!$A$7 -> AV4 | B60: ='03_Matrice_Roles'!$B$7 -> Part non contractualisée | D60: X | I60: X | J60: ='03_Matrice_Roles'!$C$7 -> [A] | K60: ='03_Matrice_Roles'!$D$7 -> MVP
A61: ='03_Matrice_Roles'!$A$8 -> AV5 | B61: ='03_Matrice_Roles'!$B$8 -> Mise en service fonctionnelle | D61: X | I61: X | J61: ='03_Matrice_Roles'!$C$8 -> [S] | K61: ='03_Matrice_Roles'!$D$8 -> MVP
A62: ='03_Matrice_Roles'!$A$9 -> FI1 | B62: ='03_Matrice_Roles'!$B$9 -> Écart physique–financier | D62: X | E62: X | I62: X | J62: ='03_Matrice_Roles'!$C$9 -> [M] | K62: ='03_Matrice_Roles'!$D$9 -> MVP
A63: ='03_Matrice_Roles'!$A$10 -> FI2 | B63: ='03_Matrice_Roles'!$B$10 -> Couverture du reste à faire | E63: X | I63: X | J63: ='03_Matrice_Roles'!$C$10 -> [S] | K63: ='03_Matrice_Roles'!$D$10 -> V2
A64: ='03_Matrice_Roles'!$A$11 -> FI3 | B64: ='03_Matrice_Roles'!$B$11 -> Couverture des crédits de paiement | E64: X | I64: X | J64: ='03_Matrice_Roles'!$C$11 -> [S] | K64: ='03_Matrice_Roles'!$D$11 -> V2
A65: ='03_Matrice_Roles'!$A$12 -> FI4 | B65: ='03_Matrice_Roles'!$B$12 -> Dérive d'AE ajustée | E65: X | I65: X | J65: ='03_Matrice_Roles'!$C$12 -> [M] | K65: ='03_Matrice_Roles'!$D$12 -> MVP
A66: ='03_Matrice_Roles'!$A$13 -> FI5 | B66: ='03_Matrice_Roles'!$B$13 -> Réévaluations d'AE en attente | E66: X | I66: X | J66: ='03_Matrice_Roles'!$C$13 -> [M] | K66: ='03_Matrice_Roles'!$D$13 -> MVP
A67: ='03_Matrice_Roles'!$A$14 -> FI6 | B67: ='03_Matrice_Roles'!$B$14 -> Retard de paiement des situations | D67: X | E67: X | I67: X | J67: ='03_Matrice_Roles'!$C$14 -> [A] | K67: ='03_Matrice_Roles'!$D$14 -> V2
A68: ='03_Matrice_Roles'!$A$15 -> FI7 | B68: ='03_Matrice_Roles'!$B$15 -> Encours de situations | E68: X | I68: X | J68: ='03_Matrice_Roles'!$C$15 -> [A] | K68: ='03_Matrice_Roles'!$D$15 -> V2
A69: ='03_Matrice_Roles'!$A$16 -> DL1 | B69: ='03_Matrice_Roles'!$B$16 -> Consommation du délai en vigueur | D69: X | F69: X | I69: X | J69: ='03_Matrice_Roles'!$C$16 -> [M] | K69: ='03_Matrice_Roles'!$D$16 -> MVP
A70: ='03_Matrice_Roles'!$A$17 -> DL2 | B70: ='03_Matrice_Roles'!$B$17 -> Dérive de délai par avenants | D70: X | H70: X | I70: X | J70: ='03_Matrice_Roles'!$C$17 -> [M] | K70: ='03_Matrice_Roles'!$D$17 -> MVP
A71: ='03_Matrice_Roles'!$A$18 -> DL3 | B71: ='03_Matrice_Roles'!$B$18 -> Dépassement de la date contractuelle | D71: X | H71: X | I71: X | J71: ='03_Matrice_Roles'!$C$18 -> [M] | K71: ='03_Matrice_Roles'!$D$18 -> MVP
A72: ='03_Matrice_Roles'!$A$19 -> DL4 | B72: ='03_Matrice_Roles'!$B$19 -> Date d'achèvement prévisionnelle | D72: X | I72: X | J72: ='03_Matrice_Roles'!$C$19 -> [S] | K72: ='03_Matrice_Roles'!$D$19 -> V2
A73: ='03_Matrice_Roles'!$A$20 -> BU1 | B73: ='03_Matrice_Roles'!$B$20 -> Poids financier des avenants | D73: X | E73: X | H73: X | I73: X | J73: ='03_Matrice_Roles'!$C$20 -> [M] | K73: ='03_Matrice_Roles'!$D$20 -> MVP
A74: ='03_Matrice_Roles'!$A$21 -> BU2 | B74: ='03_Matrice_Roles'!$B$21 -> Nombre d'avenants cumulés | D74: X | F74: X | H74: X | I74: X | J74: ='03_Matrice_Roles'!$C$21 -> [A] | K74: ='03_Matrice_Roles'!$D$21 -> MVP
A75: ='03_Matrice_Roles'!$A$22 -> BU3 | B75: ='03_Matrice_Roles'!$B$22 -> Coût final prévisionnel | E75: X | I75: X | J75: ='03_Matrice_Roles'!$C$22 -> [S] | K75: ='03_Matrice_Roles'!$D$22 -> V2
A76: ='03_Matrice_Roles'!$A$23 -> QR1 | B76: ='03_Matrice_Roles'!$B$23 -> Taux de libération des emprises | C76: X | D76: X | I76: X | J76: ='03_Matrice_Roles'!$C$23 -> [M] | K76: ='03_Matrice_Roles'!$D$23 -> MVP
A77: ='03_Matrice_Roles'!$A$24 -> QR2 | B77: ='03_Matrice_Roles'!$B$24 -> Interférences réseaux traitées | C77: X | D77: X | I77: X | J77: ='03_Matrice_Roles'!$C$24 -> [M] | K77: ='03_Matrice_Roles'!$D$24 -> MVP
A78: ='03_Matrice_Roles'!$A$25 -> QR3 | B78: ='03_Matrice_Roles'!$B$25 -> Âge des blocages ouverts | D78: X | I78: X | J78: ='03_Matrice_Roles'!$C$25 -> [M] | K78: ='03_Matrice_Roles'!$D$25 -> MVP
A79: ='03_Matrice_Roles'!$A$26 -> QR4 | B79: ='03_Matrice_Roles'!$B$26 -> Temps perdu à l'arrêt | C79: X | D79: X | I79: X | J79: ='03_Matrice_Roles'!$C$26 -> [M] | K79: ='03_Matrice_Roles'!$D$26 -> MVP
A80: ='03_Matrice_Roles'!$A$27 -> QR5 | B80: ='03_Matrice_Roles'!$B$27 -> Aléas non prévus ouverts | C80: X | D80: X | F80: X | I80: X | J80: ='03_Matrice_Roles'!$C$27 -> [A] | K80: ='03_Matrice_Roles'!$D$27 -> V2
A81: ='03_Matrice_Roles'!$A$28 -> QR6 | B81: ='03_Matrice_Roles'!$B$28 -> Modification de consistance en cours | D81: X | F81: X | I81: X | J81: ='03_Matrice_Roles'!$C$28 -> [A] | K81: ='03_Matrice_Roles'!$D$28 -> V2
A82: ='03_Matrice_Roles'!$A$29 -> QR7 | B82: ='03_Matrice_Roles'!$B$29 -> Non-conformité critique la plus ancienne | F82: X | I82: X | J82: ='03_Matrice_Roles'!$C$29 -> [A] | K82: ='03_Matrice_Roles'!$D$29 -> V2
A83: ='03_Matrice_Roles'!$A$30 -> QR8 | B83: ='03_Matrice_Roles'!$B$30 -> Incidents HSE graves | F83: X | G83: X | I83: X | J83: ='03_Matrice_Roles'!$C$30 -> [A] | K83: ='03_Matrice_Roles'!$D$30 -> Vision
A84: ='03_Matrice_Roles'!$A$31 -> DO1 | B84: ='03_Matrice_Roles'!$B$31 -> Fraîcheur des données | I84: X | J84: ='03_Matrice_Roles'!$C$31 -> [M] | K84: ='03_Matrice_Roles'!$D$31 -> MVP
A85: ='03_Matrice_Roles'!$A$32 -> DO2 | B85: ='03_Matrice_Roles'!$B$32 -> Complétude | I85: X | J85: ='03_Matrice_Roles'!$C$32 -> [M] | K85: ='03_Matrice_Roles'!$D$32 -> MVP
A86: ='03_Matrice_Roles'!$A$33 -> DO3 | B86: ='03_Matrice_Roles'!$B$33 -> Cohérence | I86: X | J86: ='03_Matrice_Roles'!$C$33 -> [M] | K86: ='03_Matrice_Roles'!$D$33 -> MVP
A87: ='03_Matrice_Roles'!$A$34 -> PP1 | B87: ='03_Matrice_Roles'!$B$34 -> Fiabilité du planning hebdomadaire | C87: X | D87: X | I87: X | J87: ='03_Matrice_Roles'!$C$34 -> [A] | K87: ='03_Matrice_Roles'!$D$34 -> V2
A88: ='03_Matrice_Roles'!$A$35 -> PP2 | B88: ='03_Matrice_Roles'!$B$35 -> Mobilisation effective | C88: X | D88: X | I88: X | J88: ='03_Matrice_Roles'!$C$35 -> [A] | K88: ='03_Matrice_Roles'!$D$35 -> V2
A89: ='03_Matrice_Roles'!$A$36 -> PP3 | B89: ='03_Matrice_Roles'!$B$36 -> Causes de non-réalisation externes | C89: X | D89: X | I89: X | J89: ='03_Matrice_Roles'!$C$36 -> [A] | K89: ='03_Matrice_Roles'!$D$36 -> V2
A90: ='03_Matrice_Roles'!$A$37 -> CO1 | B90: ='03_Matrice_Roles'!$B$37 -> Santé du contractant (0–100) | I90: X | J90: ='03_Matrice_Roles'!$C$37 -> [S] | K90: ='03_Matrice_Roles'!$D$37 -> MVP
A91: ='03_Matrice_Roles'!$A$38 -> CO2 | B91: ='03_Matrice_Roles'!$B$38 -> Concentration par contractant | I91: X | J91: ='03_Matrice_Roles'!$C$38 -> [S] | K91: ='03_Matrice_Roles'!$D$38 -> V2
A92: ='03_Matrice_Roles'!$A$39 -> CO3 | B92: ='03_Matrice_Roles'!$B$39 -> Part en parachèvement après résiliation | H92: X | I92: X | J92: ='03_Matrice_Roles'!$C$39 -> [S] | K92: ='03_Matrice_Roles'!$D$39 -> MVP
A93: ='03_Matrice_Roles'!$A$40 -> CO4 | B93: ='03_Matrice_Roles'!$B$40 -> Projets en retard important | I93: X | J93: ='03_Matrice_Roles'!$C$40 -> [M] | K93: ='03_Matrice_Roles'!$D$40 -> MVP
A94: ='03_Matrice_Roles'!$A$41 -> CO5 | B94: ='03_Matrice_Roles'!$B$41 -> Projets à l'arrêt | I94: X | J94: ='03_Matrice_Roles'!$C$41 -> [M] | K94: ='03_Matrice_Roles'!$D$41 -> MVP
A95: ='03_Matrice_Roles'!$A$42 -> CO6 | B95: ='03_Matrice_Roles'!$B$42 -> Score de santé du portefeuille | I95: X | J95: ='03_Matrice_Roles'!$C$42 -> [S] | K95: ='03_Matrice_Roles'!$D$42 -> V2
A96: ='03_Matrice_Roles'!$A$43 -> GV1 | B96: ='03_Matrice_Roles'!$B$43 -> Blocages avec responsable et échéance | I96: X | J96: ='03_Matrice_Roles'!$C$43 -> [M] | K96: ='03_Matrice_Roles'!$D$43 -> MVP
A97: ='03_Matrice_Roles'!$A$44 -> GV2 | B97: ='03_Matrice_Roles'!$B$44 -> Avenants en attente de visa (CSM) | D97: X | E97: X | H97: X | I97: X | J97: ='03_Matrice_Roles'!$C$44 -> [M] | K97: ='03_Matrice_Roles'!$D$44 -> MVP
A98: ='03_Matrice_Roles'!$A$45 -> GV3 | B98: ='03_Matrice_Roles'!$B$45 -> Arbitrages échus | I98: X | J98: ='03_Matrice_Roles'!$C$45 -> [A] | K98: ='03_Matrice_Roles'!$D$45 -> V2
A99: ='03_Matrice_Roles'!$A$46 -> GV4 | B99: ='03_Matrice_Roles'!$B$46 -> Réceptions en attente | D99: X | F99: X | I99: X | J99: ='03_Matrice_Roles'!$C$46 -> [A] | K99: ='03_Matrice_Roles'!$D$46 -> MVP
A101: 7. Correspondance alerte → interface (à valider en équipe)
A102: X = l'alerte est notifiée dans l'interface. Aucune règle d'alerte n'existe aujourd'hui pour I5 · HSE (QR8 n'est relié à aucune règle).
A103: Regle_ID | B103: Nom | C103: =$A$7 -> I1 · Terrain (mobile-first) | D103: =$A$8 -> I2 · MO local | E103: =$A$9 -> I3 · Financier | F103: =$A$10 -> I4 · BET / CTC | G103: =$A$11 -> I5 · HSE | H103: =$A$12 -> I6 · Juridique | I103: =$A$13 -> I7 · Pilotage CNED | J103: Importance | K103: Niveau
A104: ='03_Matrice_Roles'!$A$51 -> AL01 | B104: ='03_Matrice_Roles'!$B$51 -> Avant-coureur d'abandon | D104: X | E104: X | I104: X | J104: ='03_Matrice_Roles'!$C$51 -> [A] | K104: ='03_Matrice_Roles'!$D$51 -> ROUGE
A105: ='03_Matrice_Roles'!$A$52 -> AL02 | B105: ='03_Matrice_Roles'!$B$52 -> Emprise bloquée critique | C105: X | D105: X | I105: X | J105: ='03_Matrice_Roles'!$C$52 -> [M] | K105: ='03_Matrice_Roles'!$D$52 -> ROUGE
A106: ='03_Matrice_Roles'!$A$53 -> AL03 | B106: ='03_Matrice_Roles'!$B$53 -> Étranglement financier | E106: X | I106: X | J106: ='03_Matrice_Roles'!$C$53 -> [S] | K106: ='03_Matrice_Roles'!$D$53 -> ROUGE
A107: ='03_Matrice_Roles'!$A$54 -> AL04 | B107: ='03_Matrice_Roles'!$B$54 -> Dégradation contractant | D107: X | I107: X | J107: ='03_Matrice_Roles'!$C$54 -> [A] | K107: ='03_Matrice_Roles'!$D$54 -> ORANGE
A108: ='03_Matrice_Roles'!$A$55 -> AL05 | B108: ='03_Matrice_Roles'!$B$55 -> Déblocage critique qui approche | C108: X | D108: X | I108: X | J108: ='03_Matrice_Roles'!$C$55 -> [A] | K108: ='03_Matrice_Roles'!$D$55 -> ORANGE
...
